Workbook
Name PolicyID: 'Control'!$C$4
Name ScenID: 'Control'!$C$5
Name T0: 'Control'!$C$6
Name BatchLimit: 'Control'!$C$10
Name BatchTol: 'Control'!$C$11
Name MP_ID: Policy_Data!$A$4:$A$303
Name MP_Product: Policy_Data!$B$4:$B$303
Name MP_PolType: Policy_Data!$C$4:$C$303
Name MP_Gen: Policy_Data!$D$4:$D$303
Name MP_Sex: Policy_Data!$E$4:$E$303
Name MP_IssueAge: Policy_Data!$F$4:$F$303
Name MP_PremFreq: Policy_Data!$G$4:$G$303
Name MP_Term: Policy_Data!$H$4:$H$303
Name MP_Count: Policy_Data!$I$4:$I$303
Name MP_SumAssured: Policy_Data!$J$4:$J$303
Name AsmpKeys: Basis_Lookup!$F$4:$F$42
Name AsmpVals: Basis_Lookup!$E$4:$E$42
Name SpecKeys: Basis_Lookup!$M$4:$M$68
Name SpecVals: Basis_Lookup!$L$4:$L$68
Name AsmpTblGrid: Basis_Tables!$B$4:$I$23
Name AsmpTblNames: Basis_Tables!$B$2:$I$2
Name FactorKeys: Basis_Tables!$K$4:$K$18
Name FactorVals: Basis_Tables!$L$4:$L$18
Name MortGrid: Mortality!$B$4:$M$134
Name MortAges: Mortality!$A$4:$A$134
Name ScenGrid: Scenarios!$B$4:$K$154
Name Product: 'Policy_Basis'!$C$4
Name PolicyType: 'Policy_Basis'!$C$5
Name Gen: 'Policy_Basis'!$C$6
Name Sex: 'Policy_Basis'!$C$7
Name IssueAge: 'Policy_Basis'!$C$8
Name PremFreq: 'Policy_Basis'!$C$9
Name PolicyTerm: 'Policy_Basis'!$C$10
Name PolicyCount: 'Policy_Basis'!$C$11
Name SumAssured: 'Policy_Basis'!$C$12
Name BaseMortTable: 'Policy_Basis'!$C$16
Name MortFactorTable: 'Policy_Basis'!$C$17
Name SurrTable: 'Policy_Basis'!$C$18
Name CnsmpTax: 'Policy_Basis'!$C$19
Name CommInitPrem: 'Policy_Basis'!$C$20
Name CommRenPrem: 'Policy_Basis'!$C$21
Name CommRenTerm: 'Policy_Basis'!$C$22
Name ExpsAcqAnnPrem: 'Policy_Basis'!$C$23
Name ExpsAcqPol: 'Policy_Basis'!$C$24
Name ExpsAcqSA: 'Policy_Basis'!$C$25
Name ExpsMaintAnnPrem: 'Policy_Basis'!$C$26
Name ExpsMaintPol: 'Policy_Basis'!$C$27
Name ExpsMaintSA: 'Policy_Basis'!$C$28
Name InflRate: 'Policy_Basis'!$C$29
Name IntRatePrem: 'Policy_Basis'!$C$30
Name TableIDPrem: 'Policy_Basis'!$C$31
Name LoadAcqP1: 'Policy_Basis'!$C$32
Name LoadAcqP2: 'Policy_Basis'!$C$33
Name LoadMaintPremP1: 'Policy_Basis'!$C$34
Name LoadMaintPremP2: 'Policy_Basis'!$C$35
Name LoadMaintSA: 'Policy_Basis'!$C$36
Name LoadMaintSA2: 'Policy_Basis'!$C$37
Name SurrP1: 'Policy_Basis'!$C$38
Name SurrP2: 'Policy_Basis'!$C$39
Name BaseMortCol: 'Policy_Basis'!$C$43

Sheet Cover
B2: Solvency2 — Life Underwriting Risk SCR (Standard Formula)
B3: Life SCR for a selected policy: base and stressed liability projections aggregated through the standard-formula correlation matrix
B5: Purpose | C5: Calculates the Solvency II life underwriting risk SCR for the policy selected on the Control sheet. The annual liability cashflow engine is projected on seven scenario sheets — the base basis plus mortality, longevity, expense and three lapse stresses — and the SCR sheet aggregates the resulting risk charges with the standard-formula correlation matrix. The workbook is a formula-for-formula replication of the open-source lifelib model 'solvency2' (MIT licence), verified cell-by-cell against it.
B6: Method | C6: SCR_life = sqrt( sum_ij Corr(i,j) * Life_i * Life_j ). Each Life charge is max(NAV_base − NAV_stressed, 0), where NAV is the present value of net liability cashflows at time t0 (assets assumed insensitive to life stresses, as in lifelib). Lapse risk takes the worst of the up / down / mass shocks.
B7: Engine | C7: Net level premium engine: gross premium rates and reserves from PREM-basis commutation functions (Commutation sheet); decrements from the base mortality table, mortality factor and surrender rate tables; expense and commission assumptions resolved per product via the Basis_Lookup cascade.
B8: Stresses | C8: Scenario sheets share one engine layout; each carries a parameter block (risk, shock, factors from the Factors table) that reproduces the lifelib Override spaces: mortality/longevity rate factors from t0, lapse up/down rate shocks with limits, one-off mass lapse at t0, expense level and inflation shocks. Disability, revision and catastrophe risks have no lifelib override (stressed projection would equal base), so their charges are zero.
B9: Scope | C9: Only the cells lifelib evaluates for SCR_life() are replicated. Statutory reserve roll-forward and profit cells (ChangeRsrv, ProfitBefTax, InvstIncome, AccumCF) and the VAL rate basis lie outside that subgraph.
B10: Reconciliation | C10: The RunAllPolicies macro (Batch_Results) computes the SCR and its risk decomposition for every one of the 300 policies and reconciles them against the lifelib values on Lifelib_Reference.
B11: Source model | C11: lifelib solvency2 — https://lifelib.io (MIT licence)
B12: Verification | C12: verification/verify_solvency2.py compares every mapped cell against the Python model for deep profiles across products, sexes, t0 and scenarios; see the Checks sheet for in-workbook consistency tests.
B14: Version control
B15: Version | C15: 0.2.0
B16: Date | C16: 2026-07-14
B17: Prepared by | C17: XL Marinade project
B18: Review status | C18: Verified against lifelib; adversarial actuarial audit remediated (see verification/reports)
B20: Sheet index
B21: Control | C21: Run selection (policy, scenario, t0) and batch settings
B22: Policy_Basis | C22: Selected policy, resolved lookups, premium/reserve rates
B23: Policy_Data | C23: Policy file — 300 policies (input data)
B24: Basis_Lookup | C24: Assumption and product-spec lookup tables (input data)
B25: Basis_Tables | C25: Year-indexed assumption tables and shock factors (input data)
B26: Mortality | C26: Mortality tables qx by age, 6 tables x M/F (input data)
B27: Scenarios | C27: Discount rate paths by scenario (input data)
B28: Commutation | C28: PREM-basis commutation functions lx/Dx/Cx/Nx/Mx
B29: Policy_Sched | C29: Per-policy schedule shared by all stress projections
B30: Proj_Base … Proj_LapseMass | C30: Liability projections — base + 6 life stresses
B31: SCR | C31: NAVs, risk charges, correlation matrix, SCR aggregation
B32: Summary | C32: Run details, SCR decomposition, risk radar
... B35: Batch_Results | C35: All-policies batch reconciliation vs lifelib (macro)
B37: Conventions
B38: Blue — hardcoded input
B39: Black — calculated on this sheet
B40: Green — link from another sheet

Sheet Control
B2: Run selection
B3: Item | C3: Value | D3: Notes / lifelib parameter
B4: Policy ID | C4: 1 | D4: PolicyID — choose 1 to 300
B5: Economic scenario | C5: 1 | D5: ScenID — discount rate path, choose 1 to 10
B6: Valuation time t0 (years) | C6: 0 | D6: t0 — stresses apply from t0; NAV is PV of net cashflows at t0
B8: Batch run (RunAllPolicies macro)
B9: Item | C9: Value | D9: Notes
B10: Policies to run (blank = all) | D10: Cap for quick test runs; leave blank to run all 300 policies
B11: Reconciliation tolerance (relative) | C11: 1e-06 | D11: A value reconciles when |workbook − lifelib| ≤ tol × max(1, |lifelib|)
B13: The batch runs at t0 = 0, scenario 1 (the Lifelib_Reference basis) and restores the run selection afterwards.

Sheet Policy_Data
A1: Policy data — 300 policies (lifelib Input.PolicyData; unused attributes Channel/Duration/PaymentMode/MaxPolicyTerm omitted)
A2: policy_id | B2: Product | C2: PolicyType | D2: Gen | E2: Sex | F2: IssueAge | G2: PremFreq | H2: PolicyTerm | I2: PolicyCount | J2: SumAssured
A3: PolicyID | B3: Product | C3: PolicyType | D3: Gen | E3: Sex | F3: IssueAge | G3: PremFreq | H3: PolicyTerm | I3: PolicyCount | J3: SumAssured
A4: 1 | B4: TERM | C4: 1 | D4: 1 | E4: M | F4: 30 | G4: 12 | H4: 15 | I4: 1 | J4: 1000000
A5: 2 | B5: TERM | C5: 1 | D5: 1 | E5: F | F5: 30 | G5: 12 | H5: 15 | I5: 1 | J5: 1000000
A6: 3 | B6: TERM | C6: 1 | D6: 1 | E6: M | F6: 31 | G6: 12 | H6: 15 | I6: 1 | J6: 1000000
A7: 4 | B7: TERM | C7: 1 | D7: 1 | E7: F | F7: 31 | G7: 12 | H7: 15 | I7: 1 | J7: 1000000
A8: 5 | B8: TERM | C8: 1 | D8: 1 | E8: M | F8: 32 | G8: 12 | H8: 15 | I8: 1 | J8: 1000000
A9: 6 | B9: TERM | C9: 1 | D9: 1 | E9: F | F9: 32 | G9: 12 | H9: 15 | I9: 1 | J9: 1000000
A10: 7 | B10: TERM | C10: 1 | D10: 1 | E10: M | F10: 33 | G10: 12 | H10: 15 | I10: 1 | J10: 1000000
A11: 8 | B11: TERM | C11: 1 | D11: 1 | E11: F | F11: 33 | G11: 12 | H11: 15 | I11: 1 | J11: 1000000
A12: 9 | B12: TERM | C12: 1 | D12: 1 | E12: M | F12: 34 | G12: 12 | H12: 15 | I12: 1 | J12: 1000000
A13: 10 | B13: TERM | C13: 1 | D13: 1 | E13: F | F13: 34 | G13: 12 | H13: 15 | I13: 1 | J13: 1000000
A14: 11 | B14: TERM | C14: 1 | D14: 1 | E14: M | F14: 35 | G14: 12 | H14: 15 | I14: 1 | J14: 1000000
A15: 12 | B15: TERM | C15: 1 | D15: 1 | E15: F | F15: 35 | G15: 12 | H15: 15 | I15: 1 | J15: 1000000
... A303: 300 | B303: ENDW | C303: 1 | D303: 1 | E303: F | F303: 79 | G303: 12 | H303: 10 | I303: 1 | J303: 1000000

Sheet Basis_Lookup
A1: Assumption and product-spec lookup tables (rows with empty values omitted — modelx match() skips them). Lookup key = item|product|policy_type|generation; the Policy_Basis cascade tries masks from most to least specific.
A2: item | B2: prod | C2: polt | D2: gen | E2: value | F2: lookup key | H2: item | I2: prod | J2: polt | K2: gen | L2: value | M2: lookup key
E3: Assumption | L3: ProductSpec
A4: BaseMort | B4: TERM | C4: 1 | E4: 3 | F4: =A4&"|"&B4&"|"&C4&"|"&D4 | H4: LoadAcqSAParam1 | I4: TERM | L4: 0 | M4: =H4&"|"&I4&"|"&J4&"|"&K4
A5: BaseMort | B5: TERM | C5: 2 | E5: 6 | F5: =A5&"|"&B5&"|"&C5&"|"&D5 | H5: LoadAcqSAParam1 | I5: WL | L5: 0.02 | M5: =H5&"|"&I5&"|"&J5&"|"&K5
A6: BaseMort | B6: WL | C6: 1 | E6: 3 | F6: =A6&"|"&B6&"|"&C6&"|"&D6 | H6: LoadAcqSAParam1 | I6: ENDW | L6: 0.02 | M6: =H6&"|"&I6&"|"&J6&"|"&K6
A7: BaseMort | B7: WL | C7: 2 | E7: 6 | F7: =A7&"|"&B7&"|"&C7&"|"&D7 | H7: LoadAcqSAParam2 | I7: TERM | L7: 0 | M7: =H7&"|"&I7&"|"&J7&"|"&K7
A8: BaseMort | B8: ENDW | C8: 1 | E8: 3 | F8: =A8&"|"&B8&"|"&C8&"|"&D8 | H8: LoadAcqSAParam2 | I8: WL | L8: 0.01 | M8: =H8&"|"&I8&"|"&J8&"|"&K8
A9: BaseMort | B9: ENDW | C9: 2 | E9: 3 | F9: =A9&"|"&B9&"|"&C9&"|"&D9 | H9: LoadAcqSAParam2 | I9: ENDW | L9: 0.01 | M9: =H9&"|"&I9&"|"&J9&"|"&K9
A10: MortFactor | B10: TERM | E10: MortAsmp2 | F10: =A10&"|"&B10&"|"&C10&"|"&D10 | H10: LoadMaintSA | I10: TERM | L10: 0.002 | M10: =H10&"|"&I10&"|"&J10&"|"&K10
A11: MortFactor | B11: WL | E11: MortAsmp2 | F11: =A11&"|"&B11&"|"&C11&"|"&D11 | H11: LoadMaintSA | I11: TERM | K11: 1 | L11: 0.002 | M11: =H11&"|"&I11&"|"&J11&"|"&K11
A12: MortFactor | B12: ENDW | E12: MortAsmp2 | F12: =A12&"|"&B12&"|"&C12&"|"&D12 | H12: LoadMaintSA | I12: TERM | K12: 2 | L12: 0.002 | M12: =H12&"|"&I12&"|"&J12&"|"&K12
A13: Surrender | B13: TERM | E13: LapseRate1 | F13: =A13&"|"&B13&"|"&C13&"|"&D13 | H13: LoadMaintSA | I13: WL | K13: 1 | L13: 0.002 | M13: =H13&"|"&I13&"|"&J13&"|"&K13
A14: Surrender | B14: WL | E14: LapseRate1 | F14: =A14&"|"&B14&"|"&C14&"|"&D14 | H14: LoadMaintSA | I14: ENDW | L14: 0.002 | M14: =H14&"|"&I14&"|"&J14&"|"&K14
A15: Surrender | B15: ENDW | E15: LapseRate1 | F15: =A15&"|"&B15&"|"&C15&"|"&D15 | H15: LoadMaintSA | I15: ENDW | J15: 1 | L15: 0.4 | M15: =H15&"|"&I15&"|"&J15&"|"&K15
A16: Renewal | B16: TERM | E16: 0.6 | F16: =A16&"|"&B16&"|"&C16&"|"&D16 | H16: LoadMaintSA | I16: ENDW | J16: 2 | L16: 0.5 | M16: =H16&"|"&I16&"|"&J16&"|"&K16
A17: InvstRet | B17: TERM | E17: 0.005 | F17: =A17&"|"&B17&"|"&C17&"|"&D17 | H17: LoadMaintSA | I17: ENDW | J17: 3 | L17: 0.6 | M17: =H17&"|"&I17&"|"&J17&"|"&K17
A18: InvstRet | B18: WL | E18: 0.005 | F18: =A18&"|"&B18&"|"&C18&"|"&D18 | H18: LoadMaintSA | I18: ENDW | J18: 4 | L18: 0.6 | M18: =H18&"|"&I18&"|"&J18&"|"&K18
A19: InvstRet | B19: ENDW | E19: 0.005 | F19: =A19&"|"&B19&"|"&C19&"|"&D19 | H19: LoadMaintSA2 | L19: 0.001 | M19: =H19&"|"&I19&"|"&J19&"|"&K19
A20: CommInitPrem | B20: TERM | E20: 0.2 | F20: =A20&"|"&B20&"|"&C20&"|"&D20 | H20: LoadMaintSA2 | I20: TERM | J20: 1 | L20: 0 | M20: =H20&"|"&I20&"|"&J20&"|"&K20
A21: CommInitPrem | B21: WL | E21: 0.5 | F21: =A21&"|"&B21&"|"&C21&"|"&D21 | H21: LoadMaintSA2 | I21: TERM | J21: 2 | L21: 0 | M21: =H21&"|"&I21&"|"&J21&"|"&K21
A22: CommInitPrem | B22: ENDW | E22: 0.5 | F22: =A22&"|"&B22&"|"&C22&"|"&D22 | H22: LoadMaintSA2 | I22: WL | L22: 0.002 | M22: =H22&"|"&I22&"|"&J22&"|"&K22
A23: CommRenPrem | B23: TERM | E23: 0.05 | F23: =A23&"|"&B23&"|"&C23&"|"&D23 | H23: LoadMaintSA2 | I23: ENDW | L23: 0.002 | M23: =H23&"|"&I23&"|"&J23&"|"&K23
A24: CommRenPrem | B24: WL | E24: 0.05 | F24: =A24&"|"&B24&"|"&C24&"|"&D24 | H24: LoadMaintSA2 | I24: ENDW | J24: 1 | L24: 0.3 | M24: =H24&"|"&I24&"|"&J24&"|"&K24
A25: CommRenPrem | B25: ENDW | E25: 0.05 | F25: =A25&"|"&B25&"|"&C25&"|"&D25 | H25: LoadMaintSA2 | I25: ENDW | J25: 2 | L25: 0.4 | M25: =H25&"|"&I25&"|"&J25&"|"&K25
A26: CommRenTerm | B26: TERM | E26: 5 | F26: =A26&"|"&B26&"|"&C26&"|"&D26 | H26: LoadMaintSA2 | I26: ENDW | J26: 3 | L26: 0.5 | M26: =H26&"|"&I26&"|"&J26&"|"&K26
A27: CommRenTerm | B27: WL | E27: 5 | F27: =A27&"|"&B27&"|"&C27&"|"&D27 | H27: LoadMaintSA2 | I27: ENDW | J27: 4 | L27: 0.6 | M27: =H27&"|"&I27&"|"&J27&"|"&K27
A28: CommRenTerm | B28: ENDW | E28: 5 | F28: =A28&"|"&B28&"|"&C28&"|"&D28 | H28: LoadMaintPremParam1 | I28: TERM | L28: 0.1 | M28: =H28&"|"&I28&"|"&J28&"|"&K28
A29: ExpsAcqSA | B29: TERM | E29: 0.003 | F29: =A29&"|"&B29&"|"&C29&"|"&D29 | H29: LoadMaintPremParam1 | I29: WL | L29: 0.03 | M29: =H29&"|"&I29&"|"&J29&"|"&K29
A30: ExpsAcqSA | B30: WL | E30: 0 | F30: =A30&"|"&B30&"|"&C30&"|"&D30 | H30: LoadMaintPremParam1 | I30: ENDW | L30: 0.03 | M30: =H30&"|"&I30&"|"&J30&"|"&K30
A31: ExpsAcqSA | B31: ENDW | E31: 0 | F31: =A31&"|"&B31&"|"&C31&"|"&D31 | H31: LoadMaintPremParam2 | L31: 10 | M31: =H31&"|"&I31&"|"&J31&"|"&K31
A32: ExpsAcqAnnPrem | B32: TERM | E32: 0.1 | F32: =A32&"|"&B32&"|"&C32&"|"&D32 | H32: SurrChargeParam1 | I32: TERM | L32: 0 | M32: =H32&"|"&I32&"|"&J32&"|"&K32
A33: ExpsAcqAnnPrem | B33: WL | E33: 0.1 | F33: =A33&"|"&B33&"|"&C33&"|"&D33 | H33: SurrChargeParam1 | I33: WL | L33: 0.01 | M33: =H33&"|"&I33&"|"&J33&"|"&K33
A34: ExpsAcqAnnPrem | B34: ENDW | E34: 0.1 | F34: =A34&"|"&B34&"|"&C34&"|"&D34 | H34: SurrChargeParam1 | I34: ENDW | L34: 0.005 | M34: =H34&"|"&I34&"|"&J34&"|"&K34
A35: ExpsAcqPol | B35: TERM | E35: 0 | F35: =A35&"|"&B35&"|"&C35&"|"&D35 | H35: SurrChargeParam2 | I35: TERM | L35: 0 | M35: =H35&"|"&I35&"|"&J35&"|"&K35
A36: ExpsAcqPol | B36: WL | E36: 10000 | F36: =A36&"|"&B36&"|"&C36&"|"&D36 | H36: SurrChargeParam2 | I36: WL | L36: 0.005 | M36: =H36&"|"&I36&"|"&J36&"|"&K36
A37: ExpsAcqPol | B37: ENDW | E37: 10000 | F37: =A37&"|"&B37&"|"&C37&"|"&D37 | H37: SurrChargeParam2 | I37: ENDW | L37: 0.01 | M37: =H37&"|"&I37&"|"&J37&"|"&K37
A38: ExpsMaintSA | E38: 0 | F38: =A38&"|"&B38&"|"&C38&"|"&D38 | H38: MortTablePrem | I38: TERM | K38: 1 | L38: 3 | M38: =H38&"|"&I38&"|"&J38&"|"&K38
A39: ExpsMaintPrem | E39: 0.01 | F39: =A39&"|"&B39&"|"&C39&"|"&D39 | H39: MortTablePrem | I39: TERM | K39: 2 | L39: 3 | M39: =H39&"|"&I39&"|"&J39&"|"&K39
A40: ExpsMaintPol | E40: 1000 | F40: =A40&"|"&B40&"|"&C40&"|"&D40 | H40: MortTablePrem | I40: WL | K40: 1 | L40: 3 | M40: =H40&"|"&I40&"|"&J40&"|"&K40
A41: InflRate | E41: 0 | F41: =A41&"|"&B41&"|"&C41&"|"&D41 | H41: MortTablePrem | I41: ENDW | L41: 3 | M41: =H41&"|"&I41&"|"&J41&"|"&K41
A42: CnsmpTax | E42: 0 | F42: =A42&"|"&B42&"|"&C42&"|"&D42 | H42: MortTableVal | I42: TERM | K42: 1 | L42: 1 | M42: =H42&"|"&I42&"|"&J42&"|"&K42
H43: MortTableVal | I43: TERM | K43: 2 | L43: 1 | M43: =H43&"|"&I43&"|"&J43&"|"&K43
H44: MortTableVal | I44: WL | K44: 1 | L44: 1 | M44: =H44&"|"&I44&"|"&J44&"|"&K44
H45: MortTableVal | I45: ENDW | L45: 1 | M45: =H45&"|"&I45&"|"&J45&"|"&K45
H46: IntRatePrem | I46: TERM | L46: 0.015 | M46: =H46&"|"&I46&"|"&J46&"|"&K46
H47: IntRatePrem | I47: TERM | K47: 1 | L47: 0.03 | M47: =H47&"|"&I47&"|"&J47&"|"&K47
H48: IntRatePrem | I48: TERM | K48: 2 | L48: 0.02 | M48: =H48&"|"&I48&"|"&J48&"|"&K48
H49: IntRatePrem | I49: WL | K49: 1 | L49: 0.015 | M49: =H49&"|"&I49&"|"&J49&"|"&K49
H50: IntRatePrem | I50: ENDW | L50: 0.03 | M50: =H50&"|"&I50&"|"&J50&"|"&K50
H51: IntRateVal | K51: 1 | L51: 0.015 | M51: =H51&"|"&I51&"|"&J51&"|"&K51
H52: IntRateVal | K52: 2 | L52: 0.01 | M52: =H52&"|"&I52&"|"&J52&"|"&K52
H53: LapseRatePrem | I53: TERM | L53: 0.015 | M53: =H53&"|"&I53&"|"&J53&"|"&K53
H54: LapseRateVal | I54: TERM | L54: 0.01 | M54: =H54&"|"&I54&"|"&J54&"|"&K54
H55: Hsx | I55: TERM | J55: 1 | L55: 6 | M55: =H55&"|"&I55&"|"&J55&"|"&K55
H56: Hsx | I56: TERM | J56: 2 | L56: 7 | M56: =H56&"|"&I56&"|"&J56&"|"&K56
H57: Hsx | I57: ENDW | L57: 1 | M57: =H57&"|"&I57&"|"&J57&"|"&K57
H58: Tsx | I58: TERM | J58: 1 | L58: 7 | M58: =H58&"|"&I58&"|"&J58&"|"&K58
H59: Tsx | I59: TERM | J59: 2 | L59: 7 | M59: =H59&"|"&I59&"|"&J59&"|"&K59
H60: Tsx | I60: ENDW | J60: 1 | L60: 2 | M60: =H60&"|"&I60&"|"&J60&"|"&K60
H61: Tsx | I61: ENDW | J61: 2 | L61: 3 | M61: =H61&"|"&I61&"|"&J61&"|"&K61
H62: Tsx | I62: ENDW | J62: 3 | L62: 4 | M62: =H62&"|"&I62&"|"&J62&"|"&K62
H63: Tsx | I63: ENDW | J63: 4 | L63: 5 | M63: =H63&"|"&I63&"|"&J63&"|"&K63
H64: Hax | I64: ENDW | L64: 9 | M64: =H64&"|"&I64&"|"&J64&"|"&K64
H65: Tax | I65: ENDW | J65: 1 | L65: 10 | M65: =H65&"|"&I65&"|"&J65&"|"&K65
H66: Tax | I66: ENDW | J66: 2 | L66: 11 | M66: =H66&"|"&I66&"|"&J66&"|"&K66
H67: Tax | I67: ENDW | J67: 3 | L67: 12 | M67: =H67&"|"&I67&"|"&J67&"|"&K67
H68: Tax | I68: ENDW | J68: 4 | L68: 13 | M68: =H68&"|"&I68&"|"&J68&"|"&K68

Sheet Basis_Tables
A1: Assumption tables by policy year (values carry forward beyond year 19, as in lifelib), and the standard-formula shock factors
A2: year | B2: LapseRate1 | C2: Morb1 | D2: Morb2 | E2: Morb3 | F2: Morb4 | G2: Morb5 | H2: MortAsmp1 | I2: MortAsmp2 | K2: shock factor key | L2: value
A3: y | B3: AssumptionTables | K3: FactorData
A4: 0 | B4: 0.08 | C4: 0.3 | D4: 0.3 | E4: 0.3 | F4: 0.3 | G4: 0.7 | H4: 0.4 | I4: 0.7 | K4: cat||| | L4: 0.0015
A5: 1 | B5: 0.08 | C5: 0.4 | D5: 0.4 | E5: 0.4 | F5: 0.4 | G5: 0.7 | H5: 0.5 | I5: 0.7 | K5: disab|||first | L5: 0.35
A6: 2 | B6: 0.08 | C6: 0.5 | D6: 0.5 | E6: 0.5 | F6: 0.5 | G6: 0.7 | H6: 0.6 | I6: 0.7 | K6: disab|||recovery | L6: 0.2
A7: 3 | B7: 0.08 | C7: 0.6 | D7: 0.6 | E7: 0.6 | F7: 0.6 | G7: 0.7 | H7: 0.7 | I7: 0.7 | K7: disab|||second | L7: 0.25
A8: 4 | B8: 0.08 | C8: 0.7 | D8: 0.7 | E8: 0.7 | F8: 0.7 | G8: 0.7 | H8: 0.8 | I8: 0.7 | K8: exps|||inflation | L8: 0.01
A9: 5 | B9: 0.08 | C9: 0.8 | D9: 0.8 | E9: 0.8 | F9: 0.8 | G9: 0.7 | H9: 0.8 | I9: 0.7 | K9: exps||| | L9: 0.1
A10: 6 | B10: 0.08 | C10: 0.8 | D10: 0.8 | E10: 0.8 | F10: 0.8 | G10: 0.7 | H10: 0.8 | I10: 0.7 | K10: lapse|down||limit | L10: 0.2
A11: 7 | B11: 0.08 | C11: 0.8 | D11: 0.8 | E11: 0.8 | F11: 0.8 | G11: 0.7 | H11: 0.8 | I11: 0.7 | K11: lapse|down|| | L11: 0.5
A12: 8 | B12: 0.08 | C12: 0.8 | D12: 0.8 | E12: 0.8 | F12: 0.8 | G12: 0.7 | H12: 0.8 | I12: 0.7 | K12: lapse|mass|nonretail| | L12: 0.7
A13: 9 | B13: 0.08 | C13: 0.8 | D13: 0.8 | E13: 0.8 | F13: 0.8 | G13: 0.7 | H13: 0.8 | I13: 0.7 | K13: lapse|mass|| | L13: 0.4
A14: 10 | B14: 0.08 | C14: 0.8 | D14: 0.8 | E14: 0.8 | F14: 0.8 | G14: 0.7 | H14: 0.8 | I14: 0.7 | K14: lapse|up||limit | L14: 1
A15: 11 | B15: 0.08 | C15: 0.8 | D15: 0.8 | E15: 0.8 | F15: 0.8 | G15: 0.7 | H15: 0.8 | I15: 0.7 | K15: lapse|up|| | L15: 0.5
... A18: 14 | B18: 0.08 | C18: 0.8 | D18: 0.8 | E18: 0.8 | F18: 0.8 | G18: 0.7 | H18: 0.8 | I18: 0.7 | K18: rev||| | L18: 0.03
A19: 15 | B19: 0.08 | C19: 0.8 | D19: 0.8 | E19: 0.8 | F19: 0.8 | G19: 0.7 | H19: 0.8 | I19: 0.7
A20: 16 | B20: 0.08 | C20: 0.8 | D20: 0.8 | E20: 0.8 | F20: 0.8 | G20: 0.7 | H20: 0.8 | I20: 0.7
A21: 17 | B21: 0.08 | C21: 0.8 | D21: 0.8 | E21: 0.8 | F21: 0.8 | G21: 0.7 | H21: 0.8 | I21: 0.7
A22: 18 | B22: 0.08 | C22: 0.8 | D22: 0.8 | E22: 0.8 | F22: 0.8 | G22: 0.7 | H22: 0.8 | I22: 0.7
A23: 19 | B23: 0.08 | C23: 0.8 | D23: 0.8 | E23: 0.8 | F23: 0.8 | G23: 0.7 | H23: 0.8 | I23: 0.7

Sheet Mortality
A1: Mortality tables qx by age — 6 tables x M/F (lifelib Input.MortalityTables). Tables 5 and 6 are empty in the lifelib data set (never referenced by any policy's basis); the blank columns are kept so table ids map 1:1 to grid columns.
A2: age | B2: T1 M | C2: T1 F | D2: T2 M | E2: T2 F | F2: T3 M | G2: T3 F | H2: T4 M | I2: T4 F | J2: T5 M | K2: T5 F | L2: T6 M | M2: T6 F
A3: x | B3: MortalityTables
A4: 0 | B4: 0.00246 | C4: 0.0021 | D4: 0.00298 | E4: 0.00252 | F4: 0.00345 | G4: 0.00298 | H4: 0.00456 | I4: 0.00383
A5: 1 | B5: 0.00037 | C5: 0.00033 | D5: 0.00045 | E5: 0.00034 | F5: 0.00051 | G5: 0.00044 | H5: 0.00069 | I5: 0.00059
A6: 2 | B6: 0.00026 | C6: 0.00023 | D6: 0.00032 | E6: 0.00025 | F6: 0.00038 | G6: 0.0003 | H6: 0.00051 | I6: 0.00041
A7: 3 | B7: 0.00018 | C7: 0.00015 | D7: 0.00022 | E7: 0.00018 | F7: 0.00027 | G7: 0.0002 | H7: 0.00037 | I7: 0.00028
A8: 4 | B8: 0.00013 | C8: 0.00011 | D8: 0.00016 | E8: 0.00013 | F8: 0.00021 | G8: 0.00014 | H8: 0.00029 | I8: 0.00021
A9: 5 | B9: 0.00011 | C9: 9e-05 | D9: 0.00014 | E9: 0.00011 | F9: 0.00018 | G9: 0.00012 | H9: 0.00025 | I9: 0.00018
A10: 6 | B10: 0.0001 | C10: 8e-05 | D10: 0.00014 | E10: 9e-05 | F10: 0.00016 | G10: 0.00011 | H10: 0.00024 | I10: 0.00017
A11: 7 | B11: 9e-05 | C11: 8e-05 | D11: 0.00014 | E11: 9e-05 | F11: 0.00014 | G11: 0.0001 | H11: 0.00022 | I11: 0.00015
A12: 8 | B12: 8e-05 | C12: 7e-05 | D12: 0.00013 | E12: 8e-05 | F12: 0.00012 | G12: 9e-05 | H12: 0.0002 | I12: 0.00013
A13: 9 | B13: 8e-05 | C13: 6e-05 | D13: 0.00011 | E13: 7e-05 | F13: 0.00011 | G13: 8e-05 | H13: 0.00019 | I13: 0.00012
A14: 10 | B14: 8e-05 | C14: 6e-05 | D14: 9e-05 | E14: 7e-05 | F14: 0.0001 | G14: 8e-05 | H14: 0.00018 | I14: 0.00012
A15: 11 | B15: 0.0001 | C15: 6e-05 | D15: 9e-05 | E15: 6e-05 | F15: 0.00011 | G15: 8e-05 | H15: 0.00017 | I15: 0.00012
... A134: 130 | B134: 1 | C134: 1 | D134: 1 | E134: 1 | F134: 1 | G134: 1 | H134: 1 | I134: 1

Sheet Scenarios
A1: Economic scenarios — flat annual discount/earned rate paths by year (lifelib Input.Scenarios, IntRate)
A2: t | B2: Scen 1 | C2: Scen 2 | D2: Scen 3 | E2: Scen 4 | F2: Scen 5 | G2: Scen 6 | H2: Scen 7 | I2: Scen 8 | J2: Scen 9 | K2: Scen 10
A3: t | B3: DiscRate
A4: 0 | B4: 0.015 | C4: 0.02 | D4: 0.01 | E4: 0.01 | F4: 0.03 | G4: 0.03 | H4: 0.03 | I4: 0.03 | J4: 0.03 | K4: 0.03
A5: 1 | B5: 0.015 | C5: 0.02 | D5: 0.01 | E5: 0.011 | F5: 0.03 | G5: 0.03 | H5: 0.03 | I5: 0.03 | J5: 0.03 | K5: 0.03
A6: 2 | B6: 0.015 | C6: 0.02 | D6: 0.01 | E6: 0.012 | F6: 0.03 | G6: 0.03 | H6: 0.03 | I6: 0.03 | J6: 0.03 | K6: 0.03
A7: 3 | B7: 0.015 | C7: 0.02 | D7: 0.01 | E7: 0.013 | F7: 0.03 | G7: 0.03 | H7: 0.03 | I7: 0.03 | J7: 0.03 | K7: 0.03
A8: 4 | B8: 0.015 | C8: 0.02 | D8: 0.01 | E8: 0.014 | F8: 0.03 | G8: 0.03 | H8: 0.03 | I8: 0.03 | J8: 0.03 | K8: 0.03
A9: 5 | B9: 0.015 | C9: 0.02 | D9: 0.01 | E9: 0.015 | F9: 0.03 | G9: 0.03 | H9: 0.03 | I9: 0.03 | J9: 0.03 | K9: 0.03
A10: 6 | B10: 0.015 | C10: 0.02 | D10: 0.01 | E10: 0.015 | F10: 0.03 | G10: 0.03 | H10: 0.03 | I10: 0.03 | J10: 0.03 | K10: 0.03
A11: 7 | B11: 0.015 | C11: 0.02 | D11: 0.01 | E11: 0.015 | F11: 0.03 | G11: 0.03 | H11: 0.03 | I11: 0.03 | J11: 0.03 | K11: 0.03
A12: 8 | B12: 0.015 | C12: 0.02 | D12: 0.01 | E12: 0.015 | F12: 0.03 | G12: 0.03 | H12: 0.03 | I12: 0.03 | J12: 0.03 | K12: 0.03
A13: 9 | B13: 0.015 | C13: 0.02 | D13: 0.01 | E13: 0.015 | F13: 0.03 | G13: 0.03 | H13: 0.03 | I13: 0.03 | J13: 0.03 | K13: 0.03
A14: 10 | B14: 0.015 | C14: 0.02 | D14: 0.01 | E14: 0.015 | F14: 0.03 | G14: 0.03 | H14: 0.03 | I14: 0.03 | J14: 0.03 | K14: 0.03
A15: 11 | B15: 0.015 | C15: 0.02 | D15: 0.01 | E15: 0.015 | F15: 0.03 | G15: 0.03 | H15: 0.03 | I15: 0.03 | J15: 0.03 | K15: 0.03
... A154: 150 | B154: 0.015 | C154: 0.02 | D154: 0.01 | E154: 0.015 | F154: 0.03 | G154: 0.03 | H154: 0.03 | I154: 0.03 | J154: 0.03 | K154: 0.03

Sheet Policy_Basis
B2: Selected policy (from Policy_Data)
B3: Item | C3: Value | D3: Notes / lifelib cell
B4: Product | C4: =INDEX(MP_Product,MATCH(PolicyID,MP_ID,0)) | D4: Product() — TERM / WL / ENDW
B5: Policy type | C5: =INDEX(MP_PolType,MATCH(PolicyID,MP_ID,0)) | D5: PolicyType()
B6: Generation | C6: =INDEX(MP_Gen,MATCH(PolicyID,MP_ID,0)) | D6: Gen()
B7: Sex | C7: =INDEX(MP_Sex,MATCH(PolicyID,MP_ID,0)) | D7: Sex()
B8: Issue age | C8: =INDEX(MP_IssueAge,MATCH(PolicyID,MP_ID,0)) | D8: IssueAge() — x
B9: Premium frequency p.a. | C9: =INDEX(MP_PremFreq,MATCH(PolicyID,MP_ID,0)) | D9: PremFreq()
B10: Policy term (years) | C10: =INDEX(MP_Term,MATCH(PolicyID,MP_ID,0)) | D10: PolicyTerm() — n = m (premium term alias)
B11: Policy count | C11: =INDEX(MP_Count,MATCH(PolicyID,MP_ID,0)) | D11: PolicyCount()
B12: Sum assured | C12: =INDEX(MP_SumAssured,MATCH(PolicyID,MP_ID,0)) | D12: SumAssured()
B14: Resolved lookups (modelx match cascade)
B15: Item | C15: Value | D15: Notes / lifelib cell
B16: BaseMortTable | C16: =IFERROR(INDEX(AsmpVals,IFERROR(MATCH("BaseMort|"&Product&"|"&PolicyType&"|"&Gen,AsmpKeys,0),IFERROR(MATCH("BaseMort|"&Product&"|"&PolicyType&"|",AsmpKeys,0),IFERROR(MATCH("BaseMort|"&Product&"||"&Gen,AsmpKeys,0),IFERROR(MATCH("BaseMort||"&PolicyType&"|"&Gen,AsmpKeys,0),IFERROR(MATCH("BaseMort|"&Product&"||",AsmpKeys,0),IFERROR(MATCH("BaseMort||"&PolicyType&"|",AsmpKeys,0),IFERROR(MATCH("BaseMort|||"&Gen,AsmpKeys,0),MATCH("BaseMort|||",AsmpKeys,0))))))))),"NA") | D16: asmp.BaseMortRate — base mortality table id
B17: MortFactorTable | C17: =IFERROR(INDEX(AsmpVals,IFERROR(MATCH("MortFactor|"&Product&"|"&PolicyType&"|"&Gen,AsmpKeys,0),IFERROR(MATCH("MortFactor|"&Product&"|"&PolicyType&"|",AsmpKeys,0),IFERROR(MATCH("MortFactor|"&Product&"||"&Gen,AsmpKeys,0),IFERROR(MATCH("MortFactor||"&PolicyType&"|"&Gen,AsmpKeys,0),IFERROR(MATCH("MortFactor|"&Product&"||",AsmpKeys,0),IFERROR(MATCH("MortFactor||"&PolicyType&"|",AsmpKeys,0),IFERROR(MATCH("MortFactor|||"&Gen,AsmpKeys,0),MATCH("MortFactor|||",AsmpKeys,0))))))))),"NA") | D17: asmp.MortFactor — factor table name
B18: SurrTable | C18: =IFERROR(INDEX(AsmpVals,IFERROR(MATCH("Surrender|"&Product&"|"&PolicyType&"|"&Gen,AsmpKeys,0),IFERROR(MATCH("Surrender|"&Product&"|"&PolicyType&"|",AsmpKeys,0),IFERROR(MATCH("Surrender|"&Product&"||"&Gen,AsmpKeys,0),IFERROR(MATCH("Surrender||"&PolicyType&"|"&Gen,AsmpKeys,0),IFERROR(MATCH("Surrender|"&Product&"||",AsmpKeys,0),IFERROR(MATCH("Surrender||"&PolicyType&"|",AsmpKeys,0),IFERROR(MATCH("Surrender|||"&Gen,AsmpKeys,0),MATCH("Surrender|||",AsmpKeys,0))))))))),"NA") | D18: asmp.SurrRate — surrender table name
B19: CnsmpTax | C19: =IFERROR(INDEX(AsmpVals,MATCH("CnsmpTax|||",AsmpKeys,0)),"NA") | D19: asmp.CnsmpTax() — direct global lookup in lifelib, no cascade
B20: CommInitPrem | C20: =IFERROR(INDEX(AsmpVals,IFERROR(MATCH("CommInitPrem|"&Product&"|"&PolicyType&"|"&Gen,AsmpKeys,0),IFERROR(MATCH("CommInitPrem|"&Product&"|"&PolicyType&"|",AsmpKeys,0),IFERROR(MATCH("CommInitPrem|"&Product&"||"&Gen,AsmpKeys,0),IFERROR(MATCH("CommInitPrem||"&PolicyType&"|"&Gen,AsmpKeys,0),IFERROR(MATCH("CommInitPrem|"&Product&"||",AsmpKeys,0),IFERROR(MATCH("CommInitPrem||"&PolicyType&"|",AsmpKeys,0),IFERROR(MATCH("CommInitPrem|||"&Gen,AsmpKeys,0),MATCH("CommInitPrem|||",AsmpKeys,0))))))))),"NA") | D20: asmp.CommInitPrem()
B21: CommRenPrem | C21: =IFERROR(INDEX(AsmpVals,IFERROR(MATCH("CommRenPrem|"&Product&"|"&PolicyType&"|"&Gen,AsmpKeys,0),IFERROR(MATCH("CommRenPrem|"&Product&"|"&PolicyType&"|",AsmpKeys,0),IFERROR(MATCH("CommRenPrem|"&Product&"||"&Gen,AsmpKeys,0),IFERROR(MATCH("CommRenPrem||"&PolicyType&"|"&Gen,AsmpKeys,0),IFERROR(MATCH("CommRenPrem|"&Product&"||",AsmpKeys,0),IFERROR(MATCH("CommRenPrem||"&PolicyType&"|",AsmpKeys,0),IFERROR(MATCH("CommRenPrem|||"&Gen,AsmpKeys,0),MATCH("CommRenPrem|||",AsmpKeys,0))))))))),"NA") | D21: asmp.CommRenPrem()
B22: CommRenTerm | C22: =IFERROR(INDEX(AsmpVals,IFERROR(MATCH("CommRenTerm|"&Product&"|"&PolicyType&"|"&Gen,AsmpKeys,0),IFERROR(MATCH("CommRenTerm|"&Product&"|"&PolicyType&"|",AsmpKeys,0),IFERROR(MATCH("CommRenTerm|"&Product&"||"&Gen,AsmpKeys,0),IFERROR(MATCH("CommRenTerm||"&PolicyType&"|"&Gen,AsmpKeys,0),IFERROR(MATCH("CommRenTerm|"&Product&"||",AsmpKeys,0),IFERROR(MATCH("CommRenTerm||"&PolicyType&"|",AsmpKeys,0),IFERROR(MATCH("CommRenTerm|||"&Gen,AsmpKeys,0),MATCH("CommRenTerm|||",AsmpKeys,0))))))))),"NA") | D22: asmp.CommRenTerm()
B23: ExpsAcqAnnPrem | C23: =IFERROR(INDEX(AsmpVals,IFERROR(MATCH("ExpsAcqAnnPrem|"&Product&"|"&PolicyType&"|"&Gen,AsmpKeys,0),IFERROR(MATCH("ExpsAcqAnnPrem|"&Product&"|"&PolicyType&"|",AsmpKeys,0),IFERROR(MATCH("ExpsAcqAnnPrem|"&Product&"||"&Gen,AsmpKeys,0),IFERROR(MATCH("ExpsAcqAnnPrem||"&PolicyType&"|"&Gen,AsmpKeys,0),IFERROR(MATCH("ExpsAcqAnnPrem|"&Product&"||",AsmpKeys,0),IFERROR(MATCH("ExpsAcqAnnPrem||"&PolicyType&"|",AsmpKeys,0),IFERROR(MATCH("ExpsAcqAnnPrem|||"&Gen,AsmpKeys,0),MATCH("ExpsAcqAnnPrem|||",AsmpKeys,0))))))))),"NA") | D23: asmp.ExpsAcqAnnPrem()
B24: ExpsAcqPol | C24: =IFERROR(INDEX(AsmpVals,IFERROR(MATCH("ExpsAcqPol|"&Product&"|"&PolicyType&"|"&Gen,AsmpKeys,0),IFERROR(MATCH("ExpsAcqPol|"&Product&"|"&PolicyType&"|",AsmpKeys,0),IFERROR(MATCH("ExpsAcqPol|"&Product&"||"&Gen,AsmpKeys,0),IFERROR(MATCH("ExpsAcqPol||"&PolicyType&"|"&Gen,AsmpKeys,0),IFERROR(MATCH("ExpsAcqPol|"&Product&"||",AsmpKeys,0),IFERROR(MATCH("ExpsAcqPol||"&PolicyType&"|",AsmpKeys,0),IFERROR(MATCH("ExpsAcqPol|||"&Gen,AsmpKeys,0),MATCH("ExpsAcqPol|||",AsmpKeys,0))))))))),"NA") | D24: asmp.ExpsAcqPol()
B25: ExpsAcqSA | C25: =IFERROR(INDEX(AsmpVals,IFERROR(MATCH("ExpsAcqSA|"&Product&"|"&PolicyType&"|"&Gen,AsmpKeys,0),IFERROR(MATCH("ExpsAcqSA|"&Product&"|"&PolicyType&"|",AsmpKeys,0),IFERROR(MATCH("ExpsAcqSA|"&Product&"||"&Gen,AsmpKeys,0),IFERROR(MATCH("ExpsAcqSA||"&PolicyType&"|"&Gen,AsmpKeys,0),IFERROR(MATCH("ExpsAcqSA|"&Product&"||",AsmpKeys,0),IFERROR(MATCH("ExpsAcqSA||"&PolicyType&"|",AsmpKeys,0),IFERROR(MATCH("ExpsAcqSA|||"&Gen,AsmpKeys,0),MATCH("ExpsAcqSA|||",AsmpKeys,0))))))))),"NA") | D25: asmp.ExpsAcqSA()
B26: ExpsMaintAnnPrem | C26: =IFERROR(INDEX(AsmpVals,IFERROR(MATCH("ExpsMaintPrem|"&Product&"|"&PolicyType&"|"&Gen,AsmpKeys,0),IFERROR(MATCH("ExpsMaintPrem|"&Product&"|"&PolicyType&"|",AsmpKeys,0),IFERROR(MATCH("ExpsMaintPrem|"&Product&"||"&Gen,AsmpKeys,0),IFERROR(MATCH("ExpsMaintPrem||"&PolicyType&"|"&Gen,AsmpKeys,0),IFERROR(MATCH("ExpsMaintPrem|"&Product&"||",AsmpKeys,0),IFERROR(MATCH("ExpsMaintPrem||"&PolicyType&"|",AsmpKeys,0),IFERROR(MATCH("ExpsMaintPrem|||"&Gen,AsmpKeys,0),MATCH("ExpsMaintPrem|||",AsmpKeys,0))))))))),"NA") | D26: asmp.ExpsMaintAnnPrem()
B27: ExpsMaintPol | C27: =IFERROR(INDEX(AsmpVals,IFERROR(MATCH("ExpsMaintPol|"&Product&"|"&PolicyType&"|"&Gen,AsmpKeys,0),IFERROR(MATCH("ExpsMaintPol|"&Product&"|"&PolicyType&"|",AsmpKeys,0),IFERROR(MATCH("ExpsMaintPol|"&Product&"||"&Gen,AsmpKeys,0),IFERROR(MATCH("ExpsMaintPol||"&PolicyType&"|"&Gen,AsmpKeys,0),IFERROR(MATCH("ExpsMaintPol|"&Product&"||",AsmpKeys,0),IFERROR(MATCH("ExpsMaintPol||"&PolicyType&"|",AsmpKeys,0),IFERROR(MATCH("ExpsMaintPol|||"&Gen,AsmpKeys,0),MATCH("ExpsMaintPol|||",AsmpKeys,0))))))))),"NA") | D27: asmp.ExpsMaintPol()
B28: ExpsMaintSA | C28: =IFERROR(INDEX(AsmpVals,IFERROR(MATCH("ExpsMaintSA|"&Product&"|"&PolicyType&"|"&Gen,AsmpKeys,0),IFERROR(MATCH("ExpsMaintSA|"&Product&"|"&PolicyType&"|",AsmpKeys,0),IFERROR(MATCH("ExpsMaintSA|"&Product&"||"&Gen,AsmpKeys,0),IFERROR(MATCH("ExpsMaintSA||"&PolicyType&"|"&Gen,AsmpKeys,0),IFERROR(MATCH("ExpsMaintSA|"&Product&"||",AsmpKeys,0),IFERROR(MATCH("ExpsMaintSA||"&PolicyType&"|",AsmpKeys,0),IFERROR(MATCH("ExpsMaintSA|||"&Gen,AsmpKeys,0),MATCH("ExpsMaintSA|||",AsmpKeys,0))))))))),"NA") | D28: asmp.ExpsMaintSA()
B29: InflRate | C29: =IFERROR(INDEX(AsmpVals,MATCH("InflRate|||",AsmpKeys,0)),"NA") | D29: asmp.InflRate() — direct global lookup in lifelib, no cascade
B30: IntRatePrem | C30: =IFERROR(INDEX(SpecVals,IFERROR(MATCH("IntRatePrem|"&Product&"|"&PolicyType&"|"&Gen,SpecKeys,0),IFERROR(MATCH("IntRatePrem|"&Product&"|"&PolicyType&"|",SpecKeys,0),IFERROR(MATCH("IntRatePrem|"&Product&"||"&Gen,SpecKeys,0),IFERROR(MATCH("IntRatePrem||"&PolicyType&"|"&Gen,SpecKeys,0),IFERROR(MATCH("IntRatePrem|"&Product&"||",SpecKeys,0),IFERROR(MATCH("IntRatePrem||"&PolicyType&"|",SpecKeys,0),IFERROR(MATCH("IntRatePrem|||"&Gen,SpecKeys,0),MATCH("IntRatePrem|||",SpecKeys,0))))))))),"NA") | D30: pol.IntRate('PREM')
B31: TableIDPrem | C31: =IFERROR(INDEX(SpecVals,IFERROR(MATCH("MortTablePrem|"&Product&"|"&PolicyType&"|"&Gen,SpecKeys,0),IFERROR(MATCH("MortTablePrem|"&Product&"|"&PolicyType&"|",SpecKeys,0),IFERROR(MATCH("MortTablePrem|"&Product&"||"&Gen,SpecKeys,0),IFERROR(MATCH("MortTablePrem||"&PolicyType&"|"&Gen,SpecKeys,0),IFERROR(MATCH("MortTablePrem|"&Product&"||",SpecKeys,0),IFERROR(MATCH("MortTablePrem||"&PolicyType&"|",SpecKeys,0),IFERROR(MATCH("MortTablePrem|||"&Gen,SpecKeys,0),MATCH("MortTablePrem|||",SpecKeys,0))))))))),"NA") | D31: pol.TableID('PREM')
B32: LoadAcqP1 | C32: =IFERROR(INDEX(SpecVals,MATCH("LoadAcqSAParam1|"&Product&"||",SpecKeys,0)),"NA") | D32: pol.LoadAcqSA — param 1; direct (item, product) lookup in lifelib
B33: LoadAcqP2 | C33: =IFERROR(INDEX(SpecVals,MATCH("LoadAcqSAParam2|"&Product&"||",SpecKeys,0)),"NA") | D33: pol.LoadAcqSA — param 2; direct (item, product) lookup
B34: LoadMaintPremP1 | C34: =IFERROR(INDEX(SpecVals,MATCH("LoadMaintPremParam1|"&Product&"||",SpecKeys,0)),"NA") | D34: pol.LoadMaintPrem — param 1; direct (item, product) lookup
B35: LoadMaintPremP2 | C35: =IFERROR(INDEX(SpecVals,MATCH("LoadMaintPremParam2|"&Product&"||",SpecKeys,0)),"NA") | D35: pol.LoadMaintPrem — param 2; direct lookup — NA when absent, as in lifelib
B36: LoadMaintSA | C36: =IFERROR(INDEX(SpecVals,IFERROR(MATCH("LoadMaintSA|"&Product&"|"&PolicyType&"|"&Gen,SpecKeys,0),IFERROR(MATCH("LoadMaintSA|"&Product&"|"&PolicyType&"|",SpecKeys,0),IFERROR(MATCH("LoadMaintSA|"&Product&"||"&Gen,SpecKeys,0),IFERROR(MATCH("LoadMaintSA||"&PolicyType&"|"&Gen,SpecKeys,0),IFERROR(MATCH("LoadMaintSA|"&Product&"||",SpecKeys,0),IFERROR(MATCH("LoadMaintSA||"&PolicyType&"|",SpecKeys,0),IFERROR(MATCH("LoadMaintSA|||"&Gen,SpecKeys,0),MATCH("LoadMaintSA|||",SpecKeys,0))))))))),"NA") | D36: pol.LoadMaintSA() — gamma
B37: LoadMaintSA2 | C37: =IFERROR(INDEX(SpecVals,IFERROR(MATCH("LoadMaintSA2|"&Product&"|"&PolicyType&"|"&Gen,SpecKeys,0),IFERROR(MATCH("LoadMaintSA2|"&Product&"|"&PolicyType&"|",SpecKeys,0),IFERROR(MATCH("LoadMaintSA2|"&Product&"||"&Gen,SpecKeys,0),IFERROR(MATCH("LoadMaintSA2||"&PolicyType&"|"&Gen,SpecKeys,0),IFERROR(MATCH("LoadMaintSA2|"&Product&"||",SpecKeys,0),IFERROR(MATCH("LoadMaintSA2||"&PolicyType&"|",SpecKeys,0),IFERROR(MATCH("LoadMaintSA2|||"&Gen,SpecKeys,0),MATCH("LoadMaintSA2|||",SpecKeys,0))))))))),"NA") | D37: pol.LoadMaintSA2() — gamma2
B38: SurrP1 | C38: =IFERROR(INDEX(SpecVals,IFERROR(MATCH("SurrChargeParam1|"&Product&"|"&PolicyType&"|"&Gen,SpecKeys,0),IFERROR(MATCH("SurrChargeParam1|"&Product&"|"&PolicyType&"|",SpecKeys,0),IFERROR(MATCH("SurrChargeParam1|"&Product&"||"&Gen,SpecKeys,0),IFERROR(MATCH("SurrChargeParam1||"&PolicyType&"|"&Gen,SpecKeys,0),IFERROR(MATCH("SurrChargeParam1|"&Product&"||",SpecKeys,0),IFERROR(MATCH("SurrChargeParam1||"&PolicyType&"|",SpecKeys,0),IFERROR(MATCH("SurrChargeParam1|||"&Gen,SpecKeys,0),MATCH("SurrChargeParam1|||",SpecKeys,0))))))))),"NA") | D38: pol.InitSurrCharge — param 1
B39: SurrP2 | C39: =IFERROR(INDEX(SpecVals,IFERROR(MATCH("SurrChargeParam2|"&Product&"|"&PolicyType&"|"&Gen,SpecKeys,0),IFERROR(MATCH("SurrChargeParam2|"&Product&"|"&PolicyType&"|",SpecKeys,0),IFERROR(MATCH("SurrChargeParam2|"&Product&"||"&Gen,SpecKeys,0),IFERROR(MATCH("SurrChargeParam2||"&PolicyType&"|"&Gen,SpecKeys,0),IFERROR(MATCH("SurrChargeParam2|"&Product&"||",SpecKeys,0),IFERROR(MATCH("SurrChargeParam2||"&PolicyType&"|",SpecKeys,0),IFERROR(MATCH("SurrChargeParam2|||"&Gen,SpecKeys,0),MATCH("SurrChargeParam2|||",SpecKeys,0))))))))),"NA") | D39: pol.InitSurrCharge — param 2
B41: Derived policy quantities
B42: Item | C42: Value | D42: Notes / lifelib cell
B43: BaseMortCol | C43: =(BaseMortTable-1)*2+IF(Sex="M",1,2) | D43: column of the base mortality table in the Mortality grid
B44: PremMortCol | C44: =(TableIDPrem-1)*2+IF(Sex="M",1,2) | D44: column of the PREM-basis mortality table
B45: MortFactorCol | C45: =MATCH(MortFactorTable,AsmpTblNames,0)
B46: SurrCol | C46: =MATCH(SurrTable,AsmpTblNames,0)
B47: LastAge | C47: =INDEX(MortAges,MATCH(1,INDEX(MortGrid,0,BaseMortCol),0)) | D47: asmp.LastAge() — first age with qx = 1 in the base table
B48: LastT | C48: =MIN(LastAge-IssueAge,PolicyTerm) | D48: last_t() = min(LastAge − IssueAge, PolicyTerm)
B49: DxX | C49: =INDEX(Comm_Dx,IssueAge+1) | D49: Dx(x)
B50: MxX | C50: =INDEX(Comm_Mx,IssueAge+1) | D50: Mx(x)
B51: NxX | C51: =INDEX(Comm_Nx,IssueAge+1) | D51: Nx(x)
B52: Dx_xn | C52: =INDEX(Comm_Dx,IssueAge+PolicyTerm+1) | D52: Dx(x+n)
B53: Mx_xn | C53: =INDEX(Comm_Mx,IssueAge+PolicyTerm+1) | D53: Mx(x+n)
B54: Nx_xn | C54: =INDEX(Comm_Nx,IssueAge+PolicyTerm+1) | D54: Nx(x+n) = Nx(x+m), premium term m = n
B55: Axn | C55: =(MxX-Mx_xn)/DxX | D55: lt.Axn(x, n)
B56: Exn | C56: =Dx_xn/DxX | D56: lt.Exn(x, n) — endowment pure survival factor
B57: AnnDue_xm_k | C57: =(NxX-Nx_xn)/DxX-(PremFreq-1)/(2*PremFreq)*(1-Dx_xn/DxX) | D57: lt.AnnDuenx(x, m, PremFreq) = AnnDuenx(x, n, PremFreq) since m = n
B58: AnnDue_xn_1 | C58: =(NxX-Nx_xn)/DxX | D58: lt.AnnDuenx(x, n)
B59: AnnDue_gamma2 | C59: =(Nx_xn-Nx_xn)/DxX | D59: lt.AnnDuenx(x, n−m, 1, m) — identically 0 while m = n
B60: LoadAcqSA | C60: =LoadAcqP1+LoadAcqP2*MIN(PolicyTerm/10,1) | D60: pol.LoadAcqSA() — alpha
B61: LoadMaintPrem | C61: =IF(ISNUMBER(LoadMaintPremP1),LoadMaintPremP1,(LoadMaintPremP2+MIN(10,PolicyTerm))/100) | D61: pol.LoadMaintPrem() — beta; param 1 takes priority, as in lifelib
B62: LoadWaiver | C62: =IF(PolicyTerm<5,0.0005,IF(PolicyTerm<10,0.001,0.002)) | D62: pol.LoadMaintPremWaiverPrem() — delta
B63: InitSurrCharge | C63: =SurrP1+SurrP2*MIN(PolicyTerm/10,1) | D63: pol.InitSurrCharge()
B64: GrossPremRate | C64: =(IF(Product="ENDW",Exn,0)+Axn+LoadAcqSA+LoadMaintSA*AnnDue_xm_k+LoadMaintSA2*AnnDue_gamma2)/(1-LoadMaintPrem-LoadWaiver)/PremFreq/AnnDue_xm_k | D64: pol.GrossPremRate() — per sum assured per payment
B65: NetPremRatePrem | C65: =(Axn+LoadMaintSA2*AnnDue_gamma2)/AnnDue_xn_1 | D65: pol.NetPremRate('PREM')
B66: AnnPremRate | C66: =GrossPremRate*IF(PremFreq=0,0.1,PremFreq) | D66: pol.AnnPremRate()
B67: SizePremium | C67: =SumAssured*GrossPremRate*PremFreq | D67: SizePremium(t) — constant over t
B68: SizeAnnPrem | C68: =SumAssured*AnnPremRate | D68: SizeAnnPrem(t)
B69: SizeExpsAcq0 | C69: =SizeAnnPrem*ExpsAcqAnnPrem+SumAssured*ExpsAcqSA+ExpsAcqPol | D69: SizeExpsAcq(0) — InflFactor(0)/InflFactor(0) = 1
B70: SizeExpsCommInit0 | C70: =SizePremium*CommInitPrem*(1+CnsmpTax) | D70: SizeExpsCommInit(0)

Sheet Commutation
A1: Commutation functions, PREM basis (the only basis in the SCR subgraph): qx from the PREM mortality table, i = IntRatePrem. Nx/Mx recursion floors at age 110, as in lifelib (LifeTable.Nx/Mx).
A2: x | B2: qx | C2: lx | D2: dx | E2: Dx | F2: Cx | G2: Nx | H2: Mx
A3: x | B3: qx | C3: lx | D3: dx | E3: Dx | F3: Cx | G3: Nx | H3: Mx
A4: 0 | B4: =INDEX(MortGrid,A4+1,PremMortCol) | C4: 100000 | D4: =C4*B4 | E4: =C4*(1/(1+IntRatePrem))^A4 | F4: =D4*(1/(1+IntRatePrem))^(A4+0.5) | G4: =IF(A4>=110,E4,G5+E4) | H4: =IF(A4>=110,E4,H5+F4)
A5: =A4+1 | B5: =INDEX(MortGrid,A5+1,PremMortCol) | C5: =C4-D4 | D5: =C5*B5 | E5: =C5*(1/(1+IntRatePrem))^A5 | F5: =D5*(1/(1+IntRatePrem))^(A5+0.5) | G5: =IF(A5>=110,E5,G6+E5) | H5: =IF(A5>=110,E5,H6+F5)
A6: =A5+1 | B6: =INDEX(MortGrid,A6+1,PremMortCol) | C6: =C5-D5 | D6: =C6*B6 | E6: =C6*(1/(1+IntRatePrem))^A6 | F6: =D6*(1/(1+IntRatePrem))^(A6+0.5) | G6: =IF(A6>=110,E6,G7+E6) | H6: =IF(A6>=110,E6,H7+F6)
A7: =A6+1 | B7: =INDEX(MortGrid,A7+1,PremMortCol) | C7: =C6-D6 | D7: =C7*B7 | E7: =C7*(1/(1+IntRatePrem))^A7 | F7: =D7*(1/(1+IntRatePrem))^(A7+0.5) | G7: =IF(A7>=110,E7,G8+E7) | H7: =IF(A7>=110,E7,H8+F7)
A8: =A7+1 | B8: =INDEX(MortGrid,A8+1,PremMortCol) | C8: =C7-D7 | D8: =C8*B8 | E8: =C8*(1/(1+IntRatePrem))^A8 | F8: =D8*(1/(1+IntRatePrem))^(A8+0.5) | G8: =IF(A8>=110,E8,G9+E8) | H8: =IF(A8>=110,E8,H9+F8)
A9: =A8+1 | B9: =INDEX(MortGrid,A9+1,PremMortCol) | C9: =C8-D8 | D9: =C9*B9 | E9: =C9*(1/(1+IntRatePrem))^A9 | F9: =D9*(1/(1+IntRatePrem))^(A9+0.5) | G9: =IF(A9>=110,E9,G10+E9) | H9: =IF(A9>=110,E9,H10+F9)
A10: =A9+1 | B10: =INDEX(MortGrid,A10+1,PremMortCol) | C10: =C9-D9 | D10: =C10*B10 | E10: =C10*(1/(1+IntRatePrem))^A10 | F10: =D10*(1/(1+IntRatePrem))^(A10+0.5) | G10: =IF(A10>=110,E10,G11+E10) | H10: =IF(A10>=110,E10,H11+F10)
A11: =A10+1 | B11: =INDEX(MortGrid,A11+1,PremMortCol) | C11: =C10-D10 | D11: =C11*B11 | E11: =C11*(1/(1+IntRatePrem))^A11 | F11: =D11*(1/(1+IntRatePrem))^(A11+0.5) | G11: =IF(A11>=110,E11,G12+E11) | H11: =IF(A11>=110,E11,H12+F11)
A12: =A11+1 | B12: =INDEX(MortGrid,A12+1,PremMortCol) | C12: =C11-D11 | D12: =C12*B12 | E12: =C12*(1/(1+IntRatePrem))^A12 | F12: =D12*(1/(1+IntRatePrem))^(A12+0.5) | G12: =IF(A12>=110,E12,G13+E12) | H12: =IF(A12>=110,E12,H13+F12)
A13: =A12+1 | B13: =INDEX(MortGrid,A13+1,PremMortCol) | C13: =C12-D12 | D13: =C13*B13 | E13: =C13*(1/(1+IntRatePrem))^A13 | F13: =D13*(1/(1+IntRatePrem))^(A13+0.5) | G13: =IF(A13>=110,E13,G14+E13) | H13: =IF(A13>=110,E13,H14+F13)
A14: =A13+1 | B14: =INDEX(MortGrid,A14+1,PremMortCol) | C14: =C13-D13 | D14: =C14*B14 | E14: =C14*(1/(1+IntRatePrem))^A14 | F14: =D14*(1/(1+IntRatePrem))^(A14+0.5) | G14: =IF(A14>=110,E14,G15+E14) | H14: =IF(A14>=110,E14,H15+F14)
A15: =A14+1 | B15: =INDEX(MortGrid,A15+1,PremMortCol) | C15: =C14-D14 | D15: =C15*B15 | E15: =C15*(1/(1+IntRatePrem))^A15 | F15: =D15*(1/(1+IntRatePrem))^(A15+0.5) | G15: =IF(A15>=110,E15,G16+E15) | H15: =IF(A15>=110,E15,H16+F15)
A16: =A15+1 | B16: =INDEX(MortGrid,A16+1,PremMortCol) | C16: =C15-D15 | D16: =C16*B16 | E16: =C16*(1/(1+IntRatePrem))^A16 | F16: =D16*(1/(1+IntRatePrem))^(A16+0.5) | G16: =IF(A16>=110,E16,G17+E16) | H16: =IF(A16>=110,E16,H17+F16)
... A134: =A133+1 | B134: =INDEX(MortGrid,A134+1,PremMortCol) | C134: =C133-D133 | D134: =C134*B134 | E134: =C134*(1/(1+IntRatePrem))^A134 | F134: =D134*(1/(1+IntRatePrem))^(A134+0.5) | G134: =IF(A134>=110,E134,G135+E134) | H134: =IF(A134>=110,E134,H135+F134)

Sheet Policy_Sched
A1: Per-policy schedule shared by all stress projections (lifelib pol/asmp/scen cells are policy-level and common to every Projection[risk, shock])
A5: t | B5: Attained age | C5: Base mortality qx | D5: Mortality factor | E5: Surrender rate (base) | F5: NLP reserve rate (PREM) | G5: Surrender charge rate | H5: Cash value rate | I5: Surrender benefit pp | J5: Renewal commission pp | K5: Discount rate
A6: t | B6: AttAge | C6: BaseMortRate | D6: MortFactor | E6: SurrRate | F6: ReserveNLP_Rate | G6: SurrCharge | H6: CashValueRate | I6: SizeBenefitSurr | J6: SizeExpsCommRen | K6: DiscRate
A7: 0 | B7: =IssueAge+A7 | C7: =IF($A7>LastT,0,INDEX(MortGrid,B7+1,BaseMortCol)) | D7: =IF($A7>LastT,0,INDEX(AsmpTblGrid,MIN(A7,19)+1,MortFactorCol)) | E7: =IF($A7>LastT,0,INDEX(AsmpTblGrid,MIN(A7,19)+1,SurrCol)) | F7: =IF($A7>LastT+1,0,IF(INDEX(Comm_Dx,B7+1)=0,0,(INDEX(Comm_Mx,B7+1)-Mx_xn+LoadMaintSA2*(Nx_xn-Nx_xn)-IF(A7<=PolicyTerm,NetPremRatePrem*(INDEX(Comm_Nx,B7+1)-Nx_xn),0))/INDEX(Comm_Dx,B7+1))) | G7: =IF($A7>LastT+1,0,InitSurrCharge*MAX((MIN(PolicyTerm,10)-A7)/MIN(PolicyTerm,10),0)) | H7: =IF($A7>LastT+1,0,MAX(F7-G7,0)) | I7: =IF($A7>LastT,0,SumAssured*(H7+H8)/2) | J7: =IF(OR($A7=0,$A7>LastT),0,IF(A7<CommRenTerm,SizePremium*CommRenPrem*(1+CnsmpTax),0)) | K7: =IF($A7>LastT,0,INDEX(ScenGrid,A7+1,ScenID))
A8: =A7+1 | B8: =IssueAge+A8 | C8: =IF($A8>LastT,0,INDEX(MortGrid,B8+1,BaseMortCol)) | D8: =IF($A8>LastT,0,INDEX(AsmpTblGrid,MIN(A8,19)+1,MortFactorCol)) | E8: =IF($A8>LastT,0,INDEX(AsmpTblGrid,MIN(A8,19)+1,SurrCol)) | F8: =IF($A8>LastT+1,0,IF(INDEX(Comm_Dx,B8+1)=0,0,(INDEX(Comm_Mx,B8+1)-Mx_xn+LoadMaintSA2*(Nx_xn-Nx_xn)-IF(A8<=PolicyTerm,NetPremRatePrem*(INDEX(Comm_Nx,B8+1)-Nx_xn),0))/INDEX(Comm_Dx,B8+1))) | G8: =IF($A8>LastT+1,0,InitSurrCharge*MAX((MIN(PolicyTerm,10)-A8)/MIN(PolicyTerm,10),0)) | H8: =IF($A8>LastT+1,0,MAX(F8-G8,0)) | I8: =IF($A8>LastT,0,SumAssured*(H8+H9)/2) | J8: =IF(OR($A8=0,$A8>LastT),0,IF(A8<CommRenTerm,SizePremium*CommRenPrem*(1+CnsmpTax),0)) | K8: =IF($A8>LastT,0,INDEX(ScenGrid,A8+1,ScenID))
A9: =A8+1 | B9: =IssueAge+A9 | C9: =IF($A9>LastT,0,INDEX(MortGrid,B9+1,BaseMortCol)) | D9: =IF($A9>LastT,0,INDEX(AsmpTblGrid,MIN(A9,19)+1,MortFactorCol)) | E9: =IF($A9>LastT,0,INDEX(AsmpTblGrid,MIN(A9,19)+1,SurrCol)) | F9: =IF($A9>LastT+1,0,IF(INDEX(Comm_Dx,B9+1)=0,0,(INDEX(Comm_Mx,B9+1)-Mx_xn+LoadMaintSA2*(Nx_xn-Nx_xn)-IF(A9<=PolicyTerm,NetPremRatePrem*(INDEX(Comm_Nx,B9+1)-Nx_xn),0))/INDEX(Comm_Dx,B9+1))) | G9: =IF($A9>LastT+1,0,InitSurrCharge*MAX((MIN(PolicyTerm,10)-A9)/MIN(PolicyTerm,10),0)) | H9: =IF($A9>LastT+1,0,MAX(F9-G9,0)) | I9: =IF($A9>LastT,0,SumAssured*(H9+H10)/2) | J9: =IF(OR($A9=0,$A9>LastT),0,IF(A9<CommRenTerm,SizePremium*CommRenPrem*(1+CnsmpTax),0)) | K9: =IF($A9>LastT,0,INDEX(ScenGrid,A9+1,ScenID))
A10: =A9+1 | B10: =IssueAge+A10 | C10: =IF($A10>LastT,0,INDEX(MortGrid,B10+1,BaseMortCol)) | D10: =IF($A10>LastT,0,INDEX(AsmpTblGrid,MIN(A10,19)+1,MortFactorCol)) | E10: =IF($A10>LastT,0,INDEX(AsmpTblGrid,MIN(A10,19)+1,SurrCol)) | F10: =IF($A10>LastT+1,0,IF(INDEX(Comm_Dx,B10+1)=0,0,(INDEX(Comm_Mx,B10+1)-Mx_xn+LoadMaintSA2*(Nx_xn-Nx_xn)-IF(A10<=PolicyTerm,NetPremRatePrem*(INDEX(Comm_Nx,B10+1)-Nx_xn),0))/INDEX(Comm_Dx,B10+1))) | G10: =IF($A10>LastT+1,0,InitSurrCharge*MAX((MIN(PolicyTerm,10)-A10)/MIN(PolicyTerm,10),0)) | H10: =IF($A10>LastT+1,0,MAX(F10-G10,0)) | I10: =IF($A10>LastT,0,SumAssured*(H10+H11)/2) | J10: =IF(OR($A10=0,$A10>LastT),0,IF(A10<CommRenTerm,SizePremium*CommRenPrem*(1+CnsmpTax),0)) | K10: =IF($A10>LastT,0,INDEX(ScenGrid,A10+1,ScenID))
A11: =A10+1 | B11: =IssueAge+A11 | C11: =IF($A11>LastT,0,INDEX(MortGrid,B11+1,BaseMortCol)) | D11: =IF($A11>LastT,0,INDEX(AsmpTblGrid,MIN(A11,19)+1,MortFactorCol)) | E11: =IF($A11>LastT,0,INDEX(AsmpTblGrid,MIN(A11,19)+1,SurrCol)) | F11: =IF($A11>LastT+1,0,IF(INDEX(Comm_Dx,B11+1)=0,0,(INDEX(Comm_Mx,B11+1)-Mx_xn+LoadMaintSA2*(Nx_xn-Nx_xn)-IF(A11<=PolicyTerm,NetPremRatePrem*(INDEX(Comm_Nx,B11+1)-Nx_xn),0))/INDEX(Comm_Dx,B11+1))) | G11: =IF($A11>LastT+1,0,InitSurrCharge*MAX((MIN(PolicyTerm,10)-A11)/MIN(PolicyTerm,10),0)) | H11: =IF($A11>LastT+1,0,MAX(F11-G11,0)) | I11: =IF($A11>LastT,0,SumAssured*(H11+H12)/2) | J11: =IF(OR($A11=0,$A11>LastT),0,IF(A11<CommRenTerm,SizePremium*CommRenPrem*(1+CnsmpTax),0)) | K11: =IF($A11>LastT,0,INDEX(ScenGrid,A11+1,ScenID))
A12: =A11+1 | B12: =IssueAge+A12 | C12: =IF($A12>LastT,0,INDEX(MortGrid,B12+1,BaseMortCol)) | D12: =IF($A12>LastT,0,INDEX(AsmpTblGrid,MIN(A12,19)+1,MortFactorCol)) | E12: =IF($A12>LastT,0,INDEX(AsmpTblGrid,MIN(A12,19)+1,SurrCol)) | F12: =IF($A12>LastT+1,0,IF(INDEX(Comm_Dx,B12+1)=0,0,(INDEX(Comm_Mx,B12+1)-Mx_xn+LoadMaintSA2*(Nx_xn-Nx_xn)-IF(A12<=PolicyTerm,NetPremRatePrem*(INDEX(Comm_Nx,B12+1)-Nx_xn),0))/INDEX(Comm_Dx,B12+1))) | G12: =IF($A12>LastT+1,0,InitSurrCharge*MAX((MIN(PolicyTerm,10)-A12)/MIN(PolicyTerm,10),0)) | H12: =IF($A12>LastT+1,0,MAX(F12-G12,0)) | I12: =IF($A12>LastT,0,SumAssured*(H12+H13)/2) | J12: =IF(OR($A12=0,$A12>LastT),0,IF(A12<CommRenTerm,SizePremium*CommRenPrem*(1+CnsmpTax),0)) | K12: =IF($A12>LastT,0,INDEX(ScenGrid,A12+1,ScenID))
A13: =A12+1 | B13: =IssueAge+A13 | C13: =IF($A13>LastT,0,INDEX(MortGrid,B13+1,BaseMortCol)) | D13: =IF($A13>LastT,0,INDEX(AsmpTblGrid,MIN(A13,19)+1,MortFactorCol)) | E13: =IF($A13>LastT,0,INDEX(AsmpTblGrid,MIN(A13,19)+1,SurrCol)) | F13: =IF($A13>LastT+1,0,IF(INDEX(Comm_Dx,B13+1)=0,0,(INDEX(Comm_Mx,B13+1)-Mx_xn+LoadMaintSA2*(Nx_xn-Nx_xn)-IF(A13<=PolicyTerm,NetPremRatePrem*(INDEX(Comm_Nx,B13+1)-Nx_xn),0))/INDEX(Comm_Dx,B13+1))) | G13: =IF($A13>LastT+1,0,InitSurrCharge*MAX((MIN(PolicyTerm,10)-A13)/MIN(PolicyTerm,10),0)) | H13: =IF($A13>LastT+1,0,MAX(F13-G13,0)) | I13: =IF($A13>LastT,0,SumAssured*(H13+H14)/2) | J13: =IF(OR($A13=0,$A13>LastT),0,IF(A13<CommRenTerm,SizePremium*CommRenPrem*(1+CnsmpTax),0)) | K13: =IF($A13>LastT,0,INDEX(ScenGrid,A13+1,ScenID))
A14: =A13+1 | B14: =IssueAge+A14 | C14: =IF($A14>LastT,0,INDEX(MortGrid,B14+1,BaseMortCol)) | D14: =IF($A14>LastT,0,INDEX(AsmpTblGrid,MIN(A14,19)+1,MortFactorCol)) | E14: =IF($A14>LastT,0,INDEX(AsmpTblGrid,MIN(A14,19)+1,SurrCol)) | F14: =IF($A14>LastT+1,0,IF(INDEX(Comm_Dx,B14+1)=0,0,(INDEX(Comm_Mx,B14+1)-Mx_xn+LoadMaintSA2*(Nx_xn-Nx_xn)-IF(A14<=PolicyTerm,NetPremRatePrem*(INDEX(Comm_Nx,B14+1)-Nx_xn),0))/INDEX(Comm_Dx,B14+1))) | G14: =IF($A14>LastT+1,0,InitSurrCharge*MAX((MIN(PolicyTerm,10)-A14)/MIN(PolicyTerm,10),0)) | H14: =IF($A14>LastT+1,0,MAX(F14-G14,0)) | I14: =IF($A14>LastT,0,SumAssured*(H14+H15)/2) | J14: =IF(OR($A14=0,$A14>LastT),0,IF(A14<CommRenTerm,SizePremium*CommRenPrem*(1+CnsmpTax),0)) | K14: =IF($A14>LastT,0,INDEX(ScenGrid,A14+1,ScenID))
A15: =A14+1 | B15: =IssueAge+A15 | C15: =IF($A15>LastT,0,INDEX(MortGrid,B15+1,BaseMortCol)) | D15: =IF($A15>LastT,0,INDEX(AsmpTblGrid,MIN(A15,19)+1,MortFactorCol)) | E15: =IF($A15>LastT,0,INDEX(AsmpTblGrid,MIN(A15,19)+1,SurrCol)) | F15: =IF($A15>LastT+1,0,IF(INDEX(Comm_Dx,B15+1)=0,0,(INDEX(Comm_Mx,B15+1)-Mx_xn+LoadMaintSA2*(Nx_xn-Nx_xn)-IF(A15<=PolicyTerm,NetPremRatePrem*(INDEX(Comm_Nx,B15+1)-Nx_xn),0))/INDEX(Comm_Dx,B15+1))) | G15: =IF($A15>LastT+1,0,InitSurrCharge*MAX((MIN(PolicyTerm,10)-A15)/MIN(PolicyTerm,10),0)) | H15: =IF($A15>LastT+1,0,MAX(F15-G15,0)) | I15: =IF($A15>LastT,0,SumAssured*(H15+H16)/2) | J15: =IF(OR($A15=0,$A15>LastT),0,IF(A15<CommRenTerm,SizePremium*CommRenPrem*(1+CnsmpTax),0)) | K15: =IF($A15>LastT,0,INDEX(ScenGrid,A15+1,ScenID))
A16: =A15+1 | B16: =IssueAge+A16 | C16: =IF($A16>LastT,0,INDEX(MortGrid,B16+1,BaseMortCol)) | D16: =IF($A16>LastT,0,INDEX(AsmpTblGrid,MIN(A16,19)+1,MortFactorCol)) | E16: =IF($A16>LastT,0,INDEX(AsmpTblGrid,MIN(A16,19)+1,SurrCol)) | F16: =IF($A16>LastT+1,0,IF(INDEX(Comm_Dx,B16+1)=0,0,(INDEX(Comm_Mx,B16+1)-Mx_xn+LoadMaintSA2*(Nx_xn-Nx_xn)-IF(A16<=PolicyTerm,NetPremRatePrem*(INDEX(Comm_Nx,B16+1)-Nx_xn),0))/INDEX(Comm_Dx,B16+1))) | G16: =IF($A16>LastT+1,0,InitSurrCharge*MAX((MIN(PolicyTerm,10)-A16)/MIN(PolicyTerm,10),0)) | H16: =IF($A16>LastT+1,0,MAX(F16-G16,0)) | I16: =IF($A16>LastT,0,SumAssured*(H16+H17)/2) | J16: =IF(OR($A16=0,$A16>LastT),0,IF(A16<CommRenTerm,SizePremium*CommRenPrem*(1+CnsmpTax),0)) | K16: =IF($A16>LastT,0,INDEX(ScenGrid,A16+1,ScenID))
A17: =A16+1 | B17: =IssueAge+A17 | C17: =IF($A17>LastT,0,INDEX(MortGrid,B17+1,BaseMortCol)) | D17: =IF($A17>LastT,0,INDEX(AsmpTblGrid,MIN(A17,19)+1,MortFactorCol)) | E17: =IF($A17>LastT,0,INDEX(AsmpTblGrid,MIN(A17,19)+1,SurrCol)) | F17: =IF($A17>LastT+1,0,IF(INDEX(Comm_Dx,B17+1)=0,0,(INDEX(Comm_Mx,B17+1)-Mx_xn+LoadMaintSA2*(Nx_xn-Nx_xn)-IF(A17<=PolicyTerm,NetPremRatePrem*(INDEX(Comm_Nx,B17+1)-Nx_xn),0))/INDEX(Comm_Dx,B17+1))) | G17: =IF($A17>LastT+1,0,InitSurrCharge*MAX((MIN(PolicyTerm,10)-A17)/MIN(PolicyTerm,10),0)) | H17: =IF($A17>LastT+1,0,MAX(F17-G17,0)) | I17: =IF($A17>LastT,0,SumAssured*(H17+H18)/2) | J17: =IF(OR($A17=0,$A17>LastT),0,IF(A17<CommRenTerm,SizePremium*CommRenPrem*(1+CnsmpTax),0)) | K17: =IF($A17>LastT,0,INDEX(ScenGrid,A17+1,ScenID))
A18: =A17+1 | B18: =IssueAge+A18 | C18: =IF($A18>LastT,0,INDEX(MortGrid,B18+1,BaseMortCol)) | D18: =IF($A18>LastT,0,INDEX(AsmpTblGrid,MIN(A18,19)+1,MortFactorCol)) | E18: =IF($A18>LastT,0,INDEX(AsmpTblGrid,MIN(A18,19)+1,SurrCol)) | F18: =IF($A18>LastT+1,0,IF(INDEX(Comm_Dx,B18+1)=0,0,(INDEX(Comm_Mx,B18+1)-Mx_xn+LoadMaintSA2*(Nx_xn-Nx_xn)-IF(A18<=PolicyTerm,NetPremRatePrem*(INDEX(Comm_Nx,B18+1)-Nx_xn),0))/INDEX(Comm_Dx,B18+1))) | G18: =IF($A18>LastT+1,0,InitSurrCharge*MAX((MIN(PolicyTerm,10)-A18)/MIN(PolicyTerm,10),0)) | H18: =IF($A18>LastT+1,0,MAX(F18-G18,0)) | I18: =IF($A18>LastT,0,SumAssured*(H18+H19)/2) | J18: =IF(OR($A18=0,$A18>LastT),0,IF(A18<CommRenTerm,SizePremium*CommRenPrem*(1+CnsmpTax),0)) | K18: =IF($A18>LastT,0,INDEX(ScenGrid,A18+1,ScenID))
A19: =A18+1 | B19: =IssueAge+A19 | C19: =IF($A19>LastT,0,INDEX(MortGrid,B19+1,BaseMortCol)) | D19: =IF($A19>LastT,0,INDEX(AsmpTblGrid,MIN(A19,19)+1,MortFactorCol)) | E19: =IF($A19>LastT,0,INDEX(AsmpTblGrid,MIN(A19,19)+1,SurrCol)) | F19: =IF($A19>LastT+1,0,IF(INDEX(Comm_Dx,B19+1)=0,0,(INDEX(Comm_Mx,B19+1)-Mx_xn+LoadMaintSA2*(Nx_xn-Nx_xn)-IF(A19<=PolicyTerm,NetPremRatePrem*(INDEX(Comm_Nx,B19+1)-Nx_xn),0))/INDEX(Comm_Dx,B19+1))) | G19: =IF($A19>LastT+1,0,InitSurrCharge*MAX((MIN(PolicyTerm,10)-A19)/MIN(PolicyTerm,10),0)) | H19: =IF($A19>LastT+1,0,MAX(F19-G19,0)) | I19: =IF($A19>LastT,0,SumAssured*(H19+H20)/2) | J19: =IF(OR($A19=0,$A19>LastT),0,IF(A19<CommRenTerm,SizePremium*CommRenPrem*(1+CnsmpTax),0)) | K19: =IF($A19>LastT,0,INDEX(ScenGrid,A19+1,ScenID))
... A110: =A109+1 | B110: =IssueAge+A110 | C110: =IF($A110>LastT,0,INDEX(MortGrid,B110+1,BaseMortCol)) | D110: =IF($A110>LastT,0,INDEX(AsmpTblGrid,MIN(A110,19)+1,MortFactorCol)) | E110: =IF($A110>LastT,0,INDEX(AsmpTblGrid,MIN(A110,19)+1,SurrCol)) | F110: =IF($A110>LastT+1,0,IF(INDEX(Comm_Dx,B110+1)=0,0,(INDEX(Comm_Mx,B110+1)-Mx_xn+LoadMaintSA2*(Nx_xn-Nx_xn)-IF(A110<=PolicyTerm,NetPremRatePrem*(INDEX(Comm_Nx,B110+1)-Nx_xn),0))/INDEX(Comm_Dx,B110+1))) | G110: =IF($A110>LastT+1,0,InitSurrCharge*MAX((MIN(PolicyTerm,10)-A110)/MIN(PolicyTerm,10),0)) | H110: =IF($A110>LastT+1,0,MAX(F110-G110,0)) | I110: =IF($A110>LastT,0,SumAssured*(H110+H111)/2) | J110: =IF(OR($A110=0,$A110>LastT),0,IF(A110<CommRenTerm,SizePremium*CommRenPrem*(1+CnsmpTax),0)) | K110: =IF($A110>LastT,0,INDEX(ScenGrid,A110+1,ScenID))

Sheet Proj_Base
A1: Liability projection — base basis (no shock). lifelib SCR_life.Projection['base', None, None]
B2: Risk | C2: Shock | D2: Risk sign | E2: Shock factor | F2: Shock limit | G2: Inflation shock
B3: base | D3: 0 | E3: =IFERROR(INDEX(FactorVals,MATCH($B$3&"|"&$C$3&"||",FactorKeys,0)),0) | F3: =IFERROR(INDEX(FactorVals,MATCH($B$3&"|"&$C$3&"||limit",FactorKeys,0)),0) | G3: =IFERROR(INDEX(FactorVals,MATCH($B$3&"|||inflation",FactorKeys,0)),0)
B4: Risk | C4: Shock | E4: Factor
A5: t | B5: Inflation factor | C5: Mortality shock factor | D5: Surrender rate | E5: In force: end | F5: Maturities | G5: In force: after maturity | H5: New business | I5: Mass lapse | J5: In force: beginning | K5: Deaths | L5: Surrenders | M5: Maint expense pp | N5: Premium income | O5: Death benefits | P5: Surrender benefits | Q5: Total benefits | R5: Acquisition expenses | S5: Initial commission | T5: Renewal commission | U5: Maintenance expenses | V5: Total expenses | W5: PV premiums | X5: PV benefits | Y5: PV expenses | Z5: PV net cashflow | AA5: PV net cf (fwd check)
A6: t | B6: InflFactor | C6: MortRateFactor | D6: SurrRate | E6: PolsIF_End | F6: PolsMaturity | G6: PolsIF_Beg | H6: PolsNewBiz | I6: PolsSurrMass | J6: PolsIF_Beg1 | K6: PolsDeath | L6: PolsSurr | M6: SizeExpsMaint | N6: PremIncome | O6: BenefitDeath | P6: BenefitSurr | Q6: BenefitTotal | R6: ExpsAcq | S6: ExpsCommInit | T6: ExpsCommRen | U6: ExpsMaint | V6: ExpsTotal | W6: PV_PremIncome | X6: PV_BenefitTotal | Y6: PV_ExpsTotal | Z6: PV_NetCashflow | AA6: PV_NetCashflowForCheck
A7: 0 | B7: =1 | C7: =IF($A7>LastT,0,IF(AND($D$3<>0,$A7>=T0,Policy_Sched!$B7<LastAge),1+$D$3*$E$3,1)) | D7: =IF($A7>LastT,0,IF($C$3="up",MIN(Policy_Sched!$E7*(1+IF($A7>=T0,$E$3,0)),$F$3),IF($C$3="down",MAX(Policy_Sched!$E7*(1-IF($A7>=T0,$E$3,0)),Policy_Sched!$E7-$F$3),Policy_Sched!$E7))) | E7: =0 | F7: =IF($A7>LastT,0,IF($A7=PolicyTerm,E7,0)) | G7: =IF($A7>LastT,0,E7-F7) | H7: =IF($A7=0,PolicyCount,0) | I7: =IF($A7>LastT,0,IF(AND($C$3="mass",$A7=T0),(G7+H7)*$E$3,0)) | J7: =IF($A7>LastT,0,G7+H7-I7) | K7: =IF($A7>LastT,0,J7*Policy_Sched!$C7*Policy_Sched!$D7*C7) | L7: =J7*D7 | M7: =IF($A7>LastT,0,(SizeAnnPrem*ExpsMaintAnnPrem+(SumAssured*ExpsMaintSA+ExpsMaintPol)*B7)*(1+IF($B$3="exps",$E$3,0))) | N7: =SizePremium*J7 | O7: =SumAssured*K7 | P7: =Policy_Sched!$I7*(L7+I7) | Q7: =O7+P7 | R7: =IF($A7=0,SizeExpsAcq0*H7,0) | S7: =IF($A7=0,SizeExpsCommInit0*J7,0) | T7: =Policy_Sched!$J7*J7 | U7: =M7*J7 | V7: =S7+T7+R7+U7 | W7: =IF($A7>LastT,0,N7+W8/(1+Policy_Sched!$K7)) | X7: =IF($A7>LastT,0,(-Q7+X8)/(1+Policy_Sched!$K7)) | Y7: =IF($A7>LastT,0,-V7+Y8/(1+Policy_Sched!$K7)) | Z7: =W7+Y7+X7 | AA7: =IF($A7>LastT,0,N7-V7-Q7/(1+Policy_Sched!$K7)+Z8/(1+Policy_Sched!$K7))
A8: =A7+1 | B8: =IF($A8>LastT,0,IF($B$3="exps",B7*(1+InflRate+IF($A8>=T0,$G$3,0)),B7/(1+InflRate))) | C8: =IF($A8>LastT,0,IF(AND($D$3<>0,$A8>=T0,Policy_Sched!$B8<LastAge),1+$D$3*$E$3,1)) | D8: =IF($A8>LastT,0,IF($C$3="up",MIN(Policy_Sched!$E8*(1+IF($A8>=T0,$E$3,0)),$F$3),IF($C$3="down",MAX(Policy_Sched!$E8*(1-IF($A8>=T0,$E$3,0)),Policy_Sched!$E8-$F$3),Policy_Sched!$E8))) | E8: =IF($A8>LastT,0,J7-K7-L7) | F8: =IF($A8>LastT,0,IF($A8=PolicyTerm,E8,0)) | G8: =IF($A8>LastT,0,E8-F8) | H8: =IF($A8=0,PolicyCount,0) | I8: =IF($A8>LastT,0,IF(AND($C$3="mass",$A8=T0),(G8+H8)*$E$3,0)) | J8: =IF($A8>LastT,0,G8+H8-I8) | K8: =IF($A8>LastT,0,J8*Policy_Sched!$C8*Policy_Sched!$D8*C8) | L8: =J8*D8 | M8: =IF($A8>LastT,0,(SizeAnnPrem*ExpsMaintAnnPrem+(SumAssured*ExpsMaintSA+ExpsMaintPol)*B8)*(1+IF($B$3="exps",$E$3,0))) | N8: =SizePremium*J8 | O8: =SumAssured*K8 | P8: =Policy_Sched!$I8*(L8+I8) | Q8: =O8+P8 | R8: =IF($A8=0,SizeExpsAcq0*H8,0) | S8: =IF($A8=0,SizeExpsCommInit0*J8,0) | T8: =Policy_Sched!$J8*J8 | U8: =M8*J8 | V8: =S8+T8+R8+U8 | W8: =IF($A8>LastT,0,N8+W9/(1+Policy_Sched!$K8)) | X8: =IF($A8>LastT,0,(-Q8+X9)/(1+Policy_Sched!$K8)) | Y8: =IF($A8>LastT,0,-V8+Y9/(1+Policy_Sched!$K8)) | Z8: =W8+Y8+X8 | AA8: =IF($A8>LastT,0,N8-V8-Q8/(1+Policy_Sched!$K8)+Z9/(1+Policy_Sched!$K8))
A9: =A8+1 | B9: =IF($A9>LastT,0,IF($B$3="exps",B8*(1+InflRate+IF($A9>=T0,$G$3,0)),B8/(1+InflRate))) | C9: =IF($A9>LastT,0,IF(AND($D$3<>0,$A9>=T0,Policy_Sched!$B9<LastAge),1+$D$3*$E$3,1)) | D9: =IF($A9>LastT,0,IF($C$3="up",MIN(Policy_Sched!$E9*(1+IF($A9>=T0,$E$3,0)),$F$3),IF($C$3="down",MAX(Policy_Sched!$E9*(1-IF($A9>=T0,$E$3,0)),Policy_Sched!$E9-$F$3),Policy_Sched!$E9))) | E9: =IF($A9>LastT,0,J8-K8-L8) | F9: =IF($A9>LastT,0,IF($A9=PolicyTerm,E9,0)) | G9: =IF($A9>LastT,0,E9-F9) | H9: =IF($A9=0,PolicyCount,0) | I9: =IF($A9>LastT,0,IF(AND($C$3="mass",$A9=T0),(G9+H9)*$E$3,0)) | J9: =IF($A9>LastT,0,G9+H9-I9) | K9: =IF($A9>LastT,0,J9*Policy_Sched!$C9*Policy_Sched!$D9*C9) | L9: =J9*D9 | M9: =IF($A9>LastT,0,(SizeAnnPrem*ExpsMaintAnnPrem+(SumAssured*ExpsMaintSA+ExpsMaintPol)*B9)*(1+IF($B$3="exps",$E$3,0))) | N9: =SizePremium*J9 | O9: =SumAssured*K9 | P9: =Policy_Sched!$I9*(L9+I9) | Q9: =O9+P9 | R9: =IF($A9=0,SizeExpsAcq0*H9,0) | S9: =IF($A9=0,SizeExpsCommInit0*J9,0) | T9: =Policy_Sched!$J9*J9 | U9: =M9*J9 | V9: =S9+T9+R9+U9 | W9: =IF($A9>LastT,0,N9+W10/(1+Policy_Sched!$K9)) | X9: =IF($A9>LastT,0,(-Q9+X10)/(1+Policy_Sched!$K9)) | Y9: =IF($A9>LastT,0,-V9+Y10/(1+Policy_Sched!$K9)) | Z9: =W9+Y9+X9 | AA9: =IF($A9>LastT,0,N9-V9-Q9/(1+Policy_Sched!$K9)+Z10/(1+Policy_Sched!$K9))
A10: =A9+1 | B10: =IF($A10>LastT,0,IF($B$3="exps",B9*(1+InflRate+IF($A10>=T0,$G$3,0)),B9/(1+InflRate))) | C10: =IF($A10>LastT,0,IF(AND($D$3<>0,$A10>=T0,Policy_Sched!$B10<LastAge),1+$D$3*$E$3,1)) | D10: =IF($A10>LastT,0,IF($C$3="up",MIN(Policy_Sched!$E10*(1+IF($A10>=T0,$E$3,0)),$F$3),IF($C$3="down",MAX(Policy_Sched!$E10*(1-IF($A10>=T0,$E$3,0)),Policy_Sched!$E10-$F$3),Policy_Sched!$E10))) | E10: =IF($A10>LastT,0,J9-K9-L9) | F10: =IF($A10>LastT,0,IF($A10=PolicyTerm,E10,0)) | G10: =IF($A10>LastT,0,E10-F10) | H10: =IF($A10=0,PolicyCount,0) | I10: =IF($A10>LastT,0,IF(AND($C$3="mass",$A10=T0),(G10+H10)*$E$3,0)) | J10: =IF($A10>LastT,0,G10+H10-I10) | K10: =IF($A10>LastT,0,J10*Policy_Sched!$C10*Policy_Sched!$D10*C10) | L10: =J10*D10 | M10: =IF($A10>LastT,0,(SizeAnnPrem*ExpsMaintAnnPrem+(SumAssured*ExpsMaintSA+ExpsMaintPol)*B10)*(1+IF($B$3="exps",$E$3,0))) | N10: =SizePremium*J10 | O10: =SumAssured*K10 | P10: =Policy_Sched!$I10*(L10+I10) | Q10: =O10+P10 | R10: =IF($A10=0,SizeExpsAcq0*H10,0) | S10: =IF($A10=0,SizeExpsCommInit0*J10,0) | T10: =Policy_Sched!$J10*J10 | U10: =M10*J10 | V10: =S10+T10+R10+U10 | W10: =IF($A10>LastT,0,N10+W11/(1+Policy_Sched!$K10)) | X10: =IF($A10>LastT,0,(-Q10+X11)/(1+Policy_Sched!$K10)) | Y10: =IF($A10>LastT,0,-V10+Y11/(1+Policy_Sched!$K10)) | Z10: =W10+Y10+X10 | AA10: =IF($A10>LastT,0,N10-V10-Q10/(1+Policy_Sched!$K10)+Z11/(1+Policy_Sched!$K10))
A11: =A10+1 | B11: =IF($A11>LastT,0,IF($B$3="exps",B10*(1+InflRate+IF($A11>=T0,$G$3,0)),B10/(1+InflRate))) | C11: =IF($A11>LastT,0,IF(AND($D$3<>0,$A11>=T0,Policy_Sched!$B11<LastAge),1+$D$3*$E$3,1)) | D11: =IF($A11>LastT,0,IF($C$3="up",MIN(Policy_Sched!$E11*(1+IF($A11>=T0,$E$3,0)),$F$3),IF($C$3="down",MAX(Policy_Sched!$E11*(1-IF($A11>=T0,$E$3,0)),Policy_Sched!$E11-$F$3),Policy_Sched!$E11))) | E11: =IF($A11>LastT,0,J10-K10-L10) | F11: =IF($A11>LastT,0,IF($A11=PolicyTerm,E11,0)) | G11: =IF($A11>LastT,0,E11-F11) | H11: =IF($A11=0,PolicyCount,0) | I11: =IF($A11>LastT,0,IF(AND($C$3="mass",$A11=T0),(G11+H11)*$E$3,0)) | J11: =IF($A11>LastT,0,G11+H11-I11) | K11: =IF($A11>LastT,0,J11*Policy_Sched!$C11*Policy_Sched!$D11*C11) | L11: =J11*D11 | M11: =IF($A11>LastT,0,(SizeAnnPrem*ExpsMaintAnnPrem+(SumAssured*ExpsMaintSA+ExpsMaintPol)*B11)*(1+IF($B$3="exps",$E$3,0))) | N11: =SizePremium*J11 | O11: =SumAssured*K11 | P11: =Policy_Sched!$I11*(L11+I11) | Q11: =O11+P11 | R11: =IF($A11=0,SizeExpsAcq0*H11,0) | S11: =IF($A11=0,SizeExpsCommInit0*J11,0) | T11: =Policy_Sched!$J11*J11 | U11: =M11*J11 | V11: =S11+T11+R11+U11 | W11: =IF($A11>LastT,0,N11+W12/(1+Policy_Sched!$K11)) | X11: =IF($A11>LastT,0,(-Q11+X12)/(1+Policy_Sched!$K11)) | Y11: =IF($A11>LastT,0,-V11+Y12/(1+Policy_Sched!$K11)) | Z11: =W11+Y11+X11 | AA11: =IF($A11>LastT,0,N11-V11-Q11/(1+Policy_Sched!$K11)+Z12/(1+Policy_Sched!$K11))
A12: =A11+1 | B12: =IF($A12>LastT,0,IF($B$3="exps",B11*(1+InflRate+IF($A12>=T0,$G$3,0)),B11/(1+InflRate))) | C12: =IF($A12>LastT,0,IF(AND($D$3<>0,$A12>=T0,Policy_Sched!$B12<LastAge),1+$D$3*$E$3,1)) | D12: =IF($A12>LastT,0,IF($C$3="up",MIN(Policy_Sched!$E12*(1+IF($A12>=T0,$E$3,0)),$F$3),IF($C$3="down",MAX(Policy_Sched!$E12*(1-IF($A12>=T0,$E$3,0)),Policy_Sched!$E12-$F$3),Policy_Sched!$E12))) | E12: =IF($A12>LastT,0,J11-K11-L11) | F12: =IF($A12>LastT,0,IF($A12=PolicyTerm,E12,0)) | G12: =IF($A12>LastT,0,E12-F12) | H12: =IF($A12=0,PolicyCount,0) | I12: =IF($A12>LastT,0,IF(AND($C$3="mass",$A12=T0),(G12+H12)*$E$3,0)) | J12: =IF($A12>LastT,0,G12+H12-I12) | K12: =IF($A12>LastT,0,J12*Policy_Sched!$C12*Policy_Sched!$D12*C12) | L12: =J12*D12 | M12: =IF($A12>LastT,0,(SizeAnnPrem*ExpsMaintAnnPrem+(SumAssured*ExpsMaintSA+ExpsMaintPol)*B12)*(1+IF($B$3="exps",$E$3,0))) | N12: =SizePremium*J12 | O12: =SumAssured*K12 | P12: =Policy_Sched!$I12*(L12+I12) | Q12: =O12+P12 | R12: =IF($A12=0,SizeExpsAcq0*H12,0) | S12: =IF($A12=0,SizeExpsCommInit0*J12,0) | T12: =Policy_Sched!$J12*J12 | U12: =M12*J12 | V12: =S12+T12+R12+U12 | W12: =IF($A12>LastT,0,N12+W13/(1+Policy_Sched!$K12)) | X12: =IF($A12>LastT,0,(-Q12+X13)/(1+Policy_Sched!$K12)) | Y12: =IF($A12>LastT,0,-V12+Y13/(1+Policy_Sched!$K12)) | Z12: =W12+Y12+X12 | AA12: =IF($A12>LastT,0,N12-V12-Q12/(1+Policy_Sched!$K12)+Z13/(1+Policy_Sched!$K12))
A13: =A12+1 | B13: =IF($A13>LastT,0,IF($B$3="exps",B12*(1+InflRate+IF($A13>=T0,$G$3,0)),B12/(1+InflRate))) | C13: =IF($A13>LastT,0,IF(AND($D$3<>0,$A13>=T0,Policy_Sched!$B13<LastAge),1+$D$3*$E$3,1)) | D13: =IF($A13>LastT,0,IF($C$3="up",MIN(Policy_Sched!$E13*(1+IF($A13>=T0,$E$3,0)),$F$3),IF($C$3="down",MAX(Policy_Sched!$E13*(1-IF($A13>=T0,$E$3,0)),Policy_Sched!$E13-$F$3),Policy_Sched!$E13))) | E13: =IF($A13>LastT,0,J12-K12-L12) | F13: =IF($A13>LastT,0,IF($A13=PolicyTerm,E13,0)) | G13: =IF($A13>LastT,0,E13-F13) | H13: =IF($A13=0,PolicyCount,0) | I13: =IF($A13>LastT,0,IF(AND($C$3="mass",$A13=T0),(G13+H13)*$E$3,0)) | J13: =IF($A13>LastT,0,G13+H13-I13) | K13: =IF($A13>LastT,0,J13*Policy_Sched!$C13*Policy_Sched!$D13*C13) | L13: =J13*D13 | M13: =IF($A13>LastT,0,(SizeAnnPrem*ExpsMaintAnnPrem+(SumAssured*ExpsMaintSA+ExpsMaintPol)*B13)*(1+IF($B$3="exps",$E$3,0))) | N13: =SizePremium*J13 | O13: =SumAssured*K13 | P13: =Policy_Sched!$I13*(L13+I13) | Q13: =O13+P13 | R13: =IF($A13=0,SizeExpsAcq0*H13,0) | S13: =IF($A13=0,SizeExpsCommInit0*J13,0) | T13: =Policy_Sched!$J13*J13 | U13: =M13*J13 | V13: =S13+T13+R13+U13 | W13: =IF($A13>LastT,0,N13+W14/(1+Policy_Sched!$K13)) | X13: =IF($A13>LastT,0,(-Q13+X14)/(1+Policy_Sched!$K13)) | Y13: =IF($A13>LastT,0,-V13+Y14/(1+Policy_Sched!$K13)) | Z13: =W13+Y13+X13 | AA13: =IF($A13>LastT,0,N13-V13-Q13/(1+Policy_Sched!$K13)+Z14/(1+Policy_Sched!$K13))
A14: =A13+1 | B14: =IF($A14>LastT,0,IF($B$3="exps",B13*(1+InflRate+IF($A14>=T0,$G$3,0)),B13/(1+InflRate))) | C14: =IF($A14>LastT,0,IF(AND($D$3<>0,$A14>=T0,Policy_Sched!$B14<LastAge),1+$D$3*$E$3,1)) | D14: =IF($A14>LastT,0,IF($C$3="up",MIN(Policy_Sched!$E14*(1+IF($A14>=T0,$E$3,0)),$F$3),IF($C$3="down",MAX(Policy_Sched!$E14*(1-IF($A14>=T0,$E$3,0)),Policy_Sched!$E14-$F$3),Policy_Sched!$E14))) | E14: =IF($A14>LastT,0,J13-K13-L13) | F14: =IF($A14>LastT,0,IF($A14=PolicyTerm,E14,0)) | G14: =IF($A14>LastT,0,E14-F14) | H14: =IF($A14=0,PolicyCount,0) | I14: =IF($A14>LastT,0,IF(AND($C$3="mass",$A14=T0),(G14+H14)*$E$3,0)) | J14: =IF($A14>LastT,0,G14+H14-I14) | K14: =IF($A14>LastT,0,J14*Policy_Sched!$C14*Policy_Sched!$D14*C14) | L14: =J14*D14 | M14: =IF($A14>LastT,0,(SizeAnnPrem*ExpsMaintAnnPrem+(SumAssured*ExpsMaintSA+ExpsMaintPol)*B14)*(1+IF($B$3="exps",$E$3,0))) | N14: =SizePremium*J14 | O14: =SumAssured*K14 | P14: =Policy_Sched!$I14*(L14+I14) | Q14: =O14+P14 | R14: =IF($A14=0,SizeExpsAcq0*H14,0) | S14: =IF($A14=0,SizeExpsCommInit0*J14,0) | T14: =Policy_Sched!$J14*J14 | U14: =M14*J14 | V14: =S14+T14+R14+U14 | W14: =IF($A14>LastT,0,N14+W15/(1+Policy_Sched!$K14)) | X14: =IF($A14>LastT,0,(-Q14+X15)/(1+Policy_Sched!$K14)) | Y14: =IF($A14>LastT,0,-V14+Y15/(1+Policy_Sched!$K14)) | Z14: =W14+Y14+X14 | AA14: =IF($A14>LastT,0,N14-V14-Q14/(1+Policy_Sched!$K14)+Z15/(1+Policy_Sched!$K14))
A15: =A14+1 | B15: =IF($A15>LastT,0,IF($B$3="exps",B14*(1+InflRate+IF($A15>=T0,$G$3,0)),B14/(1+InflRate))) | C15: =IF($A15>LastT,0,IF(AND($D$3<>0,$A15>=T0,Policy_Sched!$B15<LastAge),1+$D$3*$E$3,1)) | D15: =IF($A15>LastT,0,IF($C$3="up",MIN(Policy_Sched!$E15*(1+IF($A15>=T0,$E$3,0)),$F$3),IF($C$3="down",MAX(Policy_Sched!$E15*(1-IF($A15>=T0,$E$3,0)),Policy_Sched!$E15-$F$3),Policy_Sched!$E15))) | E15: =IF($A15>LastT,0,J14-K14-L14) | F15: =IF($A15>LastT,0,IF($A15=PolicyTerm,E15,0)) | G15: =IF($A15>LastT,0,E15-F15) | H15: =IF($A15=0,PolicyCount,0) | I15: =IF($A15>LastT,0,IF(AND($C$3="mass",$A15=T0),(G15+H15)*$E$3,0)) | J15: =IF($A15>LastT,0,G15+H15-I15) | K15: =IF($A15>LastT,0,J15*Policy_Sched!$C15*Policy_Sched!$D15*C15) | L15: =J15*D15 | M15: =IF($A15>LastT,0,(SizeAnnPrem*ExpsMaintAnnPrem+(SumAssured*ExpsMaintSA+ExpsMaintPol)*B15)*(1+IF($B$3="exps",$E$3,0))) | N15: =SizePremium*J15 | O15: =SumAssured*K15 | P15: =Policy_Sched!$I15*(L15+I15) | Q15: =O15+P15 | R15: =IF($A15=0,SizeExpsAcq0*H15,0) | S15: =IF($A15=0,SizeExpsCommInit0*J15,0) | T15: =Policy_Sched!$J15*J15 | U15: =M15*J15 | V15: =S15+T15+R15+U15 | W15: =IF($A15>LastT,0,N15+W16/(1+Policy_Sched!$K15)) | X15: =IF($A15>LastT,0,(-Q15+X16)/(1+Policy_Sched!$K15)) | Y15: =IF($A15>LastT,0,-V15+Y16/(1+Policy_Sched!$K15)) | Z15: =W15+Y15+X15 | AA15: =IF($A15>LastT,0,N15-V15-Q15/(1+Policy_Sched!$K15)+Z16/(1+Policy_Sched!$K15))
A16: =A15+1 | B16: =IF($A16>LastT,0,IF($B$3="exps",B15*(1+InflRate+IF($A16>=T0,$G$3,0)),B15/(1+InflRate))) | C16: =IF($A16>LastT,0,IF(AND($D$3<>0,$A16>=T0,Policy_Sched!$B16<LastAge),1+$D$3*$E$3,1)) | D16: =IF($A16>LastT,0,IF($C$3="up",MIN(Policy_Sched!$E16*(1+IF($A16>=T0,$E$3,0)),$F$3),IF($C$3="down",MAX(Policy_Sched!$E16*(1-IF($A16>=T0,$E$3,0)),Policy_Sched!$E16-$F$3),Policy_Sched!$E16))) | E16: =IF($A16>LastT,0,J15-K15-L15) | F16: =IF($A16>LastT,0,IF($A16=PolicyTerm,E16,0)) | G16: =IF($A16>LastT,0,E16-F16) | H16: =IF($A16=0,PolicyCount,0) | I16: =IF($A16>LastT,0,IF(AND($C$3="mass",$A16=T0),(G16+H16)*$E$3,0)) | J16: =IF($A16>LastT,0,G16+H16-I16) | K16: =IF($A16>LastT,0,J16*Policy_Sched!$C16*Policy_Sched!$D16*C16) | L16: =J16*D16 | M16: =IF($A16>LastT,0,(SizeAnnPrem*ExpsMaintAnnPrem+(SumAssured*ExpsMaintSA+ExpsMaintPol)*B16)*(1+IF($B$3="exps",$E$3,0))) | N16: =SizePremium*J16 | O16: =SumAssured*K16 | P16: =Policy_Sched!$I16*(L16+I16) | Q16: =O16+P16 | R16: =IF($A16=0,SizeExpsAcq0*H16,0) | S16: =IF($A16=0,SizeExpsCommInit0*J16,0) | T16: =Policy_Sched!$J16*J16 | U16: =M16*J16 | V16: =S16+T16+R16+U16 | W16: =IF($A16>LastT,0,N16+W17/(1+Policy_Sched!$K16)) | X16: =IF($A16>LastT,0,(-Q16+X17)/(1+Policy_Sched!$K16)) | Y16: =IF($A16>LastT,0,-V16+Y17/(1+Policy_Sched!$K16)) | Z16: =W16+Y16+X16 | AA16: =IF($A16>LastT,0,N16-V16-Q16/(1+Policy_Sched!$K16)+Z17/(1+Policy_Sched!$K16))
A17: =A16+1 | B17: =IF($A17>LastT,0,IF($B$3="exps",B16*(1+InflRate+IF($A17>=T0,$G$3,0)),B16/(1+InflRate))) | C17: =IF($A17>LastT,0,IF(AND($D$3<>0,$A17>=T0,Policy_Sched!$B17<LastAge),1+$D$3*$E$3,1)) | D17: =IF($A17>LastT,0,IF($C$3="up",MIN(Policy_Sched!$E17*(1+IF($A17>=T0,$E$3,0)),$F$3),IF($C$3="down",MAX(Policy_Sched!$E17*(1-IF($A17>=T0,$E$3,0)),Policy_Sched!$E17-$F$3),Policy_Sched!$E17))) | E17: =IF($A17>LastT,0,J16-K16-L16) | F17: =IF($A17>LastT,0,IF($A17=PolicyTerm,E17,0)) | G17: =IF($A17>LastT,0,E17-F17) | H17: =IF($A17=0,PolicyCount,0) | I17: =IF($A17>LastT,0,IF(AND($C$3="mass",$A17=T0),(G17+H17)*$E$3,0)) | J17: =IF($A17>LastT,0,G17+H17-I17) | K17: =IF($A17>LastT,0,J17*Policy_Sched!$C17*Policy_Sched!$D17*C17) | L17: =J17*D17 | M17: =IF($A17>LastT,0,(SizeAnnPrem*ExpsMaintAnnPrem+(SumAssured*ExpsMaintSA+ExpsMaintPol)*B17)*(1+IF($B$3="exps",$E$3,0))) | N17: =SizePremium*J17 | O17: =SumAssured*K17 | P17: =Policy_Sched!$I17*(L17+I17) | Q17: =O17+P17 | R17: =IF($A17=0,SizeExpsAcq0*H17,0) | S17: =IF($A17=0,SizeExpsCommInit0*J17,0) | T17: =Policy_Sched!$J17*J17 | U17: =M17*J17 | V17: =S17+T17+R17+U17 | W17: =IF($A17>LastT,0,N17+W18/(1+Policy_Sched!$K17)) | X17: =IF($A17>LastT,0,(-Q17+X18)/(1+Policy_Sched!$K17)) | Y17: =IF($A17>LastT,0,-V17+Y18/(1+Policy_Sched!$K17)) | Z17: =W17+Y17+X17 | AA17: =IF($A17>LastT,0,N17-V17-Q17/(1+Policy_Sched!$K17)+Z18/(1+Policy_Sched!$K17))
A18: =A17+1 | B18: =IF($A18>LastT,0,IF($B$3="exps",B17*(1+InflRate+IF($A18>=T0,$G$3,0)),B17/(1+InflRate))) | C18: =IF($A18>LastT,0,IF(AND($D$3<>0,$A18>=T0,Policy_Sched!$B18<LastAge),1+$D$3*$E$3,1)) | D18: =IF($A18>LastT,0,IF($C$3="up",MIN(Policy_Sched!$E18*(1+IF($A18>=T0,$E$3,0)),$F$3),IF($C$3="down",MAX(Policy_Sched!$E18*(1-IF($A18>=T0,$E$3,0)),Policy_Sched!$E18-$F$3),Policy_Sched!$E18))) | E18: =IF($A18>LastT,0,J17-K17-L17) | F18: =IF($A18>LastT,0,IF($A18=PolicyTerm,E18,0)) | G18: =IF($A18>LastT,0,E18-F18) | H18: =IF($A18=0,PolicyCount,0) | I18: =IF($A18>LastT,0,IF(AND($C$3="mass",$A18=T0),(G18+H18)*$E$3,0)) | J18: =IF($A18>LastT,0,G18+H18-I18) | K18: =IF($A18>LastT,0,J18*Policy_Sched!$C18*Policy_Sched!$D18*C18) | L18: =J18*D18 | M18: =IF($A18>LastT,0,(SizeAnnPrem*ExpsMaintAnnPrem+(SumAssured*ExpsMaintSA+ExpsMaintPol)*B18)*(1+IF($B$3="exps",$E$3,0))) | N18: =SizePremium*J18 | O18: =SumAssured*K18 | P18: =Policy_Sched!$I18*(L18+I18) | Q18: =O18+P18 | R18: =IF($A18=0,SizeExpsAcq0*H18,0) | S18: =IF($A18=0,SizeExpsCommInit0*J18,0) | T18: =Policy_Sched!$J18*J18 | U18: =M18*J18 | V18: =S18+T18+R18+U18 | W18: =IF($A18>LastT,0,N18+W19/(1+Policy_Sched!$K18)) | X18: =IF($A18>LastT,0,(-Q18+X19)/(1+Policy_Sched!$K18)) | Y18: =IF($A18>LastT,0,-V18+Y19/(1+Policy_Sched!$K18)) | Z18: =W18+Y18+X18 | AA18: =IF($A18>LastT,0,N18-V18-Q18/(1+Policy_Sched!$K18)+Z19/(1+Policy_Sched!$K18))
A19: =A18+1 | B19: =IF($A19>LastT,0,IF($B$3="exps",B18*(1+InflRate+IF($A19>=T0,$G$3,0)),B18/(1+InflRate))) | C19: =IF($A19>LastT,0,IF(AND($D$3<>0,$A19>=T0,Policy_Sched!$B19<LastAge),1+$D$3*$E$3,1)) | D19: =IF($A19>LastT,0,IF($C$3="up",MIN(Policy_Sched!$E19*(1+IF($A19>=T0,$E$3,0)),$F$3),IF($C$3="down",MAX(Policy_Sched!$E19*(1-IF($A19>=T0,$E$3,0)),Policy_Sched!$E19-$F$3),Policy_Sched!$E19))) | E19: =IF($A19>LastT,0,J18-K18-L18) | F19: =IF($A19>LastT,0,IF($A19=PolicyTerm,E19,0)) | G19: =IF($A19>LastT,0,E19-F19) | H19: =IF($A19=0,PolicyCount,0) | I19: =IF($A19>LastT,0,IF(AND($C$3="mass",$A19=T0),(G19+H19)*$E$3,0)) | J19: =IF($A19>LastT,0,G19+H19-I19) | K19: =IF($A19>LastT,0,J19*Policy_Sched!$C19*Policy_Sched!$D19*C19) | L19: =J19*D19 | M19: =IF($A19>LastT,0,(SizeAnnPrem*ExpsMaintAnnPrem+(SumAssured*ExpsMaintSA+ExpsMaintPol)*B19)*(1+IF($B$3="exps",$E$3,0))) | N19: =SizePremium*J19 | O19: =SumAssured*K19 | P19: =Policy_Sched!$I19*(L19+I19) | Q19: =O19+P19 | R19: =IF($A19=0,SizeExpsAcq0*H19,0) | S19: =IF($A19=0,SizeExpsCommInit0*J19,0) | T19: =Policy_Sched!$J19*J19 | U19: =M19*J19 | V19: =S19+T19+R19+U19 | W19: =IF($A19>LastT,0,N19+W20/(1+Policy_Sched!$K19)) | X19: =IF($A19>LastT,0,(-Q19+X20)/(1+Policy_Sched!$K19)) | Y19: =IF($A19>LastT,0,-V19+Y20/(1+Policy_Sched!$K19)) | Z19: =W19+Y19+X19 | AA19: =IF($A19>LastT,0,N19-V19-Q19/(1+Policy_Sched!$K19)+Z20/(1+Policy_Sched!$K19))
... A110: =A109+1 | B110: =IF($A110>LastT,0,IF($B$3="exps",B109*(1+InflRate+IF($A110>=T0,$G$3,0)),B109/(1+InflRate))) | C110: =IF($A110>LastT,0,IF(AND($D$3<>0,$A110>=T0,Policy_Sched!$B110<LastAge),1+$D$3*$E$3,1)) | D110: =IF($A110>LastT,0,IF($C$3="up",MIN(Policy_Sched!$E110*(1+IF($A110>=T0,$E$3,0)),$F$3),IF($C$3="down",MAX(Policy_Sched!$E110*(1-IF($A110>=T0,$E$3,0)),Policy_Sched!$E110-$F$3),Policy_Sched!$E110))) | E110: =IF($A110>LastT,0,J109-K109-L109) | F110: =IF($A110>LastT,0,IF($A110=PolicyTerm,E110,0)) | G110: =IF($A110>LastT,0,E110-F110) | H110: =IF($A110=0,PolicyCount,0) | I110: =IF($A110>LastT,0,IF(AND($C$3="mass",$A110=T0),(G110+H110)*$E$3,0)) | J110: =IF($A110>LastT,0,G110+H110-I110) | K110: =IF($A110>LastT,0,J110*Policy_Sched!$C110*Policy_Sched!$D110*C110) | L110: =J110*D110 | M110: =IF($A110>LastT,0,(SizeAnnPrem*ExpsMaintAnnPrem+(SumAssured*ExpsMaintSA+ExpsMaintPol)*B110)*(1+IF($B$3="exps",$E$3,0))) | N110: =SizePremium*J110 | O110: =SumAssured*K110 | P110: =Policy_Sched!$I110*(L110+I110) | Q110: =O110+P110 | R110: =IF($A110=0,SizeExpsAcq0*H110,0) | S110: =IF($A110=0,SizeExpsCommInit0*J110,0) | T110: =Policy_Sched!$J110*J110 | U110: =M110*J110 | V110: =S110+T110+R110+U110 | W110: =IF($A110>LastT,0,N110+W111/(1+Policy_Sched!$K110)) | X110: =IF($A110>LastT,0,(-Q110+X111)/(1+Policy_Sched!$K110)) | Y110: =IF($A110>LastT,0,-V110+Y111/(1+Policy_Sched!$K110)) | Z110: =W110+Y110+X110 | AA110: =IF($A110>LastT,0,N110-V110-Q110/(1+Policy_Sched!$K110)+Z111/(1+Policy_Sched!$K110))

Sheet Proj_Mort
A1: Liability projection — mortality stress (+15% rates from t0). lifelib SCR_life.Projection['mort', None, None]
B2: Risk | C2: Shock | D2: Risk sign | E2: Shock factor | F2: Shock limit | G2: Inflation shock
B3: mort | D3: 1 | E3: =IFERROR(INDEX(FactorVals,MATCH($B$3&"|"&$C$3&"||",FactorKeys,0)),0) | F3: =IFERROR(INDEX(FactorVals,MATCH($B$3&"|"&$C$3&"||limit",FactorKeys,0)),0) | G3: =IFERROR(INDEX(FactorVals,MATCH($B$3&"|||inflation",FactorKeys,0)),0)
B4: Risk | C4: Shock | E4: Factor
A5: t | B5: Inflation factor | C5: Mortality shock factor | D5: Surrender rate | E5: In force: end | F5: Maturities | G5: In force: after maturity | H5: New business | I5: Mass lapse | J5: In force: beginning | K5: Deaths | L5: Surrenders | M5: Maint expense pp | N5: Premium income | O5: Death benefits | P5: Surrender benefits | Q5: Total benefits | R5: Acquisition expenses | S5: Initial commission | T5: Renewal commission | U5: Maintenance expenses | V5: Total expenses | W5: PV premiums | X5: PV benefits | Y5: PV expenses | Z5: PV net cashflow | AA5: PV net cf (fwd check)
A6: t | B6: InflFactor | C6: MortRateFactor | D6: SurrRate | E6: PolsIF_End | F6: PolsMaturity | G6: PolsIF_Beg | H6: PolsNewBiz | I6: PolsSurrMass | J6: PolsIF_Beg1 | K6: PolsDeath | L6: PolsSurr | M6: SizeExpsMaint | N6: PremIncome | O6: BenefitDeath | P6: BenefitSurr | Q6: BenefitTotal | R6: ExpsAcq | S6: ExpsCommInit | T6: ExpsCommRen | U6: ExpsMaint | V6: ExpsTotal | W6: PV_PremIncome | X6: PV_BenefitTotal | Y6: PV_ExpsTotal | Z6: PV_NetCashflow | AA6: PV_NetCashflowForCheck
A7: 0 | B7: =1 | C7: =IF($A7>LastT,0,IF(AND($D$3<>0,$A7>=T0,Policy_Sched!$B7<LastAge),1+$D$3*$E$3,1)) | D7: =IF($A7>LastT,0,IF($C$3="up",MIN(Policy_Sched!$E7*(1+IF($A7>=T0,$E$3,0)),$F$3),IF($C$3="down",MAX(Policy_Sched!$E7*(1-IF($A7>=T0,$E$3,0)),Policy_Sched!$E7-$F$3),Policy_Sched!$E7))) | E7: =0 | F7: =IF($A7>LastT,0,IF($A7=PolicyTerm,E7,0)) | G7: =IF($A7>LastT,0,E7-F7) | H7: =IF($A7=0,PolicyCount,0) | I7: =IF($A7>LastT,0,IF(AND($C$3="mass",$A7=T0),(G7+H7)*$E$3,0)) | J7: =IF($A7>LastT,0,G7+H7-I7) | K7: =IF($A7>LastT,0,J7*Policy_Sched!$C7*Policy_Sched!$D7*C7) | L7: =J7*D7 | M7: =IF($A7>LastT,0,(SizeAnnPrem*ExpsMaintAnnPrem+(SumAssured*ExpsMaintSA+ExpsMaintPol)*B7)*(1+IF($B$3="exps",$E$3,0))) | N7: =SizePremium*J7 | O7: =SumAssured*K7 | P7: =Policy_Sched!$I7*(L7+I7) | Q7: =O7+P7 | R7: =IF($A7=0,SizeExpsAcq0*H7,0) | S7: =IF($A7=0,SizeExpsCommInit0*J7,0) | T7: =Policy_Sched!$J7*J7 | U7: =M7*J7 | V7: =S7+T7+R7+U7 | W7: =IF($A7>LastT,0,N7+W8/(1+Policy_Sched!$K7)) | X7: =IF($A7>LastT,0,(-Q7+X8)/(1+Policy_Sched!$K7)) | Y7: =IF($A7>LastT,0,-V7+Y8/(1+Policy_Sched!$K7)) | Z7: =W7+Y7+X7 | AA7: =IF($A7>LastT,0,N7-V7-Q7/(1+Policy_Sched!$K7)+Z8/(1+Policy_Sched!$K7))
A8: =A7+1 | B8: =IF($A8>LastT,0,IF($B$3="exps",B7*(1+InflRate+IF($A8>=T0,$G$3,0)),B7/(1+InflRate))) | C8: =IF($A8>LastT,0,IF(AND($D$3<>0,$A8>=T0,Policy_Sched!$B8<LastAge),1+$D$3*$E$3,1)) | D8: =IF($A8>LastT,0,IF($C$3="up",MIN(Policy_Sched!$E8*(1+IF($A8>=T0,$E$3,0)),$F$3),IF($C$3="down",MAX(Policy_Sched!$E8*(1-IF($A8>=T0,$E$3,0)),Policy_Sched!$E8-$F$3),Policy_Sched!$E8))) | E8: =IF($A8>LastT,0,J7-K7-L7) | F8: =IF($A8>LastT,0,IF($A8=PolicyTerm,E8,0)) | G8: =IF($A8>LastT,0,E8-F8) | H8: =IF($A8=0,PolicyCount,0) | I8: =IF($A8>LastT,0,IF(AND($C$3="mass",$A8=T0),(G8+H8)*$E$3,0)) | J8: =IF($A8>LastT,0,G8+H8-I8) | K8: =IF($A8>LastT,0,J8*Policy_Sched!$C8*Policy_Sched!$D8*C8) | L8: =J8*D8 | M8: =IF($A8>LastT,0,(SizeAnnPrem*ExpsMaintAnnPrem+(SumAssured*ExpsMaintSA+ExpsMaintPol)*B8)*(1+IF($B$3="exps",$E$3,0))) | N8: =SizePremium*J8 | O8: =SumAssured*K8 | P8: =Policy_Sched!$I8*(L8+I8) | Q8: =O8+P8 | R8: =IF($A8=0,SizeExpsAcq0*H8,0) | S8: =IF($A8=0,SizeExpsCommInit0*J8,0) | T8: =Policy_Sched!$J8*J8 | U8: =M8*J8 | V8: =S8+T8+R8+U8 | W8: =IF($A8>LastT,0,N8+W9/(1+Policy_Sched!$K8)) | X8: =IF($A8>LastT,0,(-Q8+X9)/(1+Policy_Sched!$K8)) | Y8: =IF($A8>LastT,0,-V8+Y9/(1+Policy_Sched!$K8)) | Z8: =W8+Y8+X8 | AA8: =IF($A8>LastT,0,N8-V8-Q8/(1+Policy_Sched!$K8)+Z9/(1+Policy_Sched!$K8))
A9: =A8+1 | B9: =IF($A9>LastT,0,IF($B$3="exps",B8*(1+InflRate+IF($A9>=T0,$G$3,0)),B8/(1+InflRate))) | C9: =IF($A9>LastT,0,IF(AND($D$3<>0,$A9>=T0,Policy_Sched!$B9<LastAge),1+$D$3*$E$3,1)) | D9: =IF($A9>LastT,0,IF($C$3="up",MIN(Policy_Sched!$E9*(1+IF($A9>=T0,$E$3,0)),$F$3),IF($C$3="down",MAX(Policy_Sched!$E9*(1-IF($A9>=T0,$E$3,0)),Policy_Sched!$E9-$F$3),Policy_Sched!$E9))) | E9: =IF($A9>LastT,0,J8-K8-L8) | F9: =IF($A9>LastT,0,IF($A9=PolicyTerm,E9,0)) | G9: =IF($A9>LastT,0,E9-F9) | H9: =IF($A9=0,PolicyCount,0) | I9: =IF($A9>LastT,0,IF(AND($C$3="mass",$A9=T0),(G9+H9)*$E$3,0)) | J9: =IF($A9>LastT,0,G9+H9-I9) | K9: =IF($A9>LastT,0,J9*Policy_Sched!$C9*Policy_Sched!$D9*C9) | L9: =J9*D9 | M9: =IF($A9>LastT,0,(SizeAnnPrem*ExpsMaintAnnPrem+(SumAssured*ExpsMaintSA+ExpsMaintPol)*B9)*(1+IF($B$3="exps",$E$3,0))) | N9: =SizePremium*J9 | O9: =SumAssured*K9 | P9: =Policy_Sched!$I9*(L9+I9) | Q9: =O9+P9 | R9: =IF($A9=0,SizeExpsAcq0*H9,0) | S9: =IF($A9=0,SizeExpsCommInit0*J9,0) | T9: =Policy_Sched!$J9*J9 | U9: =M9*J9 | V9: =S9+T9+R9+U9 | W9: =IF($A9>LastT,0,N9+W10/(1+Policy_Sched!$K9)) | X9: =IF($A9>LastT,0,(-Q9+X10)/(1+Policy_Sched!$K9)) | Y9: =IF($A9>LastT,0,-V9+Y10/(1+Policy_Sched!$K9)) | Z9: =W9+Y9+X9 | AA9: =IF($A9>LastT,0,N9-V9-Q9/(1+Policy_Sched!$K9)+Z10/(1+Policy_Sched!$K9))
A10: =A9+1 | B10: =IF($A10>LastT,0,IF($B$3="exps",B9*(1+InflRate+IF($A10>=T0,$G$3,0)),B9/(1+InflRate))) | C10: =IF($A10>LastT,0,IF(AND($D$3<>0,$A10>=T0,Policy_Sched!$B10<LastAge),1+$D$3*$E$3,1)) | D10: =IF($A10>LastT,0,IF($C$3="up",MIN(Policy_Sched!$E10*(1+IF($A10>=T0,$E$3,0)),$F$3),IF($C$3="down",MAX(Policy_Sched!$E10*(1-IF($A10>=T0,$E$3,0)),Policy_Sched!$E10-$F$3),Policy_Sched!$E10))) | E10: =IF($A10>LastT,0,J9-K9-L9) | F10: =IF($A10>LastT,0,IF($A10=PolicyTerm,E10,0)) | G10: =IF($A10>LastT,0,E10-F10) | H10: =IF($A10=0,PolicyCount,0) | I10: =IF($A10>LastT,0,IF(AND($C$3="mass",$A10=T0),(G10+H10)*$E$3,0)) | J10: =IF($A10>LastT,0,G10+H10-I10) | K10: =IF($A10>LastT,0,J10*Policy_Sched!$C10*Policy_Sched!$D10*C10) | L10: =J10*D10 | M10: =IF($A10>LastT,0,(SizeAnnPrem*ExpsMaintAnnPrem+(SumAssured*ExpsMaintSA+ExpsMaintPol)*B10)*(1+IF($B$3="exps",$E$3,0))) | N10: =SizePremium*J10 | O10: =SumAssured*K10 | P10: =Policy_Sched!$I10*(L10+I10) | Q10: =O10+P10 | R10: =IF($A10=0,SizeExpsAcq0*H10,0) | S10: =IF($A10=0,SizeExpsCommInit0*J10,0) | T10: =Policy_Sched!$J10*J10 | U10: =M10*J10 | V10: =S10+T10+R10+U10 | W10: =IF($A10>LastT,0,N10+W11/(1+Policy_Sched!$K10)) | X10: =IF($A10>LastT,0,(-Q10+X11)/(1+Policy_Sched!$K10)) | Y10: =IF($A10>LastT,0,-V10+Y11/(1+Policy_Sched!$K10)) | Z10: =W10+Y10+X10 | AA10: =IF($A10>LastT,0,N10-V10-Q10/(1+Policy_Sched!$K10)+Z11/(1+Policy_Sched!$K10))
A11: =A10+1 | B11: =IF($A11>LastT,0,IF($B$3="exps",B10*(1+InflRate+IF($A11>=T0,$G$3,0)),B10/(1+InflRate))) | C11: =IF($A11>LastT,0,IF(AND($D$3<>0,$A11>=T0,Policy_Sched!$B11<LastAge),1+$D$3*$E$3,1)) | D11: =IF($A11>LastT,0,IF($C$3="up",MIN(Policy_Sched!$E11*(1+IF($A11>=T0,$E$3,0)),$F$3),IF($C$3="down",MAX(Policy_Sched!$E11*(1-IF($A11>=T0,$E$3,0)),Policy_Sched!$E11-$F$3),Policy_Sched!$E11))) | E11: =IF($A11>LastT,0,J10-K10-L10) | F11: =IF($A11>LastT,0,IF($A11=PolicyTerm,E11,0)) | G11: =IF($A11>LastT,0,E11-F11) | H11: =IF($A11=0,PolicyCount,0) | I11: =IF($A11>LastT,0,IF(AND($C$3="mass",$A11=T0),(G11+H11)*$E$3,0)) | J11: =IF($A11>LastT,0,G11+H11-I11) | K11: =IF($A11>LastT,0,J11*Policy_Sched!$C11*Policy_Sched!$D11*C11) | L11: =J11*D11 | M11: =IF($A11>LastT,0,(SizeAnnPrem*ExpsMaintAnnPrem+(SumAssured*ExpsMaintSA+ExpsMaintPol)*B11)*(1+IF($B$3="exps",$E$3,0))) | N11: =SizePremium*J11 | O11: =SumAssured*K11 | P11: =Policy_Sched!$I11*(L11+I11) | Q11: =O11+P11 | R11: =IF($A11=0,SizeExpsAcq0*H11,0) | S11: =IF($A11=0,SizeExpsCommInit0*J11,0) | T11: =Policy_Sched!$J11*J11 | U11: =M11*J11 | V11: =S11+T11+R11+U11 | W11: =IF($A11>LastT,0,N11+W12/(1+Policy_Sched!$K11)) | X11: =IF($A11>LastT,0,(-Q11+X12)/(1+Policy_Sched!$K11)) | Y11: =IF($A11>LastT,0,-V11+Y12/(1+Policy_Sched!$K11)) | Z11: =W11+Y11+X11 | AA11: =IF($A11>LastT,0,N11-V11-Q11/(1+Policy_Sched!$K11)+Z12/(1+Policy_Sched!$K11))
A12: =A11+1 | B12: =IF($A12>LastT,0,IF($B$3="exps",B11*(1+InflRate+IF($A12>=T0,$G$3,0)),B11/(1+InflRate))) | C12: =IF($A12>LastT,0,IF(AND($D$3<>0,$A12>=T0,Policy_Sched!$B12<LastAge),1+$D$3*$E$3,1)) | D12: =IF($A12>LastT,0,IF($C$3="up",MIN(Policy_Sched!$E12*(1+IF($A12>=T0,$E$3,0)),$F$3),IF($C$3="down",MAX(Policy_Sched!$E12*(1-IF($A12>=T0,$E$3,0)),Policy_Sched!$E12-$F$3),Policy_Sched!$E12))) | E12: =IF($A12>LastT,0,J11-K11-L11) | F12: =IF($A12>LastT,0,IF($A12=PolicyTerm,E12,0)) | G12: =IF($A12>LastT,0,E12-F12) | H12: =IF($A12=0,PolicyCount,0) | I12: =IF($A12>LastT,0,IF(AND($C$3="mass",$A12=T0),(G12+H12)*$E$3,0)) | J12: =IF($A12>LastT,0,G12+H12-I12) | K12: =IF($A12>LastT,0,J12*Policy_Sched!$C12*Policy_Sched!$D12*C12) | L12: =J12*D12 | M12: =IF($A12>LastT,0,(SizeAnnPrem*ExpsMaintAnnPrem+(SumAssured*ExpsMaintSA+ExpsMaintPol)*B12)*(1+IF($B$3="exps",$E$3,0))) | N12: =SizePremium*J12 | O12: =SumAssured*K12 | P12: =Policy_Sched!$I12*(L12+I12) | Q12: =O12+P12 | R12: =IF($A12=0,SizeExpsAcq0*H12,0) | S12: =IF($A12=0,SizeExpsCommInit0*J12,0) | T12: =Policy_Sched!$J12*J12 | U12: =M12*J12 | V12: =S12+T12+R12+U12 | W12: =IF($A12>LastT,0,N12+W13/(1+Policy_Sched!$K12)) | X12: =IF($A12>LastT,0,(-Q12+X13)/(1+Policy_Sched!$K12)) | Y12: =IF($A12>LastT,0,-V12+Y13/(1+Policy_Sched!$K12)) | Z12: =W12+Y12+X12 | AA12: =IF($A12>LastT,0,N12-V12-Q12/(1+Policy_Sched!$K12)+Z13/(1+Policy_Sched!$K12))
A13: =A12+1 | B13: =IF($A13>LastT,0,IF($B$3="exps",B12*(1+InflRate+IF($A13>=T0,$G$3,0)),B12/(1+InflRate))) | C13: =IF($A13>LastT,0,IF(AND($D$3<>0,$A13>=T0,Policy_Sched!$B13<LastAge),1+$D$3*$E$3,1)) | D13: =IF($A13>LastT,0,IF($C$3="up",MIN(Policy_Sched!$E13*(1+IF($A13>=T0,$E$3,0)),$F$3),IF($C$3="down",MAX(Policy_Sched!$E13*(1-IF($A13>=T0,$E$3,0)),Policy_Sched!$E13-$F$3),Policy_Sched!$E13))) | E13: =IF($A13>LastT,0,J12-K12-L12) | F13: =IF($A13>LastT,0,IF($A13=PolicyTerm,E13,0)) | G13: =IF($A13>LastT,0,E13-F13) | H13: =IF($A13=0,PolicyCount,0) | I13: =IF($A13>LastT,0,IF(AND($C$3="mass",$A13=T0),(G13+H13)*$E$3,0)) | J13: =IF($A13>LastT,0,G13+H13-I13) | K13: =IF($A13>LastT,0,J13*Policy_Sched!$C13*Policy_Sched!$D13*C13) | L13: =J13*D13 | M13: =IF($A13>LastT,0,(SizeAnnPrem*ExpsMaintAnnPrem+(SumAssured*ExpsMaintSA+ExpsMaintPol)*B13)*(1+IF($B$3="exps",$E$3,0))) | N13: =SizePremium*J13 | O13: =SumAssured*K13 | P13: =Policy_Sched!$I13*(L13+I13) | Q13: =O13+P13 | R13: =IF($A13=0,SizeExpsAcq0*H13,0) | S13: =IF($A13=0,SizeExpsCommInit0*J13,0) | T13: =Policy_Sched!$J13*J13 | U13: =M13*J13 | V13: =S13+T13+R13+U13 | W13: =IF($A13>LastT,0,N13+W14/(1+Policy_Sched!$K13)) | X13: =IF($A13>LastT,0,(-Q13+X14)/(1+Policy_Sched!$K13)) | Y13: =IF($A13>LastT,0,-V13+Y14/(1+Policy_Sched!$K13)) | Z13: =W13+Y13+X13 | AA13: =IF($A13>LastT,0,N13-V13-Q13/(1+Policy_Sched!$K13)+Z14/(1+Policy_Sched!$K13))
A14: =A13+1 | B14: =IF($A14>LastT,0,IF($B$3="exps",B13*(1+InflRate+IF($A14>=T0,$G$3,0)),B13/(1+InflRate))) | C14: =IF($A14>LastT,0,IF(AND($D$3<>0,$A14>=T0,Policy_Sched!$B14<LastAge),1+$D$3*$E$3,1)) | D14: =IF($A14>LastT,0,IF($C$3="up",MIN(Policy_Sched!$E14*(1+IF($A14>=T0,$E$3,0)),$F$3),IF($C$3="down",MAX(Policy_Sched!$E14*(1-IF($A14>=T0,$E$3,0)),Policy_Sched!$E14-$F$3),Policy_Sched!$E14))) | E14: =IF($A14>LastT,0,J13-K13-L13) | F14: =IF($A14>LastT,0,IF($A14=PolicyTerm,E14,0)) | G14: =IF($A14>LastT,0,E14-F14) | H14: =IF($A14=0,PolicyCount,0) | I14: =IF($A14>LastT,0,IF(AND($C$3="mass",$A14=T0),(G14+H14)*$E$3,0)) | J14: =IF($A14>LastT,0,G14+H14-I14) | K14: =IF($A14>LastT,0,J14*Policy_Sched!$C14*Policy_Sched!$D14*C14) | L14: =J14*D14 | M14: =IF($A14>LastT,0,(SizeAnnPrem*ExpsMaintAnnPrem+(SumAssured*ExpsMaintSA+ExpsMaintPol)*B14)*(1+IF($B$3="exps",$E$3,0))) | N14: =SizePremium*J14 | O14: =SumAssured*K14 | P14: =Policy_Sched!$I14*(L14+I14) | Q14: =O14+P14 | R14: =IF($A14=0,SizeExpsAcq0*H14,0) | S14: =IF($A14=0,SizeExpsCommInit0*J14,0) | T14: =Policy_Sched!$J14*J14 | U14: =M14*J14 | V14: =S14+T14+R14+U14 | W14: =IF($A14>LastT,0,N14+W15/(1+Policy_Sched!$K14)) | X14: =IF($A14>LastT,0,(-Q14+X15)/(1+Policy_Sched!$K14)) | Y14: =IF($A14>LastT,0,-V14+Y15/(1+Policy_Sched!$K14)) | Z14: =W14+Y14+X14 | AA14: =IF($A14>LastT,0,N14-V14-Q14/(1+Policy_Sched!$K14)+Z15/(1+Policy_Sched!$K14))
A15: =A14+1 | B15: =IF($A15>LastT,0,IF($B$3="exps",B14*(1+InflRate+IF($A15>=T0,$G$3,0)),B14/(1+InflRate))) | C15: =IF($A15>LastT,0,IF(AND($D$3<>0,$A15>=T0,Policy_Sched!$B15<LastAge),1+$D$3*$E$3,1)) | D15: =IF($A15>LastT,0,IF($C$3="up",MIN(Policy_Sched!$E15*(1+IF($A15>=T0,$E$3,0)),$F$3),IF($C$3="down",MAX(Policy_Sched!$E15*(1-IF($A15>=T0,$E$3,0)),Policy_Sched!$E15-$F$3),Policy_Sched!$E15))) | E15: =IF($A15>LastT,0,J14-K14-L14) | F15: =IF($A15>LastT,0,IF($A15=PolicyTerm,E15,0)) | G15: =IF($A15>LastT,0,E15-F15) | H15: =IF($A15=0,PolicyCount,0) | I15: =IF($A15>LastT,0,IF(AND($C$3="mass",$A15=T0),(G15+H15)*$E$3,0)) | J15: =IF($A15>LastT,0,G15+H15-I15) | K15: =IF($A15>LastT,0,J15*Policy_Sched!$C15*Policy_Sched!$D15*C15) | L15: =J15*D15 | M15: =IF($A15>LastT,0,(SizeAnnPrem*ExpsMaintAnnPrem+(SumAssured*ExpsMaintSA+ExpsMaintPol)*B15)*(1+IF($B$3="exps",$E$3,0))) | N15: =SizePremium*J15 | O15: =SumAssured*K15 | P15: =Policy_Sched!$I15*(L15+I15) | Q15: =O15+P15 | R15: =IF($A15=0,SizeExpsAcq0*H15,0) | S15: =IF($A15=0,SizeExpsCommInit0*J15,0) | T15: =Policy_Sched!$J15*J15 | U15: =M15*J15 | V15: =S15+T15+R15+U15 | W15: =IF($A15>LastT,0,N15+W16/(1+Policy_Sched!$K15)) | X15: =IF($A15>LastT,0,(-Q15+X16)/(1+Policy_Sched!$K15)) | Y15: =IF($A15>LastT,0,-V15+Y16/(1+Policy_Sched!$K15)) | Z15: =W15+Y15+X15 | AA15: =IF($A15>LastT,0,N15-V15-Q15/(1+Policy_Sched!$K15)+Z16/(1+Policy_Sched!$K15))
A16: =A15+1 | B16: =IF($A16>LastT,0,IF($B$3="exps",B15*(1+InflRate+IF($A16>=T0,$G$3,0)),B15/(1+InflRate))) | C16: =IF($A16>LastT,0,IF(AND($D$3<>0,$A16>=T0,Policy_Sched!$B16<LastAge),1+$D$3*$E$3,1)) | D16: =IF($A16>LastT,0,IF($C$3="up",MIN(Policy_Sched!$E16*(1+IF($A16>=T0,$E$3,0)),$F$3),IF($C$3="down",MAX(Policy_Sched!$E16*(1-IF($A16>=T0,$E$3,0)),Policy_Sched!$E16-$F$3),Policy_Sched!$E16))) | E16: =IF($A16>LastT,0,J15-K15-L15) | F16: =IF($A16>LastT,0,IF($A16=PolicyTerm,E16,0)) | G16: =IF($A16>LastT,0,E16-F16) | H16: =IF($A16=0,PolicyCount,0) | I16: =IF($A16>LastT,0,IF(AND($C$3="mass",$A16=T0),(G16+H16)*$E$3,0)) | J16: =IF($A16>LastT,0,G16+H16-I16) | K16: =IF($A16>LastT,0,J16*Policy_Sched!$C16*Policy_Sched!$D16*C16) | L16: =J16*D16 | M16: =IF($A16>LastT,0,(SizeAnnPrem*ExpsMaintAnnPrem+(SumAssured*ExpsMaintSA+ExpsMaintPol)*B16)*(1+IF($B$3="exps",$E$3,0))) | N16: =SizePremium*J16 | O16: =SumAssured*K16 | P16: =Policy_Sched!$I16*(L16+I16) | Q16: =O16+P16 | R16: =IF($A16=0,SizeExpsAcq0*H16,0) | S16: =IF($A16=0,SizeExpsCommInit0*J16,0) | T16: =Policy_Sched!$J16*J16 | U16: =M16*J16 | V16: =S16+T16+R16+U16 | W16: =IF($A16>LastT,0,N16+W17/(1+Policy_Sched!$K16)) | X16: =IF($A16>LastT,0,(-Q16+X17)/(1+Policy_Sched!$K16)) | Y16: =IF($A16>LastT,0,-V16+Y17/(1+Policy_Sched!$K16)) | Z16: =W16+Y16+X16 | AA16: =IF($A16>LastT,0,N16-V16-Q16/(1+Policy_Sched!$K16)+Z17/(1+Policy_Sched!$K16))
A17: =A16+1 | B17: =IF($A17>LastT,0,IF($B$3="exps",B16*(1+InflRate+IF($A17>=T0,$G$3,0)),B16/(1+InflRate))) | C17: =IF($A17>LastT,0,IF(AND($D$3<>0,$A17>=T0,Policy_Sched!$B17<LastAge),1+$D$3*$E$3,1)) | D17: =IF($A17>LastT,0,IF($C$3="up",MIN(Policy_Sched!$E17*(1+IF($A17>=T0,$E$3,0)),$F$3),IF($C$3="down",MAX(Policy_Sched!$E17*(1-IF($A17>=T0,$E$3,0)),Policy_Sched!$E17-$F$3),Policy_Sched!$E17))) | E17: =IF($A17>LastT,0,J16-K16-L16) | F17: =IF($A17>LastT,0,IF($A17=PolicyTerm,E17,0)) | G17: =IF($A17>LastT,0,E17-F17) | H17: =IF($A17=0,PolicyCount,0) | I17: =IF($A17>LastT,0,IF(AND($C$3="mass",$A17=T0),(G17+H17)*$E$3,0)) | J17: =IF($A17>LastT,0,G17+H17-I17) | K17: =IF($A17>LastT,0,J17*Policy_Sched!$C17*Policy_Sched!$D17*C17) | L17: =J17*D17 | M17: =IF($A17>LastT,0,(SizeAnnPrem*ExpsMaintAnnPrem+(SumAssured*ExpsMaintSA+ExpsMaintPol)*B17)*(1+IF($B$3="exps",$E$3,0))) | N17: =SizePremium*J17 | O17: =SumAssured*K17 | P17: =Policy_Sched!$I17*(L17+I17) | Q17: =O17+P17 | R17: =IF($A17=0,SizeExpsAcq0*H17,0) | S17: =IF($A17=0,SizeExpsCommInit0*J17,0) | T17: =Policy_Sched!$J17*J17 | U17: =M17*J17 | V17: =S17+T17+R17+U17 | W17: =IF($A17>LastT,0,N17+W18/(1+Policy_Sched!$K17)) | X17: =IF($A17>LastT,0,(-Q17+X18)/(1+Policy_Sched!$K17)) | Y17: =IF($A17>LastT,0,-V17+Y18/(1+Policy_Sched!$K17)) | Z17: =W17+Y17+X17 | AA17: =IF($A17>LastT,0,N17-V17-Q17/(1+Policy_Sched!$K17)+Z18/(1+Policy_Sched!$K17))
A18: =A17+1 | B18: =IF($A18>LastT,0,IF($B$3="exps",B17*(1+InflRate+IF($A18>=T0,$G$3,0)),B17/(1+InflRate))) | C18: =IF($A18>LastT,0,IF(AND($D$3<>0,$A18>=T0,Policy_Sched!$B18<LastAge),1+$D$3*$E$3,1)) | D18: =IF($A18>LastT,0,IF($C$3="up",MIN(Policy_Sched!$E18*(1+IF($A18>=T0,$E$3,0)),$F$3),IF($C$3="down",MAX(Policy_Sched!$E18*(1-IF($A18>=T0,$E$3,0)),Policy_Sched!$E18-$F$3),Policy_Sched!$E18))) | E18: =IF($A18>LastT,0,J17-K17-L17) | F18: =IF($A18>LastT,0,IF($A18=PolicyTerm,E18,0)) | G18: =IF($A18>LastT,0,E18-F18) | H18: =IF($A18=0,PolicyCount,0) | I18: =IF($A18>LastT,0,IF(AND($C$3="mass",$A18=T0),(G18+H18)*$E$3,0)) | J18: =IF($A18>LastT,0,G18+H18-I18) | K18: =IF($A18>LastT,0,J18*Policy_Sched!$C18*Policy_Sched!$D18*C18) | L18: =J18*D18 | M18: =IF($A18>LastT,0,(SizeAnnPrem*ExpsMaintAnnPrem+(SumAssured*ExpsMaintSA+ExpsMaintPol)*B18)*(1+IF($B$3="exps",$E$3,0))) | N18: =SizePremium*J18 | O18: =SumAssured*K18 | P18: =Policy_Sched!$I18*(L18+I18) | Q18: =O18+P18 | R18: =IF($A18=0,SizeExpsAcq0*H18,0) | S18: =IF($A18=0,SizeExpsCommInit0*J18,0) | T18: =Policy_Sched!$J18*J18 | U18: =M18*J18 | V18: =S18+T18+R18+U18 | W18: =IF($A18>LastT,0,N18+W19/(1+Policy_Sched!$K18)) | X18: =IF($A18>LastT,0,(-Q18+X19)/(1+Policy_Sched!$K18)) | Y18: =IF($A18>LastT,0,-V18+Y19/(1+Policy_Sched!$K18)) | Z18: =W18+Y18+X18 | AA18: =IF($A18>LastT,0,N18-V18-Q18/(1+Policy_Sched!$K18)+Z19/(1+Policy_Sched!$K18))
A19: =A18+1 | B19: =IF($A19>LastT,0,IF($B$3="exps",B18*(1+InflRate+IF($A19>=T0,$G$3,0)),B18/(1+InflRate))) | C19: =IF($A19>LastT,0,IF(AND($D$3<>0,$A19>=T0,Policy_Sched!$B19<LastAge),1+$D$3*$E$3,1)) | D19: =IF($A19>LastT,0,IF($C$3="up",MIN(Policy_Sched!$E19*(1+IF($A19>=T0,$E$3,0)),$F$3),IF($C$3="down",MAX(Policy_Sched!$E19*(1-IF($A19>=T0,$E$3,0)),Policy_Sched!$E19-$F$3),Policy_Sched!$E19))) | E19: =IF($A19>LastT,0,J18-K18-L18) | F19: =IF($A19>LastT,0,IF($A19=PolicyTerm,E19,0)) | G19: =IF($A19>LastT,0,E19-F19) | H19: =IF($A19=0,PolicyCount,0) | I19: =IF($A19>LastT,0,IF(AND($C$3="mass",$A19=T0),(G19+H19)*$E$3,0)) | J19: =IF($A19>LastT,0,G19+H19-I19) | K19: =IF($A19>LastT,0,J19*Policy_Sched!$C19*Policy_Sched!$D19*C19) | L19: =J19*D19 | M19: =IF($A19>LastT,0,(SizeAnnPrem*ExpsMaintAnnPrem+(SumAssured*ExpsMaintSA+ExpsMaintPol)*B19)*(1+IF($B$3="exps",$E$3,0))) | N19: =SizePremium*J19 | O19: =SumAssured*K19 | P19: =Policy_Sched!$I19*(L19+I19) | Q19: =O19+P19 | R19: =IF($A19=0,SizeExpsAcq0*H19,0) | S19: =IF($A19=0,SizeExpsCommInit0*J19,0) | T19: =Policy_Sched!$J19*J19 | U19: =M19*J19 | V19: =S19+T19+R19+U19 | W19: =IF($A19>LastT,0,N19+W20/(1+Policy_Sched!$K19)) | X19: =IF($A19>LastT,0,(-Q19+X20)/(1+Policy_Sched!$K19)) | Y19: =IF($A19>LastT,0,-V19+Y20/(1+Policy_Sched!$K19)) | Z19: =W19+Y19+X19 | AA19: =IF($A19>LastT,0,N19-V19-Q19/(1+Policy_Sched!$K19)+Z20/(1+Policy_Sched!$K19))
... A110: =A109+1 | B110: =IF($A110>LastT,0,IF($B$3="exps",B109*(1+InflRate+IF($A110>=T0,$G$3,0)),B109/(1+InflRate))) | C110: =IF($A110>LastT,0,IF(AND($D$3<>0,$A110>=T0,Policy_Sched!$B110<LastAge),1+$D$3*$E$3,1)) | D110: =IF($A110>LastT,0,IF($C$3="up",MIN(Policy_Sched!$E110*(1+IF($A110>=T0,$E$3,0)),$F$3),IF($C$3="down",MAX(Policy_Sched!$E110*(1-IF($A110>=T0,$E$3,0)),Policy_Sched!$E110-$F$3),Policy_Sched!$E110))) | E110: =IF($A110>LastT,0,J109-K109-L109) | F110: =IF($A110>LastT,0,IF($A110=PolicyTerm,E110,0)) | G110: =IF($A110>LastT,0,E110-F110) | H110: =IF($A110=0,PolicyCount,0) | I110: =IF($A110>LastT,0,IF(AND($C$3="mass",$A110=T0),(G110+H110)*$E$3,0)) | J110: =IF($A110>LastT,0,G110+H110-I110) | K110: =IF($A110>LastT,0,J110*Policy_Sched!$C110*Policy_Sched!$D110*C110) | L110: =J110*D110 | M110: =IF($A110>LastT,0,(SizeAnnPrem*ExpsMaintAnnPrem+(SumAssured*ExpsMaintSA+ExpsMaintPol)*B110)*(1+IF($B$3="exps",$E$3,0))) | N110: =SizePremium*J110 | O110: =SumAssured*K110 | P110: =Policy_Sched!$I110*(L110+I110) | Q110: =O110+P110 | R110: =IF($A110=0,SizeExpsAcq0*H110,0) | S110: =IF($A110=0,SizeExpsCommInit0*J110,0) | T110: =Policy_Sched!$J110*J110 | U110: =M110*J110 | V110: =S110+T110+R110+U110 | W110: =IF($A110>LastT,0,N110+W111/(1+Policy_Sched!$K110)) | X110: =IF($A110>LastT,0,(-Q110+X111)/(1+Policy_Sched!$K110)) | Y110: =IF($A110>LastT,0,-V110+Y111/(1+Policy_Sched!$K110)) | Z110: =W110+Y110+X110 | AA110: =IF($A110>LastT,0,N110-V110-Q110/(1+Policy_Sched!$K110)+Z111/(1+Policy_Sched!$K110))

Sheet Proj_Longev
A1: Liability projection — longevity stress (−25% rates from t0). lifelib SCR_life.Projection['longev', None, None]
B2: Risk | C2: Shock | D2: Risk sign | E2: Shock factor | F2: Shock limit | G2: Inflation shock
B3: longev | D3: -1 | E3: =IFERROR(INDEX(FactorVals,MATCH($B$3&"|"&$C$3&"||",FactorKeys,0)),0) | F3: =IFERROR(INDEX(FactorVals,MATCH($B$3&"|"&$C$3&"||limit",FactorKeys,0)),0) | G3: =IFERROR(INDEX(FactorVals,MATCH($B$3&"|||inflation",FactorKeys,0)),0)
B4: Risk | C4: Shock | E4: Factor
A5: t | B5: Inflation factor | C5: Mortality shock factor | D5: Surrender rate | E5: In force: end | F5: Maturities | G5: In force: after maturity | H5: New business | I5: Mass lapse | J5: In force: beginning | K5: Deaths | L5: Surrenders | M5: Maint expense pp | N5: Premium income | O5: Death benefits | P5: Surrender benefits | Q5: Total benefits | R5: Acquisition expenses | S5: Initial commission | T5: Renewal commission | U5: Maintenance expenses | V5: Total expenses | W5: PV premiums | X5: PV benefits | Y5: PV expenses | Z5: PV net cashflow | AA5: PV net cf (fwd check)
A6: t | B6: InflFactor | C6: MortRateFactor | D6: SurrRate | E6: PolsIF_End | F6: PolsMaturity | G6: PolsIF_Beg | H6: PolsNewBiz | I6: PolsSurrMass | J6: PolsIF_Beg1 | K6: PolsDeath | L6: PolsSurr | M6: SizeExpsMaint | N6: PremIncome | O6: BenefitDeath | P6: BenefitSurr | Q6: BenefitTotal | R6: ExpsAcq | S6: ExpsCommInit | T6: ExpsCommRen | U6: ExpsMaint | V6: ExpsTotal | W6: PV_PremIncome | X6: PV_BenefitTotal | Y6: PV_ExpsTotal | Z6: PV_NetCashflow | AA6: PV_NetCashflowForCheck
A7: 0 | B7: =1 | C7: =IF($A7>LastT,0,IF(AND($D$3<>0,$A7>=T0,Policy_Sched!$B7<LastAge),1+$D$3*$E$3,1)) | D7: =IF($A7>LastT,0,IF($C$3="up",MIN(Policy_Sched!$E7*(1+IF($A7>=T0,$E$3,0)),$F$3),IF($C$3="down",MAX(Policy_Sched!$E7*(1-IF($A7>=T0,$E$3,0)),Policy_Sched!$E7-$F$3),Policy_Sched!$E7))) | E7: =0 | F7: =IF($A7>LastT,0,IF($A7=PolicyTerm,E7,0)) | G7: =IF($A7>LastT,0,E7-F7) | H7: =IF($A7=0,PolicyCount,0) | I7: =IF($A7>LastT,0,IF(AND($C$3="mass",$A7=T0),(G7+H7)*$E$3,0)) | J7: =IF($A7>LastT,0,G7+H7-I7) | K7: =IF($A7>LastT,0,J7*Policy_Sched!$C7*Policy_Sched!$D7*C7) | L7: =J7*D7 | M7: =IF($A7>LastT,0,(SizeAnnPrem*ExpsMaintAnnPrem+(SumAssured*ExpsMaintSA+ExpsMaintPol)*B7)*(1+IF($B$3="exps",$E$3,0))) | N7: =SizePremium*J7 | O7: =SumAssured*K7 | P7: =Policy_Sched!$I7*(L7+I7) | Q7: =O7+P7 | R7: =IF($A7=0,SizeExpsAcq0*H7,0) | S7: =IF($A7=0,SizeExpsCommInit0*J7,0) | T7: =Policy_Sched!$J7*J7 | U7: =M7*J7 | V7: =S7+T7+R7+U7 | W7: =IF($A7>LastT,0,N7+W8/(1+Policy_Sched!$K7)) | X7: =IF($A7>LastT,0,(-Q7+X8)/(1+Policy_Sched!$K7)) | Y7: =IF($A7>LastT,0,-V7+Y8/(1+Policy_Sched!$K7)) | Z7: =W7+Y7+X7 | AA7: =IF($A7>LastT,0,N7-V7-Q7/(1+Policy_Sched!$K7)+Z8/(1+Policy_Sched!$K7))
A8: =A7+1 | B8: =IF($A8>LastT,0,IF($B$3="exps",B7*(1+InflRate+IF($A8>=T0,$G$3,0)),B7/(1+InflRate))) | C8: =IF($A8>LastT,0,IF(AND($D$3<>0,$A8>=T0,Policy_Sched!$B8<LastAge),1+$D$3*$E$3,1)) | D8: =IF($A8>LastT,0,IF($C$3="up",MIN(Policy_Sched!$E8*(1+IF($A8>=T0,$E$3,0)),$F$3),IF($C$3="down",MAX(Policy_Sched!$E8*(1-IF($A8>=T0,$E$3,0)),Policy_Sched!$E8-$F$3),Policy_Sched!$E8))) | E8: =IF($A8>LastT,0,J7-K7-L7) | F8: =IF($A8>LastT,0,IF($A8=PolicyTerm,E8,0)) | G8: =IF($A8>LastT,0,E8-F8) | H8: =IF($A8=0,PolicyCount,0) | I8: =IF($A8>LastT,0,IF(AND($C$3="mass",$A8=T0),(G8+H8)*$E$3,0)) | J8: =IF($A8>LastT,0,G8+H8-I8) | K8: =IF($A8>LastT,0,J8*Policy_Sched!$C8*Policy_Sched!$D8*C8) | L8: =J8*D8 | M8: =IF($A8>LastT,0,(SizeAnnPrem*ExpsMaintAnnPrem+(SumAssured*ExpsMaintSA+ExpsMaintPol)*B8)*(1+IF($B$3="exps",$E$3,0))) | N8: =SizePremium*J8 | O8: =SumAssured*K8 | P8: =Policy_Sched!$I8*(L8+I8) | Q8: =O8+P8 | R8: =IF($A8=0,SizeExpsAcq0*H8,0) | S8: =IF($A8=0,SizeExpsCommInit0*J8,0) | T8: =Policy_Sched!$J8*J8 | U8: =M8*J8 | V8: =S8+T8+R8+U8 | W8: =IF($A8>LastT,0,N8+W9/(1+Policy_Sched!$K8)) | X8: =IF($A8>LastT,0,(-Q8+X9)/(1+Policy_Sched!$K8)) | Y8: =IF($A8>LastT,0,-V8+Y9/(1+Policy_Sched!$K8)) | Z8: =W8+Y8+X8 | AA8: =IF($A8>LastT,0,N8-V8-Q8/(1+Policy_Sched!$K8)+Z9/(1+Policy_Sched!$K8))
A9: =A8+1 | B9: =IF($A9>LastT,0,IF($B$3="exps",B8*(1+InflRate+IF($A9>=T0,$G$3,0)),B8/(1+InflRate))) | C9: =IF($A9>LastT,0,IF(AND($D$3<>0,$A9>=T0,Policy_Sched!$B9<LastAge),1+$D$3*$E$3,1)) | D9: =IF($A9>LastT,0,IF($C$3="up",MIN(Policy_Sched!$E9*(1+IF($A9>=T0,$E$3,0)),$F$3),IF($C$3="down",MAX(Policy_Sched!$E9*(1-IF($A9>=T0,$E$3,0)),Policy_Sched!$E9-$F$3),Policy_Sched!$E9))) | E9: =IF($A9>LastT,0,J8-K8-L8) | F9: =IF($A9>LastT,0,IF($A9=PolicyTerm,E9,0)) | G9: =IF($A9>LastT,0,E9-F9) | H9: =IF($A9=0,PolicyCount,0) | I9: =IF($A9>LastT,0,IF(AND($C$3="mass",$A9=T0),(G9+H9)*$E$3,0)) | J9: =IF($A9>LastT,0,G9+H9-I9) | K9: =IF($A9>LastT,0,J9*Policy_Sched!$C9*Policy_Sched!$D9*C9) | L9: =J9*D9 | M9: =IF($A9>LastT,0,(SizeAnnPrem*ExpsMaintAnnPrem+(SumAssured*ExpsMaintSA+ExpsMaintPol)*B9)*(1+IF($B$3="exps",$E$3,0))) | N9: =SizePremium*J9 | O9: =SumAssured*K9 | P9: =Policy_Sched!$I9*(L9+I9) | Q9: =O9+P9 | R9: =IF($A9=0,SizeExpsAcq0*H9,0) | S9: =IF($A9=0,SizeExpsCommInit0*J9,0) | T9: =Policy_Sched!$J9*J9 | U9: =M9*J9 | V9: =S9+T9+R9+U9 | W9: =IF($A9>LastT,0,N9+W10/(1+Policy_Sched!$K9)) | X9: =IF($A9>LastT,0,(-Q9+X10)/(1+Policy_Sched!$K9)) | Y9: =IF($A9>LastT,0,-V9+Y10/(1+Policy_Sched!$K9)) | Z9: =W9+Y9+X9 | AA9: =IF($A9>LastT,0,N9-V9-Q9/(1+Policy_Sched!$K9)+Z10/(1+Policy_Sched!$K9))
A10: =A9+1 | B10: =IF($A10>LastT,0,IF($B$3="exps",B9*(1+InflRate+IF($A10>=T0,$G$3,0)),B9/(1+InflRate))) | C10: =IF($A10>LastT,0,IF(AND($D$3<>0,$A10>=T0,Policy_Sched!$B10<LastAge),1+$D$3*$E$3,1)) | D10: =IF($A10>LastT,0,IF($C$3="up",MIN(Policy_Sched!$E10*(1+IF($A10>=T0,$E$3,0)),$F$3),IF($C$3="down",MAX(Policy_Sched!$E10*(1-IF($A10>=T0,$E$3,0)),Policy_Sched!$E10-$F$3),Policy_Sched!$E10))) | E10: =IF($A10>LastT,0,J9-K9-L9) | F10: =IF($A10>LastT,0,IF($A10=PolicyTerm,E10,0)) | G10: =IF($A10>LastT,0,E10-F10) | H10: =IF($A10=0,PolicyCount,0) | I10: =IF($A10>LastT,0,IF(AND($C$3="mass",$A10=T0),(G10+H10)*$E$3,0)) | J10: =IF($A10>LastT,0,G10+H10-I10) | K10: =IF($A10>LastT,0,J10*Policy_Sched!$C10*Policy_Sched!$D10*C10) | L10: =J10*D10 | M10: =IF($A10>LastT,0,(SizeAnnPrem*ExpsMaintAnnPrem+(SumAssured*ExpsMaintSA+ExpsMaintPol)*B10)*(1+IF($B$3="exps",$E$3,0))) | N10: =SizePremium*J10 | O10: =SumAssured*K10 | P10: =Policy_Sched!$I10*(L10+I10) | Q10: =O10+P10 | R10: =IF($A10=0,SizeExpsAcq0*H10,0) | S10: =IF($A10=0,SizeExpsCommInit0*J10,0) | T10: =Policy_Sched!$J10*J10 | U10: =M10*J10 | V10: =S10+T10+R10+U10 | W10: =IF($A10>LastT,0,N10+W11/(1+Policy_Sched!$K10)) | X10: =IF($A10>LastT,0,(-Q10+X11)/(1+Policy_Sched!$K10)) | Y10: =IF($A10>LastT,0,-V10+Y11/(1+Policy_Sched!$K10)) | Z10: =W10+Y10+X10 | AA10: =IF($A10>LastT,0,N10-V10-Q10/(1+Policy_Sched!$K10)+Z11/(1+Policy_Sched!$K10))
A11: =A10+1 | B11: =IF($A11>LastT,0,IF($B$3="exps",B10*(1+InflRate+IF($A11>=T0,$G$3,0)),B10/(1+InflRate))) | C11: =IF($A11>LastT,0,IF(AND($D$3<>0,$A11>=T0,Policy_Sched!$B11<LastAge),1+$D$3*$E$3,1)) | D11: =IF($A11>LastT,0,IF($C$3="up",MIN(Policy_Sched!$E11*(1+IF($A11>=T0,$E$3,0)),$F$3),IF($C$3="down",MAX(Policy_Sched!$E11*(1-IF($A11>=T0,$E$3,0)),Policy_Sched!$E11-$F$3),Policy_Sched!$E11))) | E11: =IF($A11>LastT,0,J10-K10-L10) | F11: =IF($A11>LastT,0,IF($A11=PolicyTerm,E11,0)) | G11: =IF($A11>LastT,0,E11-F11) | H11: =IF($A11=0,PolicyCount,0) | I11: =IF($A11>LastT,0,IF(AND($C$3="mass",$A11=T0),(G11+H11)*$E$3,0)) | J11: =IF($A11>LastT,0,G11+H11-I11) | K11: =IF($A11>LastT,0,J11*Policy_Sched!$C11*Policy_Sched!$D11*C11) | L11: =J11*D11 | M11: =IF($A11>LastT,0,(SizeAnnPrem*ExpsMaintAnnPrem+(SumAssured*ExpsMaintSA+ExpsMaintPol)*B11)*(1+IF($B$3="exps",$E$3,0))) | N11: =SizePremium*J11 | O11: =SumAssured*K11 | P11: =Policy_Sched!$I11*(L11+I11) | Q11: =O11+P11 | R11: =IF($A11=0,SizeExpsAcq0*H11,0) | S11: =IF($A11=0,SizeExpsCommInit0*J11,0) | T11: =Policy_Sched!$J11*J11 | U11: =M11*J11 | V11: =S11+T11+R11+U11 | W11: =IF($A11>LastT,0,N11+W12/(1+Policy_Sched!$K11)) | X11: =IF($A11>LastT,0,(-Q11+X12)/(1+Policy_Sched!$K11)) | Y11: =IF($A11>LastT,0,-V11+Y12/(1+Policy_Sched!$K11)) | Z11: =W11+Y11+X11 | AA11: =IF($A11>LastT,0,N11-V11-Q11/(1+Policy_Sched!$K11)+Z12/(1+Policy_Sched!$K11))
A12: =A11+1 | B12: =IF($A12>LastT,0,IF($B$3="exps",B11*(1+InflRate+IF($A12>=T0,$G$3,0)),B11/(1+InflRate))) | C12: =IF($A12>LastT,0,IF(AND($D$3<>0,$A12>=T0,Policy_Sched!$B12<LastAge),1+$D$3*$E$3,1)) | D12: =IF($A12>LastT,0,IF($C$3="up",MIN(Policy_Sched!$E12*(1+IF($A12>=T0,$E$3,0)),$F$3),IF($C$3="down",MAX(Policy_Sched!$E12*(1-IF($A12>=T0,$E$3,0)),Policy_Sched!$E12-$F$3),Policy_Sched!$E12))) | E12: =IF($A12>LastT,0,J11-K11-L11) | F12: =IF($A12>LastT,0,IF($A12=PolicyTerm,E12,0)) | G12: =IF($A12>LastT,0,E12-F12) | H12: =IF($A12=0,PolicyCount,0) | I12: =IF($A12>LastT,0,IF(AND($C$3="mass",$A12=T0),(G12+H12)*$E$3,0)) | J12: =IF($A12>LastT,0,G12+H12-I12) | K12: =IF($A12>LastT,0,J12*Policy_Sched!$C12*Policy_Sched!$D12*C12) | L12: =J12*D12 | M12: =IF($A12>LastT,0,(SizeAnnPrem*ExpsMaintAnnPrem+(SumAssured*ExpsMaintSA+ExpsMaintPol)*B12)*(1+IF($B$3="exps",$E$3,0))) | N12: =SizePremium*J12 | O12: =SumAssured*K12 | P12: =Policy_Sched!$I12*(L12+I12) | Q12: =O12+P12 | R12: =IF($A12=0,SizeExpsAcq0*H12,0) | S12: =IF($A12=0,SizeExpsCommInit0*J12,0) | T12: =Policy_Sched!$J12*J12 | U12: =M12*J12 | V12: =S12+T12+R12+U12 | W12: =IF($A12>LastT,0,N12+W13/(1+Policy_Sched!$K12)) | X12: =IF($A12>LastT,0,(-Q12+X13)/(1+Policy_Sched!$K12)) | Y12: =IF($A12>LastT,0,-V12+Y13/(1+Policy_Sched!$K12)) | Z12: =W12+Y12+X12 | AA12: =IF($A12>LastT,0,N12-V12-Q12/(1+Policy_Sched!$K12)+Z13/(1+Policy_Sched!$K12))
A13: =A12+1 | B13: =IF($A13>LastT,0,IF($B$3="exps",B12*(1+InflRate+IF($A13>=T0,$G$3,0)),B12/(1+InflRate))) | C13: =IF($A13>LastT,0,IF(AND($D$3<>0,$A13>=T0,Policy_Sched!$B13<LastAge),1+$D$3*$E$3,1)) | D13: =IF($A13>LastT,0,IF($C$3="up",MIN(Policy_Sched!$E13*(1+IF($A13>=T0,$E$3,0)),$F$3),IF($C$3="down",MAX(Policy_Sched!$E13*(1-IF($A13>=T0,$E$3,0)),Policy_Sched!$E13-$F$3),Policy_Sched!$E13))) | E13: =IF($A13>LastT,0,J12-K12-L12) | F13: =IF($A13>LastT,0,IF($A13=PolicyTerm,E13,0)) | G13: =IF($A13>LastT,0,E13-F13) | H13: =IF($A13=0,PolicyCount,0) | I13: =IF($A13>LastT,0,IF(AND($C$3="mass",$A13=T0),(G13+H13)*$E$3,0)) | J13: =IF($A13>LastT,0,G13+H13-I13) | K13: =IF($A13>LastT,0,J13*Policy_Sched!$C13*Policy_Sched!$D13*C13) | L13: =J13*D13 | M13: =IF($A13>LastT,0,(SizeAnnPrem*ExpsMaintAnnPrem+(SumAssured*ExpsMaintSA+ExpsMaintPol)*B13)*(1+IF($B$3="exps",$E$3,0))) | N13: =SizePremium*J13 | O13: =SumAssured*K13 | P13: =Policy_Sched!$I13*(L13+I13) | Q13: =O13+P13 | R13: =IF($A13=0,SizeExpsAcq0*H13,0) | S13: =IF($A13=0,SizeExpsCommInit0*J13,0) | T13: =Policy_Sched!$J13*J13 | U13: =M13*J13 | V13: =S13+T13+R13+U13 | W13: =IF($A13>LastT,0,N13+W14/(1+Policy_Sched!$K13)) | X13: =IF($A13>LastT,0,(-Q13+X14)/(1+Policy_Sched!$K13)) | Y13: =IF($A13>LastT,0,-V13+Y14/(1+Policy_Sched!$K13)) | Z13: =W13+Y13+X13 | AA13: =IF($A13>LastT,0,N13-V13-Q13/(1+Policy_Sched!$K13)+Z14/(1+Policy_Sched!$K13))
A14: =A13+1 | B14: =IF($A14>LastT,0,IF($B$3="exps",B13*(1+InflRate+IF($A14>=T0,$G$3,0)),B13/(1+InflRate))) | C14: =IF($A14>LastT,0,IF(AND($D$3<>0,$A14>=T0,Policy_Sched!$B14<LastAge),1+$D$3*$E$3,1)) | D14: =IF($A14>LastT,0,IF($C$3="up",MIN(Policy_Sched!$E14*(1+IF($A14>=T0,$E$3,0)),$F$3),IF($C$3="down",MAX(Policy_Sched!$E14*(1-IF($A14>=T0,$E$3,0)),Policy_Sched!$E14-$F$3),Policy_Sched!$E14))) | E14: =IF($A14>LastT,0,J13-K13-L13) | F14: =IF($A14>LastT,0,IF($A14=PolicyTerm,E14,0)) | G14: =IF($A14>LastT,0,E14-F14) | H14: =IF($A14=0,PolicyCount,0) | I14: =IF($A14>LastT,0,IF(AND($C$3="mass",$A14=T0),(G14+H14)*$E$3,0)) | J14: =IF($A14>LastT,0,G14+H14-I14) | K14: =IF($A14>LastT,0,J14*Policy_Sched!$C14*Policy_Sched!$D14*C14) | L14: =J14*D14 | M14: =IF($A14>LastT,0,(SizeAnnPrem*ExpsMaintAnnPrem+(SumAssured*ExpsMaintSA+ExpsMaintPol)*B14)*(1+IF($B$3="exps",$E$3,0))) | N14: =SizePremium*J14 | O14: =SumAssured*K14 | P14: =Policy_Sched!$I14*(L14+I14) | Q14: =O14+P14 | R14: =IF($A14=0,SizeExpsAcq0*H14,0) | S14: =IF($A14=0,SizeExpsCommInit0*J14,0) | T14: =Policy_Sched!$J14*J14 | U14: =M14*J14 | V14: =S14+T14+R14+U14 | W14: =IF($A14>LastT,0,N14+W15/(1+Policy_Sched!$K14)) | X14: =IF($A14>LastT,0,(-Q14+X15)/(1+Policy_Sched!$K14)) | Y14: =IF($A14>LastT,0,-V14+Y15/(1+Policy_Sched!$K14)) | Z14: =W14+Y14+X14 | AA14: =IF($A14>LastT,0,N14-V14-Q14/(1+Policy_Sched!$K14)+Z15/(1+Policy_Sched!$K14))
A15: =A14+1 | B15: =IF($A15>LastT,0,IF($B$3="exps",B14*(1+InflRate+IF($A15>=T0,$G$3,0)),B14/(1+InflRate))) | C15: =IF($A15>LastT,0,IF(AND($D$3<>0,$A15>=T0,Policy_Sched!$B15<LastAge),1+$D$3*$E$3,1)) | D15: =IF($A15>LastT,0,IF($C$3="up",MIN(Policy_Sched!$E15*(1+IF($A15>=T0,$E$3,0)),$F$3),IF($C$3="down",MAX(Policy_Sched!$E15*(1-IF($A15>=T0,$E$3,0)),Policy_Sched!$E15-$F$3),Policy_Sched!$E15))) | E15: =IF($A15>LastT,0,J14-K14-L14) | F15: =IF($A15>LastT,0,IF($A15=PolicyTerm,E15,0)) | G15: =IF($A15>LastT,0,E15-F15) | H15: =IF($A15=0,PolicyCount,0) | I15: =IF($A15>LastT,0,IF(AND($C$3="mass",$A15=T0),(G15+H15)*$E$3,0)) | J15: =IF($A15>LastT,0,G15+H15-I15) | K15: =IF($A15>LastT,0,J15*Policy_Sched!$C15*Policy_Sched!$D15*C15) | L15: =J15*D15 | M15: =IF($A15>LastT,0,(SizeAnnPrem*ExpsMaintAnnPrem+(SumAssured*ExpsMaintSA+ExpsMaintPol)*B15)*(1+IF($B$3="exps",$E$3,0))) | N15: =SizePremium*J15 | O15: =SumAssured*K15 | P15: =Policy_Sched!$I15*(L15+I15) | Q15: =O15+P15 | R15: =IF($A15=0,SizeExpsAcq0*H15,0) | S15: =IF($A15=0,SizeExpsCommInit0*J15,0) | T15: =Policy_Sched!$J15*J15 | U15: =M15*J15 | V15: =S15+T15+R15+U15 | W15: =IF($A15>LastT,0,N15+W16/(1+Policy_Sched!$K15)) | X15: =IF($A15>LastT,0,(-Q15+X16)/(1+Policy_Sched!$K15)) | Y15: =IF($A15>LastT,0,-V15+Y16/(1+Policy_Sched!$K15)) | Z15: =W15+Y15+X15 | AA15: =IF($A15>LastT,0,N15-V15-Q15/(1+Policy_Sched!$K15)+Z16/(1+Policy_Sched!$K15))
A16: =A15+1 | B16: =IF($A16>LastT,0,IF($B$3="exps",B15*(1+InflRate+IF($A16>=T0,$G$3,0)),B15/(1+InflRate))) | C16: =IF($A16>LastT,0,IF(AND($D$3<>0,$A16>=T0,Policy_Sched!$B16<LastAge),1+$D$3*$E$3,1)) | D16: =IF($A16>LastT,0,IF($C$3="up",MIN(Policy_Sched!$E16*(1+IF($A16>=T0,$E$3,0)),$F$3),IF($C$3="down",MAX(Policy_Sched!$E16*(1-IF($A16>=T0,$E$3,0)),Policy_Sched!$E16-$F$3),Policy_Sched!$E16))) | E16: =IF($A16>LastT,0,J15-K15-L15) | F16: =IF($A16>LastT,0,IF($A16=PolicyTerm,E16,0)) | G16: =IF($A16>LastT,0,E16-F16) | H16: =IF($A16=0,PolicyCount,0) | I16: =IF($A16>LastT,0,IF(AND($C$3="mass",$A16=T0),(G16+H16)*$E$3,0)) | J16: =IF($A16>LastT,0,G16+H16-I16) | K16: =IF($A16>LastT,0,J16*Policy_Sched!$C16*Policy_Sched!$D16*C16) | L16: =J16*D16 | M16: =IF($A16>LastT,0,(SizeAnnPrem*ExpsMaintAnnPrem+(SumAssured*ExpsMaintSA+ExpsMaintPol)*B16)*(1+IF($B$3="exps",$E$3,0))) | N16: =SizePremium*J16 | O16: =SumAssured*K16 | P16: =Policy_Sched!$I16*(L16+I16) | Q16: =O16+P16 | R16: =IF($A16=0,SizeExpsAcq0*H16,0) | S16: =IF($A16=0,SizeExpsCommInit0*J16,0) | T16: =Policy_Sched!$J16*J16 | U16: =M16*J16 | V16: =S16+T16+R16+U16 | W16: =IF($A16>LastT,0,N16+W17/(1+Policy_Sched!$K16)) | X16: =IF($A16>LastT,0,(-Q16+X17)/(1+Policy_Sched!$K16)) | Y16: =IF($A16>LastT,0,-V16+Y17/(1+Policy_Sched!$K16)) | Z16: =W16+Y16+X16 | AA16: =IF($A16>LastT,0,N16-V16-Q16/(1+Policy_Sched!$K16)+Z17/(1+Policy_Sched!$K16))
A17: =A16+1 | B17: =IF($A17>LastT,0,IF($B$3="exps",B16*(1+InflRate+IF($A17>=T0,$G$3,0)),B16/(1+InflRate))) | C17: =IF($A17>LastT,0,IF(AND($D$3<>0,$A17>=T0,Policy_Sched!$B17<LastAge),1+$D$3*$E$3,1)) | D17: =IF($A17>LastT,0,IF($C$3="up",MIN(Policy_Sched!$E17*(1+IF($A17>=T0,$E$3,0)),$F$3),IF($C$3="down",MAX(Policy_Sched!$E17*(1-IF($A17>=T0,$E$3,0)),Policy_Sched!$E17-$F$3),Policy_Sched!$E17))) | E17: =IF($A17>LastT,0,J16-K16-L16) | F17: =IF($A17>LastT,0,IF($A17=PolicyTerm,E17,0)) | G17: =IF($A17>LastT,0,E17-F17) | H17: =IF($A17=0,PolicyCount,0) | I17: =IF($A17>LastT,0,IF(AND($C$3="mass",$A17=T0),(G17+H17)*$E$3,0)) | J17: =IF($A17>LastT,0,G17+H17-I17) | K17: =IF($A17>LastT,0,J17*Policy_Sched!$C17*Policy_Sched!$D17*C17) | L17: =J17*D17 | M17: =IF($A17>LastT,0,(SizeAnnPrem*ExpsMaintAnnPrem+(SumAssured*ExpsMaintSA+ExpsMaintPol)*B17)*(1+IF($B$3="exps",$E$3,0))) | N17: =SizePremium*J17 | O17: =SumAssured*K17 | P17: =Policy_Sched!$I17*(L17+I17) | Q17: =O17+P17 | R17: =IF($A17=0,SizeExpsAcq0*H17,0) | S17: =IF($A17=0,SizeExpsCommInit0*J17,0) | T17: =Policy_Sched!$J17*J17 | U17: =M17*J17 | V17: =S17+T17+R17+U17 | W17: =IF($A17>LastT,0,N17+W18/(1+Policy_Sched!$K17)) | X17: =IF($A17>LastT,0,(-Q17+X18)/(1+Policy_Sched!$K17)) | Y17: =IF($A17>LastT,0,-V17+Y18/(1+Policy_Sched!$K17)) | Z17: =W17+Y17+X17 | AA17: =IF($A17>LastT,0,N17-V17-Q17/(1+Policy_Sched!$K17)+Z18/(1+Policy_Sched!$K17))
A18: =A17+1 | B18: =IF($A18>LastT,0,IF($B$3="exps",B17*(1+InflRate+IF($A18>=T0,$G$3,0)),B17/(1+InflRate))) | C18: =IF($A18>LastT,0,IF(AND($D$3<>0,$A18>=T0,Policy_Sched!$B18<LastAge),1+$D$3*$E$3,1)) | D18: =IF($A18>LastT,0,IF($C$3="up",MIN(Policy_Sched!$E18*(1+IF($A18>=T0,$E$3,0)),$F$3),IF($C$3="down",MAX(Policy_Sched!$E18*(1-IF($A18>=T0,$E$3,0)),Policy_Sched!$E18-$F$3),Policy_Sched!$E18))) | E18: =IF($A18>LastT,0,J17-K17-L17) | F18: =IF($A18>LastT,0,IF($A18=PolicyTerm,E18,0)) | G18: =IF($A18>LastT,0,E18-F18) | H18: =IF($A18=0,PolicyCount,0) | I18: =IF($A18>LastT,0,IF(AND($C$3="mass",$A18=T0),(G18+H18)*$E$3,0)) | J18: =IF($A18>LastT,0,G18+H18-I18) | K18: =IF($A18>LastT,0,J18*Policy_Sched!$C18*Policy_Sched!$D18*C18) | L18: =J18*D18 | M18: =IF($A18>LastT,0,(SizeAnnPrem*ExpsMaintAnnPrem+(SumAssured*ExpsMaintSA+ExpsMaintPol)*B18)*(1+IF($B$3="exps",$E$3,0))) | N18: =SizePremium*J18 | O18: =SumAssured*K18 | P18: =Policy_Sched!$I18*(L18+I18) | Q18: =O18+P18 | R18: =IF($A18=0,SizeExpsAcq0*H18,0) | S18: =IF($A18=0,SizeExpsCommInit0*J18,0) | T18: =Policy_Sched!$J18*J18 | U18: =M18*J18 | V18: =S18+T18+R18+U18 | W18: =IF($A18>LastT,0,N18+W19/(1+Policy_Sched!$K18)) | X18: =IF($A18>LastT,0,(-Q18+X19)/(1+Policy_Sched!$K18)) | Y18: =IF($A18>LastT,0,-V18+Y19/(1+Policy_Sched!$K18)) | Z18: =W18+Y18+X18 | AA18: =IF($A18>LastT,0,N18-V18-Q18/(1+Policy_Sched!$K18)+Z19/(1+Policy_Sched!$K18))
A19: =A18+1 | B19: =IF($A19>LastT,0,IF($B$3="exps",B18*(1+InflRate+IF($A19>=T0,$G$3,0)),B18/(1+InflRate))) | C19: =IF($A19>LastT,0,IF(AND($D$3<>0,$A19>=T0,Policy_Sched!$B19<LastAge),1+$D$3*$E$3,1)) | D19: =IF($A19>LastT,0,IF($C$3="up",MIN(Policy_Sched!$E19*(1+IF($A19>=T0,$E$3,0)),$F$3),IF($C$3="down",MAX(Policy_Sched!$E19*(1-IF($A19>=T0,$E$3,0)),Policy_Sched!$E19-$F$3),Policy_Sched!$E19))) | E19: =IF($A19>LastT,0,J18-K18-L18) | F19: =IF($A19>LastT,0,IF($A19=PolicyTerm,E19,0)) | G19: =IF($A19>LastT,0,E19-F19) | H19: =IF($A19=0,PolicyCount,0) | I19: =IF($A19>LastT,0,IF(AND($C$3="mass",$A19=T0),(G19+H19)*$E$3,0)) | J19: =IF($A19>LastT,0,G19+H19-I19) | K19: =IF($A19>LastT,0,J19*Policy_Sched!$C19*Policy_Sched!$D19*C19) | L19: =J19*D19 | M19: =IF($A19>LastT,0,(SizeAnnPrem*ExpsMaintAnnPrem+(SumAssured*ExpsMaintSA+ExpsMaintPol)*B19)*(1+IF($B$3="exps",$E$3,0))) | N19: =SizePremium*J19 | O19: =SumAssured*K19 | P19: =Policy_Sched!$I19*(L19+I19) | Q19: =O19+P19 | R19: =IF($A19=0,SizeExpsAcq0*H19,0) | S19: =IF($A19=0,SizeExpsCommInit0*J19,0) | T19: =Policy_Sched!$J19*J19 | U19: =M19*J19 | V19: =S19+T19+R19+U19 | W19: =IF($A19>LastT,0,N19+W20/(1+Policy_Sched!$K19)) | X19: =IF($A19>LastT,0,(-Q19+X20)/(1+Policy_Sched!$K19)) | Y19: =IF($A19>LastT,0,-V19+Y20/(1+Policy_Sched!$K19)) | Z19: =W19+Y19+X19 | AA19: =IF($A19>LastT,0,N19-V19-Q19/(1+Policy_Sched!$K19)+Z20/(1+Policy_Sched!$K19))
... A110: =A109+1 | B110: =IF($A110>LastT,0,IF($B$3="exps",B109*(1+InflRate+IF($A110>=T0,$G$3,0)),B109/(1+InflRate))) | C110: =IF($A110>LastT,0,IF(AND($D$3<>0,$A110>=T0,Policy_Sched!$B110<LastAge),1+$D$3*$E$3,1)) | D110: =IF($A110>LastT,0,IF($C$3="up",MIN(Policy_Sched!$E110*(1+IF($A110>=T0,$E$3,0)),$F$3),IF($C$3="down",MAX(Policy_Sched!$E110*(1-IF($A110>=T0,$E$3,0)),Policy_Sched!$E110-$F$3),Policy_Sched!$E110))) | E110: =IF($A110>LastT,0,J109-K109-L109) | F110: =IF($A110>LastT,0,IF($A110=PolicyTerm,E110,0)) | G110: =IF($A110>LastT,0,E110-F110) | H110: =IF($A110=0,PolicyCount,0) | I110: =IF($A110>LastT,0,IF(AND($C$3="mass",$A110=T0),(G110+H110)*$E$3,0)) | J110: =IF($A110>LastT,0,G110+H110-I110) | K110: =IF($A110>LastT,0,J110*Policy_Sched!$C110*Policy_Sched!$D110*C110) | L110: =J110*D110 | M110: =IF($A110>LastT,0,(SizeAnnPrem*ExpsMaintAnnPrem+(SumAssured*ExpsMaintSA+ExpsMaintPol)*B110)*(1+IF($B$3="exps",$E$3,0))) | N110: =SizePremium*J110 | O110: =SumAssured*K110 | P110: =Policy_Sched!$I110*(L110+I110) | Q110: =O110+P110 | R110: =IF($A110=0,SizeExpsAcq0*H110,0) | S110: =IF($A110=0,SizeExpsCommInit0*J110,0) | T110: =Policy_Sched!$J110*J110 | U110: =M110*J110 | V110: =S110+T110+R110+U110 | W110: =IF($A110>LastT,0,N110+W111/(1+Policy_Sched!$K110)) | X110: =IF($A110>LastT,0,(-Q110+X111)/(1+Policy_Sched!$K110)) | Y110: =IF($A110>LastT,0,-V110+Y111/(1+Policy_Sched!$K110)) | Z110: =W110+Y110+X110 | AA110: =IF($A110>LastT,0,N110-V110-Q110/(1+Policy_Sched!$K110)+Z111/(1+Policy_Sched!$K110))

Sheet Proj_Exps
A1: Liability projection — expense stress (+10% level, +1% inflation from t0). lifelib SCR_life.Projection['exps', None, None]
B2: Risk | C2: Shock | D2: Risk sign | E2: Shock factor | F2: Shock limit | G2: Inflation shock
B3: exps | D3: 0 | E3: =IFERROR(INDEX(FactorVals,MATCH($B$3&"|"&$C$3&"||",FactorKeys,0)),0) | F3: =IFERROR(INDEX(FactorVals,MATCH($B$3&"|"&$C$3&"||limit",FactorKeys,0)),0) | G3: =IFERROR(INDEX(FactorVals,MATCH($B$3&"|||inflation",FactorKeys,0)),0)
B4: Risk | C4: Shock | E4: Factor
A5: t | B5: Inflation factor | C5: Mortality shock factor | D5: Surrender rate | E5: In force: end | F5: Maturities | G5: In force: after maturity | H5: New business | I5: Mass lapse | J5: In force: beginning | K5: Deaths | L5: Surrenders | M5: Maint expense pp | N5: Premium income | O5: Death benefits | P5: Surrender benefits | Q5: Total benefits | R5: Acquisition expenses | S5: Initial commission | T5: Renewal commission | U5: Maintenance expenses | V5: Total expenses | W5: PV premiums | X5: PV benefits | Y5: PV expenses | Z5: PV net cashflow | AA5: PV net cf (fwd check)
A6: t | B6: InflFactor | C6: MortRateFactor | D6: SurrRate | E6: PolsIF_End | F6: PolsMaturity | G6: PolsIF_Beg | H6: PolsNewBiz | I6: PolsSurrMass | J6: PolsIF_Beg1 | K6: PolsDeath | L6: PolsSurr | M6: SizeExpsMaint | N6: PremIncome | O6: BenefitDeath | P6: BenefitSurr | Q6: BenefitTotal | R6: ExpsAcq | S6: ExpsCommInit | T6: ExpsCommRen | U6: ExpsMaint | V6: ExpsTotal | W6: PV_PremIncome | X6: PV_BenefitTotal | Y6: PV_ExpsTotal | Z6: PV_NetCashflow | AA6: PV_NetCashflowForCheck
A7: 0 | B7: =1 | C7: =IF($A7>LastT,0,IF(AND($D$3<>0,$A7>=T0,Policy_Sched!$B7<LastAge),1+$D$3*$E$3,1)) | D7: =IF($A7>LastT,0,IF($C$3="up",MIN(Policy_Sched!$E7*(1+IF($A7>=T0,$E$3,0)),$F$3),IF($C$3="down",MAX(Policy_Sched!$E7*(1-IF($A7>=T0,$E$3,0)),Policy_Sched!$E7-$F$3),Policy_Sched!$E7))) | E7: =0 | F7: =IF($A7>LastT,0,IF($A7=PolicyTerm,E7,0)) | G7: =IF($A7>LastT,0,E7-F7) | H7: =IF($A7=0,PolicyCount,0) | I7: =IF($A7>LastT,0,IF(AND($C$3="mass",$A7=T0),(G7+H7)*$E$3,0)) | J7: =IF($A7>LastT,0,G7+H7-I7) | K7: =IF($A7>LastT,0,J7*Policy_Sched!$C7*Policy_Sched!$D7*C7) | L7: =J7*D7 | M7: =IF($A7>LastT,0,(SizeAnnPrem*ExpsMaintAnnPrem+(SumAssured*ExpsMaintSA+ExpsMaintPol)*B7)*(1+IF($B$3="exps",$E$3,0))) | N7: =SizePremium*J7 | O7: =SumAssured*K7 | P7: =Policy_Sched!$I7*(L7+I7) | Q7: =O7+P7 | R7: =IF($A7=0,SizeExpsAcq0*H7,0) | S7: =IF($A7=0,SizeExpsCommInit0*J7,0) | T7: =Policy_Sched!$J7*J7 | U7: =M7*J7 | V7: =S7+T7+R7+U7 | W7: =IF($A7>LastT,0,N7+W8/(1+Policy_Sched!$K7)) | X7: =IF($A7>LastT,0,(-Q7+X8)/(1+Policy_Sched!$K7)) | Y7: =IF($A7>LastT,0,-V7+Y8/(1+Policy_Sched!$K7)) | Z7: =W7+Y7+X7 | AA7: =IF($A7>LastT,0,N7-V7-Q7/(1+Policy_Sched!$K7)+Z8/(1+Policy_Sched!$K7))
A8: =A7+1 | B8: =IF($A8>LastT,0,IF($B$3="exps",B7*(1+InflRate+IF($A8>=T0,$G$3,0)),B7/(1+InflRate))) | C8: =IF($A8>LastT,0,IF(AND($D$3<>0,$A8>=T0,Policy_Sched!$B8<LastAge),1+$D$3*$E$3,1)) | D8: =IF($A8>LastT,0,IF($C$3="up",MIN(Policy_Sched!$E8*(1+IF($A8>=T0,$E$3,0)),$F$3),IF($C$3="down",MAX(Policy_Sched!$E8*(1-IF($A8>=T0,$E$3,0)),Policy_Sched!$E8-$F$3),Policy_Sched!$E8))) | E8: =IF($A8>LastT,0,J7-K7-L7) | F8: =IF($A8>LastT,0,IF($A8=PolicyTerm,E8,0)) | G8: =IF($A8>LastT,0,E8-F8) | H8: =IF($A8=0,PolicyCount,0) | I8: =IF($A8>LastT,0,IF(AND($C$3="mass",$A8=T0),(G8+H8)*$E$3,0)) | J8: =IF($A8>LastT,0,G8+H8-I8) | K8: =IF($A8>LastT,0,J8*Policy_Sched!$C8*Policy_Sched!$D8*C8) | L8: =J8*D8 | M8: =IF($A8>LastT,0,(SizeAnnPrem*ExpsMaintAnnPrem+(SumAssured*ExpsMaintSA+ExpsMaintPol)*B8)*(1+IF($B$3="exps",$E$3,0))) | N8: =SizePremium*J8 | O8: =SumAssured*K8 | P8: =Policy_Sched!$I8*(L8+I8) | Q8: =O8+P8 | R8: =IF($A8=0,SizeExpsAcq0*H8,0) | S8: =IF($A8=0,SizeExpsCommInit0*J8,0) | T8: =Policy_Sched!$J8*J8 | U8: =M8*J8 | V8: =S8+T8+R8+U8 | W8: =IF($A8>LastT,0,N8+W9/(1+Policy_Sched!$K8)) | X8: =IF($A8>LastT,0,(-Q8+X9)/(1+Policy_Sched!$K8)) | Y8: =IF($A8>LastT,0,-V8+Y9/(1+Policy_Sched!$K8)) | Z8: =W8+Y8+X8 | AA8: =IF($A8>LastT,0,N8-V8-Q8/(1+Policy_Sched!$K8)+Z9/(1+Policy_Sched!$K8))
A9: =A8+1 | B9: =IF($A9>LastT,0,IF($B$3="exps",B8*(1+InflRate+IF($A9>=T0,$G$3,0)),B8/(1+InflRate))) | C9: =IF($A9>LastT,0,IF(AND($D$3<>0,$A9>=T0,Policy_Sched!$B9<LastAge),1+$D$3*$E$3,1)) | D9: =IF($A9>LastT,0,IF($C$3="up",MIN(Policy_Sched!$E9*(1+IF($A9>=T0,$E$3,0)),$F$3),IF($C$3="down",MAX(Policy_Sched!$E9*(1-IF($A9>=T0,$E$3,0)),Policy_Sched!$E9-$F$3),Policy_Sched!$E9))) | E9: =IF($A9>LastT,0,J8-K8-L8) | F9: =IF($A9>LastT,0,IF($A9=PolicyTerm,E9,0)) | G9: =IF($A9>LastT,0,E9-F9) | H9: =IF($A9=0,PolicyCount,0) | I9: =IF($A9>LastT,0,IF(AND($C$3="mass",$A9=T0),(G9+H9)*$E$3,0)) | J9: =IF($A9>LastT,0,G9+H9-I9) | K9: =IF($A9>LastT,0,J9*Policy_Sched!$C9*Policy_Sched!$D9*C9) | L9: =J9*D9 | M9: =IF($A9>LastT,0,(SizeAnnPrem*ExpsMaintAnnPrem+(SumAssured*ExpsMaintSA+ExpsMaintPol)*B9)*(1+IF($B$3="exps",$E$3,0))) | N9: =SizePremium*J9 | O9: =SumAssured*K9 | P9: =Policy_Sched!$I9*(L9+I9) | Q9: =O9+P9 | R9: =IF($A9=0,SizeExpsAcq0*H9,0) | S9: =IF($A9=0,SizeExpsCommInit0*J9,0) | T9: =Policy_Sched!$J9*J9 | U9: =M9*J9 | V9: =S9+T9+R9+U9 | W9: =IF($A9>LastT,0,N9+W10/(1+Policy_Sched!$K9)) | X9: =IF($A9>LastT,0,(-Q9+X10)/(1+Policy_Sched!$K9)) | Y9: =IF($A9>LastT,0,-V9+Y10/(1+Policy_Sched!$K9)) | Z9: =W9+Y9+X9 | AA9: =IF($A9>LastT,0,N9-V9-Q9/(1+Policy_Sched!$K9)+Z10/(1+Policy_Sched!$K9))
A10: =A9+1 | B10: =IF($A10>LastT,0,IF($B$3="exps",B9*(1+InflRate+IF($A10>=T0,$G$3,0)),B9/(1+InflRate))) | C10: =IF($A10>LastT,0,IF(AND($D$3<>0,$A10>=T0,Policy_Sched!$B10<LastAge),1+$D$3*$E$3,1)) | D10: =IF($A10>LastT,0,IF($C$3="up",MIN(Policy_Sched!$E10*(1+IF($A10>=T0,$E$3,0)),$F$3),IF($C$3="down",MAX(Policy_Sched!$E10*(1-IF($A10>=T0,$E$3,0)),Policy_Sched!$E10-$F$3),Policy_Sched!$E10))) | E10: =IF($A10>LastT,0,J9-K9-L9) | F10: =IF($A10>LastT,0,IF($A10=PolicyTerm,E10,0)) | G10: =IF($A10>LastT,0,E10-F10) | H10: =IF($A10=0,PolicyCount,0) | I10: =IF($A10>LastT,0,IF(AND($C$3="mass",$A10=T0),(G10+H10)*$E$3,0)) | J10: =IF($A10>LastT,0,G10+H10-I10) | K10: =IF($A10>LastT,0,J10*Policy_Sched!$C10*Policy_Sched!$D10*C10) | L10: =J10*D10 | M10: =IF($A10>LastT,0,(SizeAnnPrem*ExpsMaintAnnPrem+(SumAssured*ExpsMaintSA+ExpsMaintPol)*B10)*(1+IF($B$3="exps",$E$3,0))) | N10: =SizePremium*J10 | O10: =SumAssured*K10 | P10: =Policy_Sched!$I10*(L10+I10) | Q10: =O10+P10 | R10: =IF($A10=0,SizeExpsAcq0*H10,0) | S10: =IF($A10=0,SizeExpsCommInit0*J10,0) | T10: =Policy_Sched!$J10*J10 | U10: =M10*J10 | V10: =S10+T10+R10+U10 | W10: =IF($A10>LastT,0,N10+W11/(1+Policy_Sched!$K10)) | X10: =IF($A10>LastT,0,(-Q10+X11)/(1+Policy_Sched!$K10)) | Y10: =IF($A10>LastT,0,-V10+Y11/(1+Policy_Sched!$K10)) | Z10: =W10+Y10+X10 | AA10: =IF($A10>LastT,0,N10-V10-Q10/(1+Policy_Sched!$K10)+Z11/(1+Policy_Sched!$K10))
A11: =A10+1 | B11: =IF($A11>LastT,0,IF($B$3="exps",B10*(1+InflRate+IF($A11>=T0,$G$3,0)),B10/(1+InflRate))) | C11: =IF($A11>LastT,0,IF(AND($D$3<>0,$A11>=T0,Policy_Sched!$B11<LastAge),1+$D$3*$E$3,1)) | D11: =IF($A11>LastT,0,IF($C$3="up",MIN(Policy_Sched!$E11*(1+IF($A11>=T0,$E$3,0)),$F$3),IF($C$3="down",MAX(Policy_Sched!$E11*(1-IF($A11>=T0,$E$3,0)),Policy_Sched!$E11-$F$3),Policy_Sched!$E11))) | E11: =IF($A11>LastT,0,J10-K10-L10) | F11: =IF($A11>LastT,0,IF($A11=PolicyTerm,E11,0)) | G11: =IF($A11>LastT,0,E11-F11) | H11: =IF($A11=0,PolicyCount,0) | I11: =IF($A11>LastT,0,IF(AND($C$3="mass",$A11=T0),(G11+H11)*$E$3,0)) | J11: =IF($A11>LastT,0,G11+H11-I11) | K11: =IF($A11>LastT,0,J11*Policy_Sched!$C11*Policy_Sched!$D11*C11) | L11: =J11*D11 | M11: =IF($A11>LastT,0,(SizeAnnPrem*ExpsMaintAnnPrem+(SumAssured*ExpsMaintSA+ExpsMaintPol)*B11)*(1+IF($B$3="exps",$E$3,0))) | N11: =SizePremium*J11 | O11: =SumAssured*K11 | P11: =Policy_Sched!$I11*(L11+I11) | Q11: =O11+P11 | R11: =IF($A11=0,SizeExpsAcq0*H11,0) | S11: =IF($A11=0,SizeExpsCommInit0*J11,0) | T11: =Policy_Sched!$J11*J11 | U11: =M11*J11 | V11: =S11+T11+R11+U11 | W11: =IF($A11>LastT,0,N11+W12/(1+Policy_Sched!$K11)) | X11: =IF($A11>LastT,0,(-Q11+X12)/(1+Policy_Sched!$K11)) | Y11: =IF($A11>LastT,0,-V11+Y12/(1+Policy_Sched!$K11)) | Z11: =W11+Y11+X11 | AA11: =IF($A11>LastT,0,N11-V11-Q11/(1+Policy_Sched!$K11)+Z12/(1+Policy_Sched!$K11))
A12: =A11+1 | B12: =IF($A12>LastT,0,IF($B$3="exps",B11*(1+InflRate+IF($A12>=T0,$G$3,0)),B11/(1+InflRate))) | C12: =IF($A12>LastT,0,IF(AND($D$3<>0,$A12>=T0,Policy_Sched!$B12<LastAge),1+$D$3*$E$3,1)) | D12: =IF($A12>LastT,0,IF($C$3="up",MIN(Policy_Sched!$E12*(1+IF($A12>=T0,$E$3,0)),$F$3),IF($C$3="down",MAX(Policy_Sched!$E12*(1-IF($A12>=T0,$E$3,0)),Policy_Sched!$E12-$F$3),Policy_Sched!$E12))) | E12: =IF($A12>LastT,0,J11-K11-L11) | F12: =IF($A12>LastT,0,IF($A12=PolicyTerm,E12,0)) | G12: =IF($A12>LastT,0,E12-F12) | H12: =IF($A12=0,PolicyCount,0) | I12: =IF($A12>LastT,0,IF(AND($C$3="mass",$A12=T0),(G12+H12)*$E$3,0)) | J12: =IF($A12>LastT,0,G12+H12-I12) | K12: =IF($A12>LastT,0,J12*Policy_Sched!$C12*Policy_Sched!$D12*C12) | L12: =J12*D12 | M12: =IF($A12>LastT,0,(SizeAnnPrem*ExpsMaintAnnPrem+(SumAssured*ExpsMaintSA+ExpsMaintPol)*B12)*(1+IF($B$3="exps",$E$3,0))) | N12: =SizePremium*J12 | O12: =SumAssured*K12 | P12: =Policy_Sched!$I12*(L12+I12) | Q12: =O12+P12 | R12: =IF($A12=0,SizeExpsAcq0*H12,0) | S12: =IF($A12=0,SizeExpsCommInit0*J12,0) | T12: =Policy_Sched!$J12*J12 | U12: =M12*J12 | V12: =S12+T12+R12+U12 | W12: =IF($A12>LastT,0,N12+W13/(1+Policy_Sched!$K12)) | X12: =IF($A12>LastT,0,(-Q12+X13)/(1+Policy_Sched!$K12)) | Y12: =IF($A12>LastT,0,-V12+Y13/(1+Policy_Sched!$K12)) | Z12: =W12+Y12+X12 | AA12: =IF($A12>LastT,0,N12-V12-Q12/(1+Policy_Sched!$K12)+Z13/(1+Policy_Sched!$K12))
A13: =A12+1 | B13: =IF($A13>LastT,0,IF($B$3="exps",B12*(1+InflRate+IF($A13>=T0,$G$3,0)),B12/(1+InflRate))) | C13: =IF($A13>LastT,0,IF(AND($D$3<>0,$A13>=T0,Policy_Sched!$B13<LastAge),1+$D$3*$E$3,1)) | D13: =IF($A13>LastT,0,IF($C$3="up",MIN(Policy_Sched!$E13*(1+IF($A13>=T0,$E$3,0)),$F$3),IF($C$3="down",MAX(Policy_Sched!$E13*(1-IF($A13>=T0,$E$3,0)),Policy_Sched!$E13-$F$3),Policy_Sched!$E13))) | E13: =IF($A13>LastT,0,J12-K12-L12) | F13: =IF($A13>LastT,0,IF($A13=PolicyTerm,E13,0)) | G13: =IF($A13>LastT,0,E13-F13) | H13: =IF($A13=0,PolicyCount,0) | I13: =IF($A13>LastT,0,IF(AND($C$3="mass",$A13=T0),(G13+H13)*$E$3,0)) | J13: =IF($A13>LastT,0,G13+H13-I13) | K13: =IF($A13>LastT,0,J13*Policy_Sched!$C13*Policy_Sched!$D13*C13) | L13: =J13*D13 | M13: =IF($A13>LastT,0,(SizeAnnPrem*ExpsMaintAnnPrem+(SumAssured*ExpsMaintSA+ExpsMaintPol)*B13)*(1+IF($B$3="exps",$E$3,0))) | N13: =SizePremium*J13 | O13: =SumAssured*K13 | P13: =Policy_Sched!$I13*(L13+I13) | Q13: =O13+P13 | R13: =IF($A13=0,SizeExpsAcq0*H13,0) | S13: =IF($A13=0,SizeExpsCommInit0*J13,0) | T13: =Policy_Sched!$J13*J13 | U13: =M13*J13 | V13: =S13+T13+R13+U13 | W13: =IF($A13>LastT,0,N13+W14/(1+Policy_Sched!$K13)) | X13: =IF($A13>LastT,0,(-Q13+X14)/(1+Policy_Sched!$K13)) | Y13: =IF($A13>LastT,0,-V13+Y14/(1+Policy_Sched!$K13)) | Z13: =W13+Y13+X13 | AA13: =IF($A13>LastT,0,N13-V13-Q13/(1+Policy_Sched!$K13)+Z14/(1+Policy_Sched!$K13))
A14: =A13+1 | B14: =IF($A14>LastT,0,IF($B$3="exps",B13*(1+InflRate+IF($A14>=T0,$G$3,0)),B13/(1+InflRate))) | C14: =IF($A14>LastT,0,IF(AND($D$3<>0,$A14>=T0,Policy_Sched!$B14<LastAge),1+$D$3*$E$3,1)) | D14: =IF($A14>LastT,0,IF($C$3="up",MIN(Policy_Sched!$E14*(1+IF($A14>=T0,$E$3,0)),$F$3),IF($C$3="down",MAX(Policy_Sched!$E14*(1-IF($A14>=T0,$E$3,0)),Policy_Sched!$E14-$F$3),Policy_Sched!$E14))) | E14: =IF($A14>LastT,0,J13-K13-L13) | F14: =IF($A14>LastT,0,IF($A14=PolicyTerm,E14,0)) | G14: =IF($A14>LastT,0,E14-F14) | H14: =IF($A14=0,PolicyCount,0) | I14: =IF($A14>LastT,0,IF(AND($C$3="mass",$A14=T0),(G14+H14)*$E$3,0)) | J14: =IF($A14>LastT,0,G14+H14-I14) | K14: =IF($A14>LastT,0,J14*Policy_Sched!$C14*Policy_Sched!$D14*C14) | L14: =J14*D14 | M14: =IF($A14>LastT,0,(SizeAnnPrem*ExpsMaintAnnPrem+(SumAssured*ExpsMaintSA+ExpsMaintPol)*B14)*(1+IF($B$3="exps",$E$3,0))) | N14: =SizePremium*J14 | O14: =SumAssured*K14 | P14: =Policy_Sched!$I14*(L14+I14) | Q14: =O14+P14 | R14: =IF($A14=0,SizeExpsAcq0*H14,0) | S14: =IF($A14=0,SizeExpsCommInit0*J14,0) | T14: =Policy_Sched!$J14*J14 | U14: =M14*J14 | V14: =S14+T14+R14+U14 | W14: =IF($A14>LastT,0,N14+W15/(1+Policy_Sched!$K14)) | X14: =IF($A14>LastT,0,(-Q14+X15)/(1+Policy_Sched!$K14)) | Y14: =IF($A14>LastT,0,-V14+Y15/(1+Policy_Sched!$K14)) | Z14: =W14+Y14+X14 | AA14: =IF($A14>LastT,0,N14-V14-Q14/(1+Policy_Sched!$K14)+Z15/(1+Policy_Sched!$K14))
A15: =A14+1 | B15: =IF($A15>LastT,0,IF($B$3="exps",B14*(1+InflRate+IF($A15>=T0,$G$3,0)),B14/(1+InflRate))) | C15: =IF($A15>LastT,0,IF(AND($D$3<>0,$A15>=T0,Policy_Sched!$B15<LastAge),1+$D$3*$E$3,1)) | D15: =IF($A15>LastT,0,IF($C$3="up",MIN(Policy_Sched!$E15*(1+IF($A15>=T0,$E$3,0)),$F$3),IF($C$3="down",MAX(Policy_Sched!$E15*(1-IF($A15>=T0,$E$3,0)),Policy_Sched!$E15-$F$3),Policy_Sched!$E15))) | E15: =IF($A15>LastT,0,J14-K14-L14) | F15: =IF($A15>LastT,0,IF($A15=PolicyTerm,E15,0)) | G15: =IF($A15>LastT,0,E15-F15) | H15: =IF($A15=0,PolicyCount,0) | I15: =IF($A15>LastT,0,IF(AND($C$3="mass",$A15=T0),(G15+H15)*$E$3,0)) | J15: =IF($A15>LastT,0,G15+H15-I15) | K15: =IF($A15>LastT,0,J15*Policy_Sched!$C15*Policy_Sched!$D15*C15) | L15: =J15*D15 | M15: =IF($A15>LastT,0,(SizeAnnPrem*ExpsMaintAnnPrem+(SumAssured*ExpsMaintSA+ExpsMaintPol)*B15)*(1+IF($B$3="exps",$E$3,0))) | N15: =SizePremium*J15 | O15: =SumAssured*K15 | P15: =Policy_Sched!$I15*(L15+I15) | Q15: =O15+P15 | R15: =IF($A15=0,SizeExpsAcq0*H15,0) | S15: =IF($A15=0,SizeExpsCommInit0*J15,0) | T15: =Policy_Sched!$J15*J15 | U15: =M15*J15 | V15: =S15+T15+R15+U15 | W15: =IF($A15>LastT,0,N15+W16/(1+Policy_Sched!$K15)) | X15: =IF($A15>LastT,0,(-Q15+X16)/(1+Policy_Sched!$K15)) | Y15: =IF($A15>LastT,0,-V15+Y16/(1+Policy_Sched!$K15)) | Z15: =W15+Y15+X15 | AA15: =IF($A15>LastT,0,N15-V15-Q15/(1+Policy_Sched!$K15)+Z16/(1+Policy_Sched!$K15))
A16: =A15+1 | B16: =IF($A16>LastT,0,IF($B$3="exps",B15*(1+InflRate+IF($A16>=T0,$G$3,0)),B15/(1+InflRate))) | C16: =IF($A16>LastT,0,IF(AND($D$3<>0,$A16>=T0,Policy_Sched!$B16<LastAge),1+$D$3*$E$3,1)) | D16: =IF($A16>LastT,0,IF($C$3="up",MIN(Policy_Sched!$E16*(1+IF($A16>=T0,$E$3,0)),$F$3),IF($C$3="down",MAX(Policy_Sched!$E16*(1-IF($A16>=T0,$E$3,0)),Policy_Sched!$E16-$F$3),Policy_Sched!$E16))) | E16: =IF($A16>LastT,0,J15-K15-L15) | F16: =IF($A16>LastT,0,IF($A16=PolicyTerm,E16,0)) | G16: =IF($A16>LastT,0,E16-F16) | H16: =IF($A16=0,PolicyCount,0) | I16: =IF($A16>LastT,0,IF(AND($C$3="mass",$A16=T0),(G16+H16)*$E$3,0)) | J16: =IF($A16>LastT,0,G16+H16-I16) | K16: =IF($A16>LastT,0,J16*Policy_Sched!$C16*Policy_Sched!$D16*C16) | L16: =J16*D16 | M16: =IF($A16>LastT,0,(SizeAnnPrem*ExpsMaintAnnPrem+(SumAssured*ExpsMaintSA+ExpsMaintPol)*B16)*(1+IF($B$3="exps",$E$3,0))) | N16: =SizePremium*J16 | O16: =SumAssured*K16 | P16: =Policy_Sched!$I16*(L16+I16) | Q16: =O16+P16 | R16: =IF($A16=0,SizeExpsAcq0*H16,0) | S16: =IF($A16=0,SizeExpsCommInit0*J16,0) | T16: =Policy_Sched!$J16*J16 | U16: =M16*J16 | V16: =S16+T16+R16+U16 | W16: =IF($A16>LastT,0,N16+W17/(1+Policy_Sched!$K16)) | X16: =IF($A16>LastT,0,(-Q16+X17)/(1+Policy_Sched!$K16)) | Y16: =IF($A16>LastT,0,-V16+Y17/(1+Policy_Sched!$K16)) | Z16: =W16+Y16+X16 | AA16: =IF($A16>LastT,0,N16-V16-Q16/(1+Policy_Sched!$K16)+Z17/(1+Policy_Sched!$K16))
A17: =A16+1 | B17: =IF($A17>LastT,0,IF($B$3="exps",B16*(1+InflRate+IF($A17>=T0,$G$3,0)),B16/(1+InflRate))) | C17: =IF($A17>LastT,0,IF(AND($D$3<>0,$A17>=T0,Policy_Sched!$B17<LastAge),1+$D$3*$E$3,1)) | D17: =IF($A17>LastT,0,IF($C$3="up",MIN(Policy_Sched!$E17*(1+IF($A17>=T0,$E$3,0)),$F$3),IF($C$3="down",MAX(Policy_Sched!$E17*(1-IF($A17>=T0,$E$3,0)),Policy_Sched!$E17-$F$3),Policy_Sched!$E17))) | E17: =IF($A17>LastT,0,J16-K16-L16) | F17: =IF($A17>LastT,0,IF($A17=PolicyTerm,E17,0)) | G17: =IF($A17>LastT,0,E17-F17) | H17: =IF($A17=0,PolicyCount,0) | I17: =IF($A17>LastT,0,IF(AND($C$3="mass",$A17=T0),(G17+H17)*$E$3,0)) | J17: =IF($A17>LastT,0,G17+H17-I17) | K17: =IF($A17>LastT,0,J17*Policy_Sched!$C17*Policy_Sched!$D17*C17) | L17: =J17*D17 | M17: =IF($A17>LastT,0,(SizeAnnPrem*ExpsMaintAnnPrem+(SumAssured*ExpsMaintSA+ExpsMaintPol)*B17)*(1+IF($B$3="exps",$E$3,0))) | N17: =SizePremium*J17 | O17: =SumAssured*K17 | P17: =Policy_Sched!$I17*(L17+I17) | Q17: =O17+P17 | R17: =IF($A17=0,SizeExpsAcq0*H17,0) | S17: =IF($A17=0,SizeExpsCommInit0*J17,0) | T17: =Policy_Sched!$J17*J17 | U17: =M17*J17 | V17: =S17+T17+R17+U17 | W17: =IF($A17>LastT,0,N17+W18/(1+Policy_Sched!$K17)) | X17: =IF($A17>LastT,0,(-Q17+X18)/(1+Policy_Sched!$K17)) | Y17: =IF($A17>LastT,0,-V17+Y18/(1+Policy_Sched!$K17)) | Z17: =W17+Y17+X17 | AA17: =IF($A17>LastT,0,N17-V17-Q17/(1+Policy_Sched!$K17)+Z18/(1+Policy_Sched!$K17))
A18: =A17+1 | B18: =IF($A18>LastT,0,IF($B$3="exps",B17*(1+InflRate+IF($A18>=T0,$G$3,0)),B17/(1+InflRate))) | C18: =IF($A18>LastT,0,IF(AND($D$3<>0,$A18>=T0,Policy_Sched!$B18<LastAge),1+$D$3*$E$3,1)) | D18: =IF($A18>LastT,0,IF($C$3="up",MIN(Policy_Sched!$E18*(1+IF($A18>=T0,$E$3,0)),$F$3),IF($C$3="down",MAX(Policy_Sched!$E18*(1-IF($A18>=T0,$E$3,0)),Policy_Sched!$E18-$F$3),Policy_Sched!$E18))) | E18: =IF($A18>LastT,0,J17-K17-L17) | F18: =IF($A18>LastT,0,IF($A18=PolicyTerm,E18,0)) | G18: =IF($A18>LastT,0,E18-F18) | H18: =IF($A18=0,PolicyCount,0) | I18: =IF($A18>LastT,0,IF(AND($C$3="mass",$A18=T0),(G18+H18)*$E$3,0)) | J18: =IF($A18>LastT,0,G18+H18-I18) | K18: =IF($A18>LastT,0,J18*Policy_Sched!$C18*Policy_Sched!$D18*C18) | L18: =J18*D18 | M18: =IF($A18>LastT,0,(SizeAnnPrem*ExpsMaintAnnPrem+(SumAssured*ExpsMaintSA+ExpsMaintPol)*B18)*(1+IF($B$3="exps",$E$3,0))) | N18: =SizePremium*J18 | O18: =SumAssured*K18 | P18: =Policy_Sched!$I18*(L18+I18) | Q18: =O18+P18 | R18: =IF($A18=0,SizeExpsAcq0*H18,0) | S18: =IF($A18=0,SizeExpsCommInit0*J18,0) | T18: =Policy_Sched!$J18*J18 | U18: =M18*J18 | V18: =S18+T18+R18+U18 | W18: =IF($A18>LastT,0,N18+W19/(1+Policy_Sched!$K18)) | X18: =IF($A18>LastT,0,(-Q18+X19)/(1+Policy_Sched!$K18)) | Y18: =IF($A18>LastT,0,-V18+Y19/(1+Policy_Sched!$K18)) | Z18: =W18+Y18+X18 | AA18: =IF($A18>LastT,0,N18-V18-Q18/(1+Policy_Sched!$K18)+Z19/(1+Policy_Sched!$K18))
A19: =A18+1 | B19: =IF($A19>LastT,0,IF($B$3="exps",B18*(1+InflRate+IF($A19>=T0,$G$3,0)),B18/(1+InflRate))) | C19: =IF($A19>LastT,0,IF(AND($D$3<>0,$A19>=T0,Policy_Sched!$B19<LastAge),1+$D$3*$E$3,1)) | D19: =IF($A19>LastT,0,IF($C$3="up",MIN(Policy_Sched!$E19*(1+IF($A19>=T0,$E$3,0)),$F$3),IF($C$3="down",MAX(Policy_Sched!$E19*(1-IF($A19>=T0,$E$3,0)),Policy_Sched!$E19-$F$3),Policy_Sched!$E19))) | E19: =IF($A19>LastT,0,J18-K18-L18) | F19: =IF($A19>LastT,0,IF($A19=PolicyTerm,E19,0)) | G19: =IF($A19>LastT,0,E19-F19) | H19: =IF($A19=0,PolicyCount,0) | I19: =IF($A19>LastT,0,IF(AND($C$3="mass",$A19=T0),(G19+H19)*$E$3,0)) | J19: =IF($A19>LastT,0,G19+H19-I19) | K19: =IF($A19>LastT,0,J19*Policy_Sched!$C19*Policy_Sched!$D19*C19) | L19: =J19*D19 | M19: =IF($A19>LastT,0,(SizeAnnPrem*ExpsMaintAnnPrem+(SumAssured*ExpsMaintSA+ExpsMaintPol)*B19)*(1+IF($B$3="exps",$E$3,0))) | N19: =SizePremium*J19 | O19: =SumAssured*K19 | P19: =Policy_Sched!$I19*(L19+I19) | Q19: =O19+P19 | R19: =IF($A19=0,SizeExpsAcq0*H19,0) | S19: =IF($A19=0,SizeExpsCommInit0*J19,0) | T19: =Policy_Sched!$J19*J19 | U19: =M19*J19 | V19: =S19+T19+R19+U19 | W19: =IF($A19>LastT,0,N19+W20/(1+Policy_Sched!$K19)) | X19: =IF($A19>LastT,0,(-Q19+X20)/(1+Policy_Sched!$K19)) | Y19: =IF($A19>LastT,0,-V19+Y20/(1+Policy_Sched!$K19)) | Z19: =W19+Y19+X19 | AA19: =IF($A19>LastT,0,N19-V19-Q19/(1+Policy_Sched!$K19)+Z20/(1+Policy_Sched!$K19))
... A110: =A109+1 | B110: =IF($A110>LastT,0,IF($B$3="exps",B109*(1+InflRate+IF($A110>=T0,$G$3,0)),B109/(1+InflRate))) | C110: =IF($A110>LastT,0,IF(AND($D$3<>0,$A110>=T0,Policy_Sched!$B110<LastAge),1+$D$3*$E$3,1)) | D110: =IF($A110>LastT,0,IF($C$3="up",MIN(Policy_Sched!$E110*(1+IF($A110>=T0,$E$3,0)),$F$3),IF($C$3="down",MAX(Policy_Sched!$E110*(1-IF($A110>=T0,$E$3,0)),Policy_Sched!$E110-$F$3),Policy_Sched!$E110))) | E110: =IF($A110>LastT,0,J109-K109-L109) | F110: =IF($A110>LastT,0,IF($A110=PolicyTerm,E110,0)) | G110: =IF($A110>LastT,0,E110-F110) | H110: =IF($A110=0,PolicyCount,0) | I110: =IF($A110>LastT,0,IF(AND($C$3="mass",$A110=T0),(G110+H110)*$E$3,0)) | J110: =IF($A110>LastT,0,G110+H110-I110) | K110: =IF($A110>LastT,0,J110*Policy_Sched!$C110*Policy_Sched!$D110*C110) | L110: =J110*D110 | M110: =IF($A110>LastT,0,(SizeAnnPrem*ExpsMaintAnnPrem+(SumAssured*ExpsMaintSA+ExpsMaintPol)*B110)*(1+IF($B$3="exps",$E$3,0))) | N110: =SizePremium*J110 | O110: =SumAssured*K110 | P110: =Policy_Sched!$I110*(L110+I110) | Q110: =O110+P110 | R110: =IF($A110=0,SizeExpsAcq0*H110,0) | S110: =IF($A110=0,SizeExpsCommInit0*J110,0) | T110: =Policy_Sched!$J110*J110 | U110: =M110*J110 | V110: =S110+T110+R110+U110 | W110: =IF($A110>LastT,0,N110+W111/(1+Policy_Sched!$K110)) | X110: =IF($A110>LastT,0,(-Q110+X111)/(1+Policy_Sched!$K110)) | Y110: =IF($A110>LastT,0,-V110+Y111/(1+Policy_Sched!$K110)) | Z110: =W110+Y110+X110 | AA110: =IF($A110>LastT,0,N110-V110-Q110/(1+Policy_Sched!$K110)+Z111/(1+Policy_Sched!$K110))

Sheet Proj_LapseUp
A1: Liability projection — lapse up stress. lifelib SCR_life.Projection['lapse', 'up', None]
B2: Risk | C2: Shock | D2: Risk sign | E2: Shock factor | F2: Shock limit | G2: Inflation shock
B3: lapse | C3: up | D3: 0 | E3: =IFERROR(INDEX(FactorVals,MATCH($B$3&"|"&$C$3&"||",FactorKeys,0)),0) | F3: =IFERROR(INDEX(FactorVals,MATCH($B$3&"|"&$C$3&"||limit",FactorKeys,0)),0) | G3: =IFERROR(INDEX(FactorVals,MATCH($B$3&"|||inflation",FactorKeys,0)),0)
B4: Risk | C4: Shock | E4: Factor
A5: t | B5: Inflation factor | C5: Mortality shock factor | D5: Surrender rate | E5: In force: end | F5: Maturities | G5: In force: after maturity | H5: New business | I5: Mass lapse | J5: In force: beginning | K5: Deaths | L5: Surrenders | M5: Maint expense pp | N5: Premium income | O5: Death benefits | P5: Surrender benefits | Q5: Total benefits | R5: Acquisition expenses | S5: Initial commission | T5: Renewal commission | U5: Maintenance expenses | V5: Total expenses | W5: PV premiums | X5: PV benefits | Y5: PV expenses | Z5: PV net cashflow | AA5: PV net cf (fwd check)
A6: t | B6: InflFactor | C6: MortRateFactor | D6: SurrRate | E6: PolsIF_End | F6: PolsMaturity | G6: PolsIF_Beg | H6: PolsNewBiz | I6: PolsSurrMass | J6: PolsIF_Beg1 | K6: PolsDeath | L6: PolsSurr | M6: SizeExpsMaint | N6: PremIncome | O6: BenefitDeath | P6: BenefitSurr | Q6: BenefitTotal | R6: ExpsAcq | S6: ExpsCommInit | T6: ExpsCommRen | U6: ExpsMaint | V6: ExpsTotal | W6: PV_PremIncome | X6: PV_BenefitTotal | Y6: PV_ExpsTotal | Z6: PV_NetCashflow | AA6: PV_NetCashflowForCheck
A7: 0 | B7: =1 | C7: =IF($A7>LastT,0,IF(AND($D$3<>0,$A7>=T0,Policy_Sched!$B7<LastAge),1+$D$3*$E$3,1)) | D7: =IF($A7>LastT,0,IF($C$3="up",MIN(Policy_Sched!$E7*(1+IF($A7>=T0,$E$3,0)),$F$3),IF($C$3="down",MAX(Policy_Sched!$E7*(1-IF($A7>=T0,$E$3,0)),Policy_Sched!$E7-$F$3),Policy_Sched!$E7))) | E7: =0 | F7: =IF($A7>LastT,0,IF($A7=PolicyTerm,E7,0)) | G7: =IF($A7>LastT,0,E7-F7) | H7: =IF($A7=0,PolicyCount,0) | I7: =IF($A7>LastT,0,IF(AND($C$3="mass",$A7=T0),(G7+H7)*$E$3,0)) | J7: =IF($A7>LastT,0,G7+H7-I7) | K7: =IF($A7>LastT,0,J7*Policy_Sched!$C7*Policy_Sched!$D7*C7) | L7: =J7*D7 | M7: =IF($A7>LastT,0,(SizeAnnPrem*ExpsMaintAnnPrem+(SumAssured*ExpsMaintSA+ExpsMaintPol)*B7)*(1+IF($B$3="exps",$E$3,0))) | N7: =SizePremium*J7 | O7: =SumAssured*K7 | P7: =Policy_Sched!$I7*(L7+I7) | Q7: =O7+P7 | R7: =IF($A7=0,SizeExpsAcq0*H7,0) | S7: =IF($A7=0,SizeExpsCommInit0*J7,0) | T7: =Policy_Sched!$J7*J7 | U7: =M7*J7 | V7: =S7+T7+R7+U7 | W7: =IF($A7>LastT,0,N7+W8/(1+Policy_Sched!$K7)) | X7: =IF($A7>LastT,0,(-Q7+X8)/(1+Policy_Sched!$K7)) | Y7: =IF($A7>LastT,0,-V7+Y8/(1+Policy_Sched!$K7)) | Z7: =W7+Y7+X7 | AA7: =IF($A7>LastT,0,N7-V7-Q7/(1+Policy_Sched!$K7)+Z8/(1+Policy_Sched!$K7))
A8: =A7+1 | B8: =IF($A8>LastT,0,IF($B$3="exps",B7*(1+InflRate+IF($A8>=T0,$G$3,0)),B7/(1+InflRate))) | C8: =IF($A8>LastT,0,IF(AND($D$3<>0,$A8>=T0,Policy_Sched!$B8<LastAge),1+$D$3*$E$3,1)) | D8: =IF($A8>LastT,0,IF($C$3="up",MIN(Policy_Sched!$E8*(1+IF($A8>=T0,$E$3,0)),$F$3),IF($C$3="down",MAX(Policy_Sched!$E8*(1-IF($A8>=T0,$E$3,0)),Policy_Sched!$E8-$F$3),Policy_Sched!$E8))) | E8: =IF($A8>LastT,0,J7-K7-L7) | F8: =IF($A8>LastT,0,IF($A8=PolicyTerm,E8,0)) | G8: =IF($A8>LastT,0,E8-F8) | H8: =IF($A8=0,PolicyCount,0) | I8: =IF($A8>LastT,0,IF(AND($C$3="mass",$A8=T0),(G8+H8)*$E$3,0)) | J8: =IF($A8>LastT,0,G8+H8-I8) | K8: =IF($A8>LastT,0,J8*Policy_Sched!$C8*Policy_Sched!$D8*C8) | L8: =J8*D8 | M8: =IF($A8>LastT,0,(SizeAnnPrem*ExpsMaintAnnPrem+(SumAssured*ExpsMaintSA+ExpsMaintPol)*B8)*(1+IF($B$3="exps",$E$3,0))) | N8: =SizePremium*J8 | O8: =SumAssured*K8 | P8: =Policy_Sched!$I8*(L8+I8) | Q8: =O8+P8 | R8: =IF($A8=0,SizeExpsAcq0*H8,0) | S8: =IF($A8=0,SizeExpsCommInit0*J8,0) | T8: =Policy_Sched!$J8*J8 | U8: =M8*J8 | V8: =S8+T8+R8+U8 | W8: =IF($A8>LastT,0,N8+W9/(1+Policy_Sched!$K8)) | X8: =IF($A8>LastT,0,(-Q8+X9)/(1+Policy_Sched!$K8)) | Y8: =IF($A8>LastT,0,-V8+Y9/(1+Policy_Sched!$K8)) | Z8: =W8+Y8+X8 | AA8: =IF($A8>LastT,0,N8-V8-Q8/(1+Policy_Sched!$K8)+Z9/(1+Policy_Sched!$K8))
A9: =A8+1 | B9: =IF($A9>LastT,0,IF($B$3="exps",B8*(1+InflRate+IF($A9>=T0,$G$3,0)),B8/(1+InflRate))) | C9: =IF($A9>LastT,0,IF(AND($D$3<>0,$A9>=T0,Policy_Sched!$B9<LastAge),1+$D$3*$E$3,1)) | D9: =IF($A9>LastT,0,IF($C$3="up",MIN(Policy_Sched!$E9*(1+IF($A9>=T0,$E$3,0)),$F$3),IF($C$3="down",MAX(Policy_Sched!$E9*(1-IF($A9>=T0,$E$3,0)),Policy_Sched!$E9-$F$3),Policy_Sched!$E9))) | E9: =IF($A9>LastT,0,J8-K8-L8) | F9: =IF($A9>LastT,0,IF($A9=PolicyTerm,E9,0)) | G9: =IF($A9>LastT,0,E9-F9) | H9: =IF($A9=0,PolicyCount,0) | I9: =IF($A9>LastT,0,IF(AND($C$3="mass",$A9=T0),(G9+H9)*$E$3,0)) | J9: =IF($A9>LastT,0,G9+H9-I9) | K9: =IF($A9>LastT,0,J9*Policy_Sched!$C9*Policy_Sched!$D9*C9) | L9: =J9*D9 | M9: =IF($A9>LastT,0,(SizeAnnPrem*ExpsMaintAnnPrem+(SumAssured*ExpsMaintSA+ExpsMaintPol)*B9)*(1+IF($B$3="exps",$E$3,0))) | N9: =SizePremium*J9 | O9: =SumAssured*K9 | P9: =Policy_Sched!$I9*(L9+I9) | Q9: =O9+P9 | R9: =IF($A9=0,SizeExpsAcq0*H9,0) | S9: =IF($A9=0,SizeExpsCommInit0*J9,0) | T9: =Policy_Sched!$J9*J9 | U9: =M9*J9 | V9: =S9+T9+R9+U9 | W9: =IF($A9>LastT,0,N9+W10/(1+Policy_Sched!$K9)) | X9: =IF($A9>LastT,0,(-Q9+X10)/(1+Policy_Sched!$K9)) | Y9: =IF($A9>LastT,0,-V9+Y10/(1+Policy_Sched!$K9)) | Z9: =W9+Y9+X9 | AA9: =IF($A9>LastT,0,N9-V9-Q9/(1+Policy_Sched!$K9)+Z10/(1+Policy_Sched!$K9))
A10: =A9+1 | B10: =IF($A10>LastT,0,IF($B$3="exps",B9*(1+InflRate+IF($A10>=T0,$G$3,0)),B9/(1+InflRate))) | C10: =IF($A10>LastT,0,IF(AND($D$3<>0,$A10>=T0,Policy_Sched!$B10<LastAge),1+$D$3*$E$3,1)) | D10: =IF($A10>LastT,0,IF($C$3="up",MIN(Policy_Sched!$E10*(1+IF($A10>=T0,$E$3,0)),$F$3),IF($C$3="down",MAX(Policy_Sched!$E10*(1-IF($A10>=T0,$E$3,0)),Policy_Sched!$E10-$F$3),Policy_Sched!$E10))) | E10: =IF($A10>LastT,0,J9-K9-L9) | F10: =IF($A10>LastT,0,IF($A10=PolicyTerm,E10,0)) | G10: =IF($A10>LastT,0,E10-F10) | H10: =IF($A10=0,PolicyCount,0) | I10: =IF($A10>LastT,0,IF(AND($C$3="mass",$A10=T0),(G10+H10)*$E$3,0)) | J10: =IF($A10>LastT,0,G10+H10-I10) | K10: =IF($A10>LastT,0,J10*Policy_Sched!$C10*Policy_Sched!$D10*C10) | L10: =J10*D10 | M10: =IF($A10>LastT,0,(SizeAnnPrem*ExpsMaintAnnPrem+(SumAssured*ExpsMaintSA+ExpsMaintPol)*B10)*(1+IF($B$3="exps",$E$3,0))) | N10: =SizePremium*J10 | O10: =SumAssured*K10 | P10: =Policy_Sched!$I10*(L10+I10) | Q10: =O10+P10 | R10: =IF($A10=0,SizeExpsAcq0*H10,0) | S10: =IF($A10=0,SizeExpsCommInit0*J10,0) | T10: =Policy_Sched!$J10*J10 | U10: =M10*J10 | V10: =S10+T10+R10+U10 | W10: =IF($A10>LastT,0,N10+W11/(1+Policy_Sched!$K10)) | X10: =IF($A10>LastT,0,(-Q10+X11)/(1+Policy_Sched!$K10)) | Y10: =IF($A10>LastT,0,-V10+Y11/(1+Policy_Sched!$K10)) | Z10: =W10+Y10+X10 | AA10: =IF($A10>LastT,0,N10-V10-Q10/(1+Policy_Sched!$K10)+Z11/(1+Policy_Sched!$K10))
A11: =A10+1 | B11: =IF($A11>LastT,0,IF($B$3="exps",B10*(1+InflRate+IF($A11>=T0,$G$3,0)),B10/(1+InflRate))) | C11: =IF($A11>LastT,0,IF(AND($D$3<>0,$A11>=T0,Policy_Sched!$B11<LastAge),1+$D$3*$E$3,1)) | D11: =IF($A11>LastT,0,IF($C$3="up",MIN(Policy_Sched!$E11*(1+IF($A11>=T0,$E$3,0)),$F$3),IF($C$3="down",MAX(Policy_Sched!$E11*(1-IF($A11>=T0,$E$3,0)),Policy_Sched!$E11-$F$3),Policy_Sched!$E11))) | E11: =IF($A11>LastT,0,J10-K10-L10) | F11: =IF($A11>LastT,0,IF($A11=PolicyTerm,E11,0)) | G11: =IF($A11>LastT,0,E11-F11) | H11: =IF($A11=0,PolicyCount,0) | I11: =IF($A11>LastT,0,IF(AND($C$3="mass",$A11=T0),(G11+H11)*$E$3,0)) | J11: =IF($A11>LastT,0,G11+H11-I11) | K11: =IF($A11>LastT,0,J11*Policy_Sched!$C11*Policy_Sched!$D11*C11) | L11: =J11*D11 | M11: =IF($A11>LastT,0,(SizeAnnPrem*ExpsMaintAnnPrem+(SumAssured*ExpsMaintSA+ExpsMaintPol)*B11)*(1+IF($B$3="exps",$E$3,0))) | N11: =SizePremium*J11 | O11: =SumAssured*K11 | P11: =Policy_Sched!$I11*(L11+I11) | Q11: =O11+P11 | R11: =IF($A11=0,SizeExpsAcq0*H11,0) | S11: =IF($A11=0,SizeExpsCommInit0*J11,0) | T11: =Policy_Sched!$J11*J11 | U11: =M11*J11 | V11: =S11+T11+R11+U11 | W11: =IF($A11>LastT,0,N11+W12/(1+Policy_Sched!$K11)) | X11: =IF($A11>LastT,0,(-Q11+X12)/(1+Policy_Sched!$K11)) | Y11: =IF($A11>LastT,0,-V11+Y12/(1+Policy_Sched!$K11)) | Z11: =W11+Y11+X11 | AA11: =IF($A11>LastT,0,N11-V11-Q11/(1+Policy_Sched!$K11)+Z12/(1+Policy_Sched!$K11))
A12: =A11+1 | B12: =IF($A12>LastT,0,IF($B$3="exps",B11*(1+InflRate+IF($A12>=T0,$G$3,0)),B11/(1+InflRate))) | C12: =IF($A12>LastT,0,IF(AND($D$3<>0,$A12>=T0,Policy_Sched!$B12<LastAge),1+$D$3*$E$3,1)) | D12: =IF($A12>LastT,0,IF($C$3="up",MIN(Policy_Sched!$E12*(1+IF($A12>=T0,$E$3,0)),$F$3),IF($C$3="down",MAX(Policy_Sched!$E12*(1-IF($A12>=T0,$E$3,0)),Policy_Sched!$E12-$F$3),Policy_Sched!$E12))) | E12: =IF($A12>LastT,0,J11-K11-L11) | F12: =IF($A12>LastT,0,IF($A12=PolicyTerm,E12,0)) | G12: =IF($A12>LastT,0,E12-F12) | H12: =IF($A12=0,PolicyCount,0) | I12: =IF($A12>LastT,0,IF(AND($C$3="mass",$A12=T0),(G12+H12)*$E$3,0)) | J12: =IF($A12>LastT,0,G12+H12-I12) | K12: =IF($A12>LastT,0,J12*Policy_Sched!$C12*Policy_Sched!$D12*C12) | L12: =J12*D12 | M12: =IF($A12>LastT,0,(SizeAnnPrem*ExpsMaintAnnPrem+(SumAssured*ExpsMaintSA+ExpsMaintPol)*B12)*(1+IF($B$3="exps",$E$3,0))) | N12: =SizePremium*J12 | O12: =SumAssured*K12 | P12: =Policy_Sched!$I12*(L12+I12) | Q12: =O12+P12 | R12: =IF($A12=0,SizeExpsAcq0*H12,0) | S12: =IF($A12=0,SizeExpsCommInit0*J12,0) | T12: =Policy_Sched!$J12*J12 | U12: =M12*J12 | V12: =S12+T12+R12+U12 | W12: =IF($A12>LastT,0,N12+W13/(1+Policy_Sched!$K12)) | X12: =IF($A12>LastT,0,(-Q12+X13)/(1+Policy_Sched!$K12)) | Y12: =IF($A12>LastT,0,-V12+Y13/(1+Policy_Sched!$K12)) | Z12: =W12+Y12+X12 | AA12: =IF($A12>LastT,0,N12-V12-Q12/(1+Policy_Sched!$K12)+Z13/(1+Policy_Sched!$K12))
A13: =A12+1 | B13: =IF($A13>LastT,0,IF($B$3="exps",B12*(1+InflRate+IF($A13>=T0,$G$3,0)),B12/(1+InflRate))) | C13: =IF($A13>LastT,0,IF(AND($D$3<>0,$A13>=T0,Policy_Sched!$B13<LastAge),1+$D$3*$E$3,1)) | D13: =IF($A13>LastT,0,IF($C$3="up",MIN(Policy_Sched!$E13*(1+IF($A13>=T0,$E$3,0)),$F$3),IF($C$3="down",MAX(Policy_Sched!$E13*(1-IF($A13>=T0,$E$3,0)),Policy_Sched!$E13-$F$3),Policy_Sched!$E13))) | E13: =IF($A13>LastT,0,J12-K12-L12) | F13: =IF($A13>LastT,0,IF($A13=PolicyTerm,E13,0)) | G13: =IF($A13>LastT,0,E13-F13) | H13: =IF($A13=0,PolicyCount,0) | I13: =IF($A13>LastT,0,IF(AND($C$3="mass",$A13=T0),(G13+H13)*$E$3,0)) | J13: =IF($A13>LastT,0,G13+H13-I13) | K13: =IF($A13>LastT,0,J13*Policy_Sched!$C13*Policy_Sched!$D13*C13) | L13: =J13*D13 | M13: =IF($A13>LastT,0,(SizeAnnPrem*ExpsMaintAnnPrem+(SumAssured*ExpsMaintSA+ExpsMaintPol)*B13)*(1+IF($B$3="exps",$E$3,0))) | N13: =SizePremium*J13 | O13: =SumAssured*K13 | P13: =Policy_Sched!$I13*(L13+I13) | Q13: =O13+P13 | R13: =IF($A13=0,SizeExpsAcq0*H13,0) | S13: =IF($A13=0,SizeExpsCommInit0*J13,0) | T13: =Policy_Sched!$J13*J13 | U13: =M13*J13 | V13: =S13+T13+R13+U13 | W13: =IF($A13>LastT,0,N13+W14/(1+Policy_Sched!$K13)) | X13: =IF($A13>LastT,0,(-Q13+X14)/(1+Policy_Sched!$K13)) | Y13: =IF($A13>LastT,0,-V13+Y14/(1+Policy_Sched!$K13)) | Z13: =W13+Y13+X13 | AA13: =IF($A13>LastT,0,N13-V13-Q13/(1+Policy_Sched!$K13)+Z14/(1+Policy_Sched!$K13))
A14: =A13+1 | B14: =IF($A14>LastT,0,IF($B$3="exps",B13*(1+InflRate+IF($A14>=T0,$G$3,0)),B13/(1+InflRate))) | C14: =IF($A14>LastT,0,IF(AND($D$3<>0,$A14>=T0,Policy_Sched!$B14<LastAge),1+$D$3*$E$3,1)) | D14: =IF($A14>LastT,0,IF($C$3="up",MIN(Policy_Sched!$E14*(1+IF($A14>=T0,$E$3,0)),$F$3),IF($C$3="down",MAX(Policy_Sched!$E14*(1-IF($A14>=T0,$E$3,0)),Policy_Sched!$E14-$F$3),Policy_Sched!$E14))) | E14: =IF($A14>LastT,0,J13-K13-L13) | F14: =IF($A14>LastT,0,IF($A14=PolicyTerm,E14,0)) | G14: =IF($A14>LastT,0,E14-F14) | H14: =IF($A14=0,PolicyCount,0) | I14: =IF($A14>LastT,0,IF(AND($C$3="mass",$A14=T0),(G14+H14)*$E$3,0)) | J14: =IF($A14>LastT,0,G14+H14-I14) | K14: =IF($A14>LastT,0,J14*Policy_Sched!$C14*Policy_Sched!$D14*C14) | L14: =J14*D14 | M14: =IF($A14>LastT,0,(SizeAnnPrem*ExpsMaintAnnPrem+(SumAssured*ExpsMaintSA+ExpsMaintPol)*B14)*(1+IF($B$3="exps",$E$3,0))) | N14: =SizePremium*J14 | O14: =SumAssured*K14 | P14: =Policy_Sched!$I14*(L14+I14) | Q14: =O14+P14 | R14: =IF($A14=0,SizeExpsAcq0*H14,0) | S14: =IF($A14=0,SizeExpsCommInit0*J14,0) | T14: =Policy_Sched!$J14*J14 | U14: =M14*J14 | V14: =S14+T14+R14+U14 | W14: =IF($A14>LastT,0,N14+W15/(1+Policy_Sched!$K14)) | X14: =IF($A14>LastT,0,(-Q14+X15)/(1+Policy_Sched!$K14)) | Y14: =IF($A14>LastT,0,-V14+Y15/(1+Policy_Sched!$K14)) | Z14: =W14+Y14+X14 | AA14: =IF($A14>LastT,0,N14-V14-Q14/(1+Policy_Sched!$K14)+Z15/(1+Policy_Sched!$K14))
A15: =A14+1 | B15: =IF($A15>LastT,0,IF($B$3="exps",B14*(1+InflRate+IF($A15>=T0,$G$3,0)),B14/(1+InflRate))) | C15: =IF($A15>LastT,0,IF(AND($D$3<>0,$A15>=T0,Policy_Sched!$B15<LastAge),1+$D$3*$E$3,1)) | D15: =IF($A15>LastT,0,IF($C$3="up",MIN(Policy_Sched!$E15*(1+IF($A15>=T0,$E$3,0)),$F$3),IF($C$3="down",MAX(Policy_Sched!$E15*(1-IF($A15>=T0,$E$3,0)),Policy_Sched!$E15-$F$3),Policy_Sched!$E15))) | E15: =IF($A15>LastT,0,J14-K14-L14) | F15: =IF($A15>LastT,0,IF($A15=PolicyTerm,E15,0)) | G15: =IF($A15>LastT,0,E15-F15) | H15: =IF($A15=0,PolicyCount,0) | I15: =IF($A15>LastT,0,IF(AND($C$3="mass",$A15=T0),(G15+H15)*$E$3,0)) | J15: =IF($A15>LastT,0,G15+H15-I15) | K15: =IF($A15>LastT,0,J15*Policy_Sched!$C15*Policy_Sched!$D15*C15) | L15: =J15*D15 | M15: =IF($A15>LastT,0,(SizeAnnPrem*ExpsMaintAnnPrem+(SumAssured*ExpsMaintSA+ExpsMaintPol)*B15)*(1+IF($B$3="exps",$E$3,0))) | N15: =SizePremium*J15 | O15: =SumAssured*K15 | P15: =Policy_Sched!$I15*(L15+I15) | Q15: =O15+P15 | R15: =IF($A15=0,SizeExpsAcq0*H15,0) | S15: =IF($A15=0,SizeExpsCommInit0*J15,0) | T15: =Policy_Sched!$J15*J15 | U15: =M15*J15 | V15: =S15+T15+R15+U15 | W15: =IF($A15>LastT,0,N15+W16/(1+Policy_Sched!$K15)) | X15: =IF($A15>LastT,0,(-Q15+X16)/(1+Policy_Sched!$K15)) | Y15: =IF($A15>LastT,0,-V15+Y16/(1+Policy_Sched!$K15)) | Z15: =W15+Y15+X15 | AA15: =IF($A15>LastT,0,N15-V15-Q15/(1+Policy_Sched!$K15)+Z16/(1+Policy_Sched!$K15))
A16: =A15+1 | B16: =IF($A16>LastT,0,IF($B$3="exps",B15*(1+InflRate+IF($A16>=T0,$G$3,0)),B15/(1+InflRate))) | C16: =IF($A16>LastT,0,IF(AND($D$3<>0,$A16>=T0,Policy_Sched!$B16<LastAge),1+$D$3*$E$3,1)) | D16: =IF($A16>LastT,0,IF($C$3="up",MIN(Policy_Sched!$E16*(1+IF($A16>=T0,$E$3,0)),$F$3),IF($C$3="down",MAX(Policy_Sched!$E16*(1-IF($A16>=T0,$E$3,0)),Policy_Sched!$E16-$F$3),Policy_Sched!$E16))) | E16: =IF($A16>LastT,0,J15-K15-L15) | F16: =IF($A16>LastT,0,IF($A16=PolicyTerm,E16,0)) | G16: =IF($A16>LastT,0,E16-F16) | H16: =IF($A16=0,PolicyCount,0) | I16: =IF($A16>LastT,0,IF(AND($C$3="mass",$A16=T0),(G16+H16)*$E$3,0)) | J16: =IF($A16>LastT,0,G16+H16-I16) | K16: =IF($A16>LastT,0,J16*Policy_Sched!$C16*Policy_Sched!$D16*C16) | L16: =J16*D16 | M16: =IF($A16>LastT,0,(SizeAnnPrem*ExpsMaintAnnPrem+(SumAssured*ExpsMaintSA+ExpsMaintPol)*B16)*(1+IF($B$3="exps",$E$3,0))) | N16: =SizePremium*J16 | O16: =SumAssured*K16 | P16: =Policy_Sched!$I16*(L16+I16) | Q16: =O16+P16 | R16: =IF($A16=0,SizeExpsAcq0*H16,0) | S16: =IF($A16=0,SizeExpsCommInit0*J16,0) | T16: =Policy_Sched!$J16*J16 | U16: =M16*J16 | V16: =S16+T16+R16+U16 | W16: =IF($A16>LastT,0,N16+W17/(1+Policy_Sched!$K16)) | X16: =IF($A16>LastT,0,(-Q16+X17)/(1+Policy_Sched!$K16)) | Y16: =IF($A16>LastT,0,-V16+Y17/(1+Policy_Sched!$K16)) | Z16: =W16+Y16+X16 | AA16: =IF($A16>LastT,0,N16-V16-Q16/(1+Policy_Sched!$K16)+Z17/(1+Policy_Sched!$K16))
A17: =A16+1 | B17: =IF($A17>LastT,0,IF($B$3="exps",B16*(1+InflRate+IF($A17>=T0,$G$3,0)),B16/(1+InflRate))) | C17: =IF($A17>LastT,0,IF(AND($D$3<>0,$A17>=T0,Policy_Sched!$B17<LastAge),1+$D$3*$E$3,1)) | D17: =IF($A17>LastT,0,IF($C$3="up",MIN(Policy_Sched!$E17*(1+IF($A17>=T0,$E$3,0)),$F$3),IF($C$3="down",MAX(Policy_Sched!$E17*(1-IF($A17>=T0,$E$3,0)),Policy_Sched!$E17-$F$3),Policy_Sched!$E17))) | E17: =IF($A17>LastT,0,J16-K16-L16) | F17: =IF($A17>LastT,0,IF($A17=PolicyTerm,E17,0)) | G17: =IF($A17>LastT,0,E17-F17) | H17: =IF($A17=0,PolicyCount,0) | I17: =IF($A17>LastT,0,IF(AND($C$3="mass",$A17=T0),(G17+H17)*$E$3,0)) | J17: =IF($A17>LastT,0,G17+H17-I17) | K17: =IF($A17>LastT,0,J17*Policy_Sched!$C17*Policy_Sched!$D17*C17) | L17: =J17*D17 | M17: =IF($A17>LastT,0,(SizeAnnPrem*ExpsMaintAnnPrem+(SumAssured*ExpsMaintSA+ExpsMaintPol)*B17)*(1+IF($B$3="exps",$E$3,0))) | N17: =SizePremium*J17 | O17: =SumAssured*K17 | P17: =Policy_Sched!$I17*(L17+I17) | Q17: =O17+P17 | R17: =IF($A17=0,SizeExpsAcq0*H17,0) | S17: =IF($A17=0,SizeExpsCommInit0*J17,0) | T17: =Policy_Sched!$J17*J17 | U17: =M17*J17 | V17: =S17+T17+R17+U17 | W17: =IF($A17>LastT,0,N17+W18/(1+Policy_Sched!$K17)) | X17: =IF($A17>LastT,0,(-Q17+X18)/(1+Policy_Sched!$K17)) | Y17: =IF($A17>LastT,0,-V17+Y18/(1+Policy_Sched!$K17)) | Z17: =W17+Y17+X17 | AA17: =IF($A17>LastT,0,N17-V17-Q17/(1+Policy_Sched!$K17)+Z18/(1+Policy_Sched!$K17))
A18: =A17+1 | B18: =IF($A18>LastT,0,IF($B$3="exps",B17*(1+InflRate+IF($A18>=T0,$G$3,0)),B17/(1+InflRate))) | C18: =IF($A18>LastT,0,IF(AND($D$3<>0,$A18>=T0,Policy_Sched!$B18<LastAge),1+$D$3*$E$3,1)) | D18: =IF($A18>LastT,0,IF($C$3="up",MIN(Policy_Sched!$E18*(1+IF($A18>=T0,$E$3,0)),$F$3),IF($C$3="down",MAX(Policy_Sched!$E18*(1-IF($A18>=T0,$E$3,0)),Policy_Sched!$E18-$F$3),Policy_Sched!$E18))) | E18: =IF($A18>LastT,0,J17-K17-L17) | F18: =IF($A18>LastT,0,IF($A18=PolicyTerm,E18,0)) | G18: =IF($A18>LastT,0,E18-F18) | H18: =IF($A18=0,PolicyCount,0) | I18: =IF($A18>LastT,0,IF(AND($C$3="mass",$A18=T0),(G18+H18)*$E$3,0)) | J18: =IF($A18>LastT,0,G18+H18-I18) | K18: =IF($A18>LastT,0,J18*Policy_Sched!$C18*Policy_Sched!$D18*C18) | L18: =J18*D18 | M18: =IF($A18>LastT,0,(SizeAnnPrem*ExpsMaintAnnPrem+(SumAssured*ExpsMaintSA+ExpsMaintPol)*B18)*(1+IF($B$3="exps",$E$3,0))) | N18: =SizePremium*J18 | O18: =SumAssured*K18 | P18: =Policy_Sched!$I18*(L18+I18) | Q18: =O18+P18 | R18: =IF($A18=0,SizeExpsAcq0*H18,0) | S18: =IF($A18=0,SizeExpsCommInit0*J18,0) | T18: =Policy_Sched!$J18*J18 | U18: =M18*J18 | V18: =S18+T18+R18+U18 | W18: =IF($A18>LastT,0,N18+W19/(1+Policy_Sched!$K18)) | X18: =IF($A18>LastT,0,(-Q18+X19)/(1+Policy_Sched!$K18)) | Y18: =IF($A18>LastT,0,-V18+Y19/(1+Policy_Sched!$K18)) | Z18: =W18+Y18+X18 | AA18: =IF($A18>LastT,0,N18-V18-Q18/(1+Policy_Sched!$K18)+Z19/(1+Policy_Sched!$K18))
A19: =A18+1 | B19: =IF($A19>LastT,0,IF($B$3="exps",B18*(1+InflRate+IF($A19>=T0,$G$3,0)),B18/(1+InflRate))) | C19: =IF($A19>LastT,0,IF(AND($D$3<>0,$A19>=T0,Policy_Sched!$B19<LastAge),1+$D$3*$E$3,1)) | D19: =IF($A19>LastT,0,IF($C$3="up",MIN(Policy_Sched!$E19*(1+IF($A19>=T0,$E$3,0)),$F$3),IF($C$3="down",MAX(Policy_Sched!$E19*(1-IF($A19>=T0,$E$3,0)),Policy_Sched!$E19-$F$3),Policy_Sched!$E19))) | E19: =IF($A19>LastT,0,J18-K18-L18) | F19: =IF($A19>LastT,0,IF($A19=PolicyTerm,E19,0)) | G19: =IF($A19>LastT,0,E19-F19) | H19: =IF($A19=0,PolicyCount,0) | I19: =IF($A19>LastT,0,IF(AND($C$3="mass",$A19=T0),(G19+H19)*$E$3,0)) | J19: =IF($A19>LastT,0,G19+H19-I19) | K19: =IF($A19>LastT,0,J19*Policy_Sched!$C19*Policy_Sched!$D19*C19) | L19: =J19*D19 | M19: =IF($A19>LastT,0,(SizeAnnPrem*ExpsMaintAnnPrem+(SumAssured*ExpsMaintSA+ExpsMaintPol)*B19)*(1+IF($B$3="exps",$E$3,0))) | N19: =SizePremium*J19 | O19: =SumAssured*K19 | P19: =Policy_Sched!$I19*(L19+I19) | Q19: =O19+P19 | R19: =IF($A19=0,SizeExpsAcq0*H19,0) | S19: =IF($A19=0,SizeExpsCommInit0*J19,0) | T19: =Policy_Sched!$J19*J19 | U19: =M19*J19 | V19: =S19+T19+R19+U19 | W19: =IF($A19>LastT,0,N19+W20/(1+Policy_Sched!$K19)) | X19: =IF($A19>LastT,0,(-Q19+X20)/(1+Policy_Sched!$K19)) | Y19: =IF($A19>LastT,0,-V19+Y20/(1+Policy_Sched!$K19)) | Z19: =W19+Y19+X19 | AA19: =IF($A19>LastT,0,N19-V19-Q19/(1+Policy_Sched!$K19)+Z20/(1+Policy_Sched!$K19))
... A110: =A109+1 | B110: =IF($A110>LastT,0,IF($B$3="exps",B109*(1+InflRate+IF($A110>=T0,$G$3,0)),B109/(1+InflRate))) | C110: =IF($A110>LastT,0,IF(AND($D$3<>0,$A110>=T0,Policy_Sched!$B110<LastAge),1+$D$3*$E$3,1)) | D110: =IF($A110>LastT,0,IF($C$3="up",MIN(Policy_Sched!$E110*(1+IF($A110>=T0,$E$3,0)),$F$3),IF($C$3="down",MAX(Policy_Sched!$E110*(1-IF($A110>=T0,$E$3,0)),Policy_Sched!$E110-$F$3),Policy_Sched!$E110))) | E110: =IF($A110>LastT,0,J109-K109-L109) | F110: =IF($A110>LastT,0,IF($A110=PolicyTerm,E110,0)) | G110: =IF($A110>LastT,0,E110-F110) | H110: =IF($A110=0,PolicyCount,0) | I110: =IF($A110>LastT,0,IF(AND($C$3="mass",$A110=T0),(G110+H110)*$E$3,0)) | J110: =IF($A110>LastT,0,G110+H110-I110) | K110: =IF($A110>LastT,0,J110*Policy_Sched!$C110*Policy_Sched!$D110*C110) | L110: =J110*D110 | M110: =IF($A110>LastT,0,(SizeAnnPrem*ExpsMaintAnnPrem+(SumAssured*ExpsMaintSA+ExpsMaintPol)*B110)*(1+IF($B$3="exps",$E$3,0))) | N110: =SizePremium*J110 | O110: =SumAssured*K110 | P110: =Policy_Sched!$I110*(L110+I110) | Q110: =O110+P110 | R110: =IF($A110=0,SizeExpsAcq0*H110,0) | S110: =IF($A110=0,SizeExpsCommInit0*J110,0) | T110: =Policy_Sched!$J110*J110 | U110: =M110*J110 | V110: =S110+T110+R110+U110 | W110: =IF($A110>LastT,0,N110+W111/(1+Policy_Sched!$K110)) | X110: =IF($A110>LastT,0,(-Q110+X111)/(1+Policy_Sched!$K110)) | Y110: =IF($A110>LastT,0,-V110+Y111/(1+Policy_Sched!$K110)) | Z110: =W110+Y110+X110 | AA110: =IF($A110>LastT,0,N110-V110-Q110/(1+Policy_Sched!$K110)+Z111/(1+Policy_Sched!$K110))

Sheet Proj_LapseDown
A1: Liability projection — lapse down stress. lifelib SCR_life.Projection['lapse', 'down', None]
B2: Risk | C2: Shock | D2: Risk sign | E2: Shock factor | F2: Shock limit | G2: Inflation shock
B3: lapse | C3: down | D3: 0 | E3: =IFERROR(INDEX(FactorVals,MATCH($B$3&"|"&$C$3&"||",FactorKeys,0)),0) | F3: =IFERROR(INDEX(FactorVals,MATCH($B$3&"|"&$C$3&"||limit",FactorKeys,0)),0) | G3: =IFERROR(INDEX(FactorVals,MATCH($B$3&"|||inflation",FactorKeys,0)),0)
B4: Risk | C4: Shock | E4: Factor
A5: t | B5: Inflation factor | C5: Mortality shock factor | D5: Surrender rate | E5: In force: end | F5: Maturities | G5: In force: after maturity | H5: New business | I5: Mass lapse | J5: In force: beginning | K5: Deaths | L5: Surrenders | M5: Maint expense pp | N5: Premium income | O5: Death benefits | P5: Surrender benefits | Q5: Total benefits | R5: Acquisition expenses | S5: Initial commission | T5: Renewal commission | U5: Maintenance expenses | V5: Total expenses | W5: PV premiums | X5: PV benefits | Y5: PV expenses | Z5: PV net cashflow | AA5: PV net cf (fwd check)
A6: t | B6: InflFactor | C6: MortRateFactor | D6: SurrRate | E6: PolsIF_End | F6: PolsMaturity | G6: PolsIF_Beg | H6: PolsNewBiz | I6: PolsSurrMass | J6: PolsIF_Beg1 | K6: PolsDeath | L6: PolsSurr | M6: SizeExpsMaint | N6: PremIncome | O6: BenefitDeath | P6: BenefitSurr | Q6: BenefitTotal | R6: ExpsAcq | S6: ExpsCommInit | T6: ExpsCommRen | U6: ExpsMaint | V6: ExpsTotal | W6: PV_PremIncome | X6: PV_BenefitTotal | Y6: PV_ExpsTotal | Z6: PV_NetCashflow | AA6: PV_NetCashflowForCheck
A7: 0 | B7: =1 | C7: =IF($A7>LastT,0,IF(AND($D$3<>0,$A7>=T0,Policy_Sched!$B7<LastAge),1+$D$3*$E$3,1)) | D7: =IF($A7>LastT,0,IF($C$3="up",MIN(Policy_Sched!$E7*(1+IF($A7>=T0,$E$3,0)),$F$3),IF($C$3="down",MAX(Policy_Sched!$E7*(1-IF($A7>=T0,$E$3,0)),Policy_Sched!$E7-$F$3),Policy_Sched!$E7))) | E7: =0 | F7: =IF($A7>LastT,0,IF($A7=PolicyTerm,E7,0)) | G7: =IF($A7>LastT,0,E7-F7) | H7: =IF($A7=0,PolicyCount,0) | I7: =IF($A7>LastT,0,IF(AND($C$3="mass",$A7=T0),(G7+H7)*$E$3,0)) | J7: =IF($A7>LastT,0,G7+H7-I7) | K7: =IF($A7>LastT,0,J7*Policy_Sched!$C7*Policy_Sched!$D7*C7) | L7: =J7*D7 | M7: =IF($A7>LastT,0,(SizeAnnPrem*ExpsMaintAnnPrem+(SumAssured*ExpsMaintSA+ExpsMaintPol)*B7)*(1+IF($B$3="exps",$E$3,0))) | N7: =SizePremium*J7 | O7: =SumAssured*K7 | P7: =Policy_Sched!$I7*(L7+I7) | Q7: =O7+P7 | R7: =IF($A7=0,SizeExpsAcq0*H7,0) | S7: =IF($A7=0,SizeExpsCommInit0*J7,0) | T7: =Policy_Sched!$J7*J7 | U7: =M7*J7 | V7: =S7+T7+R7+U7 | W7: =IF($A7>LastT,0,N7+W8/(1+Policy_Sched!$K7)) | X7: =IF($A7>LastT,0,(-Q7+X8)/(1+Policy_Sched!$K7)) | Y7: =IF($A7>LastT,0,-V7+Y8/(1+Policy_Sched!$K7)) | Z7: =W7+Y7+X7 | AA7: =IF($A7>LastT,0,N7-V7-Q7/(1+Policy_Sched!$K7)+Z8/(1+Policy_Sched!$K7))
A8: =A7+1 | B8: =IF($A8>LastT,0,IF($B$3="exps",B7*(1+InflRate+IF($A8>=T0,$G$3,0)),B7/(1+InflRate))) | C8: =IF($A8>LastT,0,IF(AND($D$3<>0,$A8>=T0,Policy_Sched!$B8<LastAge),1+$D$3*$E$3,1)) | D8: =IF($A8>LastT,0,IF($C$3="up",MIN(Policy_Sched!$E8*(1+IF($A8>=T0,$E$3,0)),$F$3),IF($C$3="down",MAX(Policy_Sched!$E8*(1-IF($A8>=T0,$E$3,0)),Policy_Sched!$E8-$F$3),Policy_Sched!$E8))) | E8: =IF($A8>LastT,0,J7-K7-L7) | F8: =IF($A8>LastT,0,IF($A8=PolicyTerm,E8,0)) | G8: =IF($A8>LastT,0,E8-F8) | H8: =IF($A8=0,PolicyCount,0) | I8: =IF($A8>LastT,0,IF(AND($C$3="mass",$A8=T0),(G8+H8)*$E$3,0)) | J8: =IF($A8>LastT,0,G8+H8-I8) | K8: =IF($A8>LastT,0,J8*Policy_Sched!$C8*Policy_Sched!$D8*C8) | L8: =J8*D8 | M8: =IF($A8>LastT,0,(SizeAnnPrem*ExpsMaintAnnPrem+(SumAssured*ExpsMaintSA+ExpsMaintPol)*B8)*(1+IF($B$3="exps",$E$3,0))) | N8: =SizePremium*J8 | O8: =SumAssured*K8 | P8: =Policy_Sched!$I8*(L8+I8) | Q8: =O8+P8 | R8: =IF($A8=0,SizeExpsAcq0*H8,0) | S8: =IF($A8=0,SizeExpsCommInit0*J8,0) | T8: =Policy_Sched!$J8*J8 | U8: =M8*J8 | V8: =S8+T8+R8+U8 | W8: =IF($A8>LastT,0,N8+W9/(1+Policy_Sched!$K8)) | X8: =IF($A8>LastT,0,(-Q8+X9)/(1+Policy_Sched!$K8)) | Y8: =IF($A8>LastT,0,-V8+Y9/(1+Policy_Sched!$K8)) | Z8: =W8+Y8+X8 | AA8: =IF($A8>LastT,0,N8-V8-Q8/(1+Policy_Sched!$K8)+Z9/(1+Policy_Sched!$K8))
A9: =A8+1 | B9: =IF($A9>LastT,0,IF($B$3="exps",B8*(1+InflRate+IF($A9>=T0,$G$3,0)),B8/(1+InflRate))) | C9: =IF($A9>LastT,0,IF(AND($D$3<>0,$A9>=T0,Policy_Sched!$B9<LastAge),1+$D$3*$E$3,1)) | D9: =IF($A9>LastT,0,IF($C$3="up",MIN(Policy_Sched!$E9*(1+IF($A9>=T0,$E$3,0)),$F$3),IF($C$3="down",MAX(Policy_Sched!$E9*(1-IF($A9>=T0,$E$3,0)),Policy_Sched!$E9-$F$3),Policy_Sched!$E9))) | E9: =IF($A9>LastT,0,J8-K8-L8) | F9: =IF($A9>LastT,0,IF($A9=PolicyTerm,E9,0)) | G9: =IF($A9>LastT,0,E9-F9) | H9: =IF($A9=0,PolicyCount,0) | I9: =IF($A9>LastT,0,IF(AND($C$3="mass",$A9=T0),(G9+H9)*$E$3,0)) | J9: =IF($A9>LastT,0,G9+H9-I9) | K9: =IF($A9>LastT,0,J9*Policy_Sched!$C9*Policy_Sched!$D9*C9) | L9: =J9*D9 | M9: =IF($A9>LastT,0,(SizeAnnPrem*ExpsMaintAnnPrem+(SumAssured*ExpsMaintSA+ExpsMaintPol)*B9)*(1+IF($B$3="exps",$E$3,0))) | N9: =SizePremium*J9 | O9: =SumAssured*K9 | P9: =Policy_Sched!$I9*(L9+I9) | Q9: =O9+P9 | R9: =IF($A9=0,SizeExpsAcq0*H9,0) | S9: =IF($A9=0,SizeExpsCommInit0*J9,0) | T9: =Policy_Sched!$J9*J9 | U9: =M9*J9 | V9: =S9+T9+R9+U9 | W9: =IF($A9>LastT,0,N9+W10/(1+Policy_Sched!$K9)) | X9: =IF($A9>LastT,0,(-Q9+X10)/(1+Policy_Sched!$K9)) | Y9: =IF($A9>LastT,0,-V9+Y10/(1+Policy_Sched!$K9)) | Z9: =W9+Y9+X9 | AA9: =IF($A9>LastT,0,N9-V9-Q9/(1+Policy_Sched!$K9)+Z10/(1+Policy_Sched!$K9))
A10: =A9+1 | B10: =IF($A10>LastT,0,IF($B$3="exps",B9*(1+InflRate+IF($A10>=T0,$G$3,0)),B9/(1+InflRate))) | C10: =IF($A10>LastT,0,IF(AND($D$3<>0,$A10>=T0,Policy_Sched!$B10<LastAge),1+$D$3*$E$3,1)) | D10: =IF($A10>LastT,0,IF($C$3="up",MIN(Policy_Sched!$E10*(1+IF($A10>=T0,$E$3,0)),$F$3),IF($C$3="down",MAX(Policy_Sched!$E10*(1-IF($A10>=T0,$E$3,0)),Policy_Sched!$E10-$F$3),Policy_Sched!$E10))) | E10: =IF($A10>LastT,0,J9-K9-L9) | F10: =IF($A10>LastT,0,IF($A10=PolicyTerm,E10,0)) | G10: =IF($A10>LastT,0,E10-F10) | H10: =IF($A10=0,PolicyCount,0) | I10: =IF($A10>LastT,0,IF(AND($C$3="mass",$A10=T0),(G10+H10)*$E$3,0)) | J10: =IF($A10>LastT,0,G10+H10-I10) | K10: =IF($A10>LastT,0,J10*Policy_Sched!$C10*Policy_Sched!$D10*C10) | L10: =J10*D10 | M10: =IF($A10>LastT,0,(SizeAnnPrem*ExpsMaintAnnPrem+(SumAssured*ExpsMaintSA+ExpsMaintPol)*B10)*(1+IF($B$3="exps",$E$3,0))) | N10: =SizePremium*J10 | O10: =SumAssured*K10 | P10: =Policy_Sched!$I10*(L10+I10) | Q10: =O10+P10 | R10: =IF($A10=0,SizeExpsAcq0*H10,0) | S10: =IF($A10=0,SizeExpsCommInit0*J10,0) | T10: =Policy_Sched!$J10*J10 | U10: =M10*J10 | V10: =S10+T10+R10+U10 | W10: =IF($A10>LastT,0,N10+W11/(1+Policy_Sched!$K10)) | X10: =IF($A10>LastT,0,(-Q10+X11)/(1+Policy_Sched!$K10)) | Y10: =IF($A10>LastT,0,-V10+Y11/(1+Policy_Sched!$K10)) | Z10: =W10+Y10+X10 | AA10: =IF($A10>LastT,0,N10-V10-Q10/(1+Policy_Sched!$K10)+Z11/(1+Policy_Sched!$K10))
A11: =A10+1 | B11: =IF($A11>LastT,0,IF($B$3="exps",B10*(1+InflRate+IF($A11>=T0,$G$3,0)),B10/(1+InflRate))) | C11: =IF($A11>LastT,0,IF(AND($D$3<>0,$A11>=T0,Policy_Sched!$B11<LastAge),1+$D$3*$E$3,1)) | D11: =IF($A11>LastT,0,IF($C$3="up",MIN(Policy_Sched!$E11*(1+IF($A11>=T0,$E$3,0)),$F$3),IF($C$3="down",MAX(Policy_Sched!$E11*(1-IF($A11>=T0,$E$3,0)),Policy_Sched!$E11-$F$3),Policy_Sched!$E11))) | E11: =IF($A11>LastT,0,J10-K10-L10) | F11: =IF($A11>LastT,0,IF($A11=PolicyTerm,E11,0)) | G11: =IF($A11>LastT,0,E11-F11) | H11: =IF($A11=0,PolicyCount,0) | I11: =IF($A11>LastT,0,IF(AND($C$3="mass",$A11=T0),(G11+H11)*$E$3,0)) | J11: =IF($A11>LastT,0,G11+H11-I11) | K11: =IF($A11>LastT,0,J11*Policy_Sched!$C11*Policy_Sched!$D11*C11) | L11: =J11*D11 | M11: =IF($A11>LastT,0,(SizeAnnPrem*ExpsMaintAnnPrem+(SumAssured*ExpsMaintSA+ExpsMaintPol)*B11)*(1+IF($B$3="exps",$E$3,0))) | N11: =SizePremium*J11 | O11: =SumAssured*K11 | P11: =Policy_Sched!$I11*(L11+I11) | Q11: =O11+P11 | R11: =IF($A11=0,SizeExpsAcq0*H11,0) | S11: =IF($A11=0,SizeExpsCommInit0*J11,0) | T11: =Policy_Sched!$J11*J11 | U11: =M11*J11 | V11: =S11+T11+R11+U11 | W11: =IF($A11>LastT,0,N11+W12/(1+Policy_Sched!$K11)) | X11: =IF($A11>LastT,0,(-Q11+X12)/(1+Policy_Sched!$K11)) | Y11: =IF($A11>LastT,0,-V11+Y12/(1+Policy_Sched!$K11)) | Z11: =W11+Y11+X11 | AA11: =IF($A11>LastT,0,N11-V11-Q11/(1+Policy_Sched!$K11)+Z12/(1+Policy_Sched!$K11))
A12: =A11+1 | B12: =IF($A12>LastT,0,IF($B$3="exps",B11*(1+InflRate+IF($A12>=T0,$G$3,0)),B11/(1+InflRate))) | C12: =IF($A12>LastT,0,IF(AND($D$3<>0,$A12>=T0,Policy_Sched!$B12<LastAge),1+$D$3*$E$3,1)) | D12: =IF($A12>LastT,0,IF($C$3="up",MIN(Policy_Sched!$E12*(1+IF($A12>=T0,$E$3,0)),$F$3),IF($C$3="down",MAX(Policy_Sched!$E12*(1-IF($A12>=T0,$E$3,0)),Policy_Sched!$E12-$F$3),Policy_Sched!$E12))) | E12: =IF($A12>LastT,0,J11-K11-L11) | F12: =IF($A12>LastT,0,IF($A12=PolicyTerm,E12,0)) | G12: =IF($A12>LastT,0,E12-F12) | H12: =IF($A12=0,PolicyCount,0) | I12: =IF($A12>LastT,0,IF(AND($C$3="mass",$A12=T0),(G12+H12)*$E$3,0)) | J12: =IF($A12>LastT,0,G12+H12-I12) | K12: =IF($A12>LastT,0,J12*Policy_Sched!$C12*Policy_Sched!$D12*C12) | L12: =J12*D12 | M12: =IF($A12>LastT,0,(SizeAnnPrem*ExpsMaintAnnPrem+(SumAssured*ExpsMaintSA+ExpsMaintPol)*B12)*(1+IF($B$3="exps",$E$3,0))) | N12: =SizePremium*J12 | O12: =SumAssured*K12 | P12: =Policy_Sched!$I12*(L12+I12) | Q12: =O12+P12 | R12: =IF($A12=0,SizeExpsAcq0*H12,0) | S12: =IF($A12=0,SizeExpsCommInit0*J12,0) | T12: =Policy_Sched!$J12*J12 | U12: =M12*J12 | V12: =S12+T12+R12+U12 | W12: =IF($A12>LastT,0,N12+W13/(1+Policy_Sched!$K12)) | X12: =IF($A12>LastT,0,(-Q12+X13)/(1+Policy_Sched!$K12)) | Y12: =IF($A12>LastT,0,-V12+Y13/(1+Policy_Sched!$K12)) | Z12: =W12+Y12+X12 | AA12: =IF($A12>LastT,0,N12-V12-Q12/(1+Policy_Sched!$K12)+Z13/(1+Policy_Sched!$K12))
A13: =A12+1 | B13: =IF($A13>LastT,0,IF($B$3="exps",B12*(1+InflRate+IF($A13>=T0,$G$3,0)),B12/(1+InflRate))) | C13: =IF($A13>LastT,0,IF(AND($D$3<>0,$A13>=T0,Policy_Sched!$B13<LastAge),1+$D$3*$E$3,1)) | D13: =IF($A13>LastT,0,IF($C$3="up",MIN(Policy_Sched!$E13*(1+IF($A13>=T0,$E$3,0)),$F$3),IF($C$3="down",MAX(Policy_Sched!$E13*(1-IF($A13>=T0,$E$3,0)),Policy_Sched!$E13-$F$3),Policy_Sched!$E13))) | E13: =IF($A13>LastT,0,J12-K12-L12) | F13: =IF($A13>LastT,0,IF($A13=PolicyTerm,E13,0)) | G13: =IF($A13>LastT,0,E13-F13) | H13: =IF($A13=0,PolicyCount,0) | I13: =IF($A13>LastT,0,IF(AND($C$3="mass",$A13=T0),(G13+H13)*$E$3,0)) | J13: =IF($A13>LastT,0,G13+H13-I13) | K13: =IF($A13>LastT,0,J13*Policy_Sched!$C13*Policy_Sched!$D13*C13) | L13: =J13*D13 | M13: =IF($A13>LastT,0,(SizeAnnPrem*ExpsMaintAnnPrem+(SumAssured*ExpsMaintSA+ExpsMaintPol)*B13)*(1+IF($B$3="exps",$E$3,0))) | N13: =SizePremium*J13 | O13: =SumAssured*K13 | P13: =Policy_Sched!$I13*(L13+I13) | Q13: =O13+P13 | R13: =IF($A13=0,SizeExpsAcq0*H13,0) | S13: =IF($A13=0,SizeExpsCommInit0*J13,0) | T13: =Policy_Sched!$J13*J13 | U13: =M13*J13 | V13: =S13+T13+R13+U13 | W13: =IF($A13>LastT,0,N13+W14/(1+Policy_Sched!$K13)) | X13: =IF($A13>LastT,0,(-Q13+X14)/(1+Policy_Sched!$K13)) | Y13: =IF($A13>LastT,0,-V13+Y14/(1+Policy_Sched!$K13)) | Z13: =W13+Y13+X13 | AA13: =IF($A13>LastT,0,N13-V13-Q13/(1+Policy_Sched!$K13)+Z14/(1+Policy_Sched!$K13))
A14: =A13+1 | B14: =IF($A14>LastT,0,IF($B$3="exps",B13*(1+InflRate+IF($A14>=T0,$G$3,0)),B13/(1+InflRate))) | C14: =IF($A14>LastT,0,IF(AND($D$3<>0,$A14>=T0,Policy_Sched!$B14<LastAge),1+$D$3*$E$3,1)) | D14: =IF($A14>LastT,0,IF($C$3="up",MIN(Policy_Sched!$E14*(1+IF($A14>=T0,$E$3,0)),$F$3),IF($C$3="down",MAX(Policy_Sched!$E14*(1-IF($A14>=T0,$E$3,0)),Policy_Sched!$E14-$F$3),Policy_Sched!$E14))) | E14: =IF($A14>LastT,0,J13-K13-L13) | F14: =IF($A14>LastT,0,IF($A14=PolicyTerm,E14,0)) | G14: =IF($A14>LastT,0,E14-F14) | H14: =IF($A14=0,PolicyCount,0) | I14: =IF($A14>LastT,0,IF(AND($C$3="mass",$A14=T0),(G14+H14)*$E$3,0)) | J14: =IF($A14>LastT,0,G14+H14-I14) | K14: =IF($A14>LastT,0,J14*Policy_Sched!$C14*Policy_Sched!$D14*C14) | L14: =J14*D14 | M14: =IF($A14>LastT,0,(SizeAnnPrem*ExpsMaintAnnPrem+(SumAssured*ExpsMaintSA+ExpsMaintPol)*B14)*(1+IF($B$3="exps",$E$3,0))) | N14: =SizePremium*J14 | O14: =SumAssured*K14 | P14: =Policy_Sched!$I14*(L14+I14) | Q14: =O14+P14 | R14: =IF($A14=0,SizeExpsAcq0*H14,0) | S14: =IF($A14=0,SizeExpsCommInit0*J14,0) | T14: =Policy_Sched!$J14*J14 | U14: =M14*J14 | V14: =S14+T14+R14+U14 | W14: =IF($A14>LastT,0,N14+W15/(1+Policy_Sched!$K14)) | X14: =IF($A14>LastT,0,(-Q14+X15)/(1+Policy_Sched!$K14)) | Y14: =IF($A14>LastT,0,-V14+Y15/(1+Policy_Sched!$K14)) | Z14: =W14+Y14+X14 | AA14: =IF($A14>LastT,0,N14-V14-Q14/(1+Policy_Sched!$K14)+Z15/(1+Policy_Sched!$K14))
A15: =A14+1 | B15: =IF($A15>LastT,0,IF($B$3="exps",B14*(1+InflRate+IF($A15>=T0,$G$3,0)),B14/(1+InflRate))) | C15: =IF($A15>LastT,0,IF(AND($D$3<>0,$A15>=T0,Policy_Sched!$B15<LastAge),1+$D$3*$E$3,1)) | D15: =IF($A15>LastT,0,IF($C$3="up",MIN(Policy_Sched!$E15*(1+IF($A15>=T0,$E$3,0)),$F$3),IF($C$3="down",MAX(Policy_Sched!$E15*(1-IF($A15>=T0,$E$3,0)),Policy_Sched!$E15-$F$3),Policy_Sched!$E15))) | E15: =IF($A15>LastT,0,J14-K14-L14) | F15: =IF($A15>LastT,0,IF($A15=PolicyTerm,E15,0)) | G15: =IF($A15>LastT,0,E15-F15) | H15: =IF($A15=0,PolicyCount,0) | I15: =IF($A15>LastT,0,IF(AND($C$3="mass",$A15=T0),(G15+H15)*$E$3,0)) | J15: =IF($A15>LastT,0,G15+H15-I15) | K15: =IF($A15>LastT,0,J15*Policy_Sched!$C15*Policy_Sched!$D15*C15) | L15: =J15*D15 | M15: =IF($A15>LastT,0,(SizeAnnPrem*ExpsMaintAnnPrem+(SumAssured*ExpsMaintSA+ExpsMaintPol)*B15)*(1+IF($B$3="exps",$E$3,0))) | N15: =SizePremium*J15 | O15: =SumAssured*K15 | P15: =Policy_Sched!$I15*(L15+I15) | Q15: =O15+P15 | R15: =IF($A15=0,SizeExpsAcq0*H15,0) | S15: =IF($A15=0,SizeExpsCommInit0*J15,0) | T15: =Policy_Sched!$J15*J15 | U15: =M15*J15 | V15: =S15+T15+R15+U15 | W15: =IF($A15>LastT,0,N15+W16/(1+Policy_Sched!$K15)) | X15: =IF($A15>LastT,0,(-Q15+X16)/(1+Policy_Sched!$K15)) | Y15: =IF($A15>LastT,0,-V15+Y16/(1+Policy_Sched!$K15)) | Z15: =W15+Y15+X15 | AA15: =IF($A15>LastT,0,N15-V15-Q15/(1+Policy_Sched!$K15)+Z16/(1+Policy_Sched!$K15))
A16: =A15+1 | B16: =IF($A16>LastT,0,IF($B$3="exps",B15*(1+InflRate+IF($A16>=T0,$G$3,0)),B15/(1+InflRate))) | C16: =IF($A16>LastT,0,IF(AND($D$3<>0,$A16>=T0,Policy_Sched!$B16<LastAge),1+$D$3*$E$3,1)) | D16: =IF($A16>LastT,0,IF($C$3="up",MIN(Policy_Sched!$E16*(1+IF($A16>=T0,$E$3,0)),$F$3),IF($C$3="down",MAX(Policy_Sched!$E16*(1-IF($A16>=T0,$E$3,0)),Policy_Sched!$E16-$F$3),Policy_Sched!$E16))) | E16: =IF($A16>LastT,0,J15-K15-L15) | F16: =IF($A16>LastT,0,IF($A16=PolicyTerm,E16,0)) | G16: =IF($A16>LastT,0,E16-F16) | H16: =IF($A16=0,PolicyCount,0) | I16: =IF($A16>LastT,0,IF(AND($C$3="mass",$A16=T0),(G16+H16)*$E$3,0)) | J16: =IF($A16>LastT,0,G16+H16-I16) | K16: =IF($A16>LastT,0,J16*Policy_Sched!$C16*Policy_Sched!$D16*C16) | L16: =J16*D16 | M16: =IF($A16>LastT,0,(SizeAnnPrem*ExpsMaintAnnPrem+(SumAssured*ExpsMaintSA+ExpsMaintPol)*B16)*(1+IF($B$3="exps",$E$3,0))) | N16: =SizePremium*J16 | O16: =SumAssured*K16 | P16: =Policy_Sched!$I16*(L16+I16) | Q16: =O16+P16 | R16: =IF($A16=0,SizeExpsAcq0*H16,0) | S16: =IF($A16=0,SizeExpsCommInit0*J16,0) | T16: =Policy_Sched!$J16*J16 | U16: =M16*J16 | V16: =S16+T16+R16+U16 | W16: =IF($A16>LastT,0,N16+W17/(1+Policy_Sched!$K16)) | X16: =IF($A16>LastT,0,(-Q16+X17)/(1+Policy_Sched!$K16)) | Y16: =IF($A16>LastT,0,-V16+Y17/(1+Policy_Sched!$K16)) | Z16: =W16+Y16+X16 | AA16: =IF($A16>LastT,0,N16-V16-Q16/(1+Policy_Sched!$K16)+Z17/(1+Policy_Sched!$K16))
A17: =A16+1 | B17: =IF($A17>LastT,0,IF($B$3="exps",B16*(1+InflRate+IF($A17>=T0,$G$3,0)),B16/(1+InflRate))) | C17: =IF($A17>LastT,0,IF(AND($D$3<>0,$A17>=T0,Policy_Sched!$B17<LastAge),1+$D$3*$E$3,1)) | D17: =IF($A17>LastT,0,IF($C$3="up",MIN(Policy_Sched!$E17*(1+IF($A17>=T0,$E$3,0)),$F$3),IF($C$3="down",MAX(Policy_Sched!$E17*(1-IF($A17>=T0,$E$3,0)),Policy_Sched!$E17-$F$3),Policy_Sched!$E17))) | E17: =IF($A17>LastT,0,J16-K16-L16) | F17: =IF($A17>LastT,0,IF($A17=PolicyTerm,E17,0)) | G17: =IF($A17>LastT,0,E17-F17) | H17: =IF($A17=0,PolicyCount,0) | I17: =IF($A17>LastT,0,IF(AND($C$3="mass",$A17=T0),(G17+H17)*$E$3,0)) | J17: =IF($A17>LastT,0,G17+H17-I17) | K17: =IF($A17>LastT,0,J17*Policy_Sched!$C17*Policy_Sched!$D17*C17) | L17: =J17*D17 | M17: =IF($A17>LastT,0,(SizeAnnPrem*ExpsMaintAnnPrem+(SumAssured*ExpsMaintSA+ExpsMaintPol)*B17)*(1+IF($B$3="exps",$E$3,0))) | N17: =SizePremium*J17 | O17: =SumAssured*K17 | P17: =Policy_Sched!$I17*(L17+I17) | Q17: =O17+P17 | R17: =IF($A17=0,SizeExpsAcq0*H17,0) | S17: =IF($A17=0,SizeExpsCommInit0*J17,0) | T17: =Policy_Sched!$J17*J17 | U17: =M17*J17 | V17: =S17+T17+R17+U17 | W17: =IF($A17>LastT,0,N17+W18/(1+Policy_Sched!$K17)) | X17: =IF($A17>LastT,0,(-Q17+X18)/(1+Policy_Sched!$K17)) | Y17: =IF($A17>LastT,0,-V17+Y18/(1+Policy_Sched!$K17)) | Z17: =W17+Y17+X17 | AA17: =IF($A17>LastT,0,N17-V17-Q17/(1+Policy_Sched!$K17)+Z18/(1+Policy_Sched!$K17))
A18: =A17+1 | B18: =IF($A18>LastT,0,IF($B$3="exps",B17*(1+InflRate+IF($A18>=T0,$G$3,0)),B17/(1+InflRate))) | C18: =IF($A18>LastT,0,IF(AND($D$3<>0,$A18>=T0,Policy_Sched!$B18<LastAge),1+$D$3*$E$3,1)) | D18: =IF($A18>LastT,0,IF($C$3="up",MIN(Policy_Sched!$E18*(1+IF($A18>=T0,$E$3,0)),$F$3),IF($C$3="down",MAX(Policy_Sched!$E18*(1-IF($A18>=T0,$E$3,0)),Policy_Sched!$E18-$F$3),Policy_Sched!$E18))) | E18: =IF($A18>LastT,0,J17-K17-L17) | F18: =IF($A18>LastT,0,IF($A18=PolicyTerm,E18,0)) | G18: =IF($A18>LastT,0,E18-F18) | H18: =IF($A18=0,PolicyCount,0) | I18: =IF($A18>LastT,0,IF(AND($C$3="mass",$A18=T0),(G18+H18)*$E$3,0)) | J18: =IF($A18>LastT,0,G18+H18-I18) | K18: =IF($A18>LastT,0,J18*Policy_Sched!$C18*Policy_Sched!$D18*C18) | L18: =J18*D18 | M18: =IF($A18>LastT,0,(SizeAnnPrem*ExpsMaintAnnPrem+(SumAssured*ExpsMaintSA+ExpsMaintPol)*B18)*(1+IF($B$3="exps",$E$3,0))) | N18: =SizePremium*J18 | O18: =SumAssured*K18 | P18: =Policy_Sched!$I18*(L18+I18) | Q18: =O18+P18 | R18: =IF($A18=0,SizeExpsAcq0*H18,0) | S18: =IF($A18=0,SizeExpsCommInit0*J18,0) | T18: =Policy_Sched!$J18*J18 | U18: =M18*J18 | V18: =S18+T18+R18+U18 | W18: =IF($A18>LastT,0,N18+W19/(1+Policy_Sched!$K18)) | X18: =IF($A18>LastT,0,(-Q18+X19)/(1+Policy_Sched!$K18)) | Y18: =IF($A18>LastT,0,-V18+Y19/(1+Policy_Sched!$K18)) | Z18: =W18+Y18+X18 | AA18: =IF($A18>LastT,0,N18-V18-Q18/(1+Policy_Sched!$K18)+Z19/(1+Policy_Sched!$K18))
A19: =A18+1 | B19: =IF($A19>LastT,0,IF($B$3="exps",B18*(1+InflRate+IF($A19>=T0,$G$3,0)),B18/(1+InflRate))) | C19: =IF($A19>LastT,0,IF(AND($D$3<>0,$A19>=T0,Policy_Sched!$B19<LastAge),1+$D$3*$E$3,1)) | D19: =IF($A19>LastT,0,IF($C$3="up",MIN(Policy_Sched!$E19*(1+IF($A19>=T0,$E$3,0)),$F$3),IF($C$3="down",MAX(Policy_Sched!$E19*(1-IF($A19>=T0,$E$3,0)),Policy_Sched!$E19-$F$3),Policy_Sched!$E19))) | E19: =IF($A19>LastT,0,J18-K18-L18) | F19: =IF($A19>LastT,0,IF($A19=PolicyTerm,E19,0)) | G19: =IF($A19>LastT,0,E19-F19) | H19: =IF($A19=0,PolicyCount,0) | I19: =IF($A19>LastT,0,IF(AND($C$3="mass",$A19=T0),(G19+H19)*$E$3,0)) | J19: =IF($A19>LastT,0,G19+H19-I19) | K19: =IF($A19>LastT,0,J19*Policy_Sched!$C19*Policy_Sched!$D19*C19) | L19: =J19*D19 | M19: =IF($A19>LastT,0,(SizeAnnPrem*ExpsMaintAnnPrem+(SumAssured*ExpsMaintSA+ExpsMaintPol)*B19)*(1+IF($B$3="exps",$E$3,0))) | N19: =SizePremium*J19 | O19: =SumAssured*K19 | P19: =Policy_Sched!$I19*(L19+I19) | Q19: =O19+P19 | R19: =IF($A19=0,SizeExpsAcq0*H19,0) | S19: =IF($A19=0,SizeExpsCommInit0*J19,0) | T19: =Policy_Sched!$J19*J19 | U19: =M19*J19 | V19: =S19+T19+R19+U19 | W19: =IF($A19>LastT,0,N19+W20/(1+Policy_Sched!$K19)) | X19: =IF($A19>LastT,0,(-Q19+X20)/(1+Policy_Sched!$K19)) | Y19: =IF($A19>LastT,0,-V19+Y20/(1+Policy_Sched!$K19)) | Z19: =W19+Y19+X19 | AA19: =IF($A19>LastT,0,N19-V19-Q19/(1+Policy_Sched!$K19)+Z20/(1+Policy_Sched!$K19))
... A110: =A109+1 | B110: =IF($A110>LastT,0,IF($B$3="exps",B109*(1+InflRate+IF($A110>=T0,$G$3,0)),B109/(1+InflRate))) | C110: =IF($A110>LastT,0,IF(AND($D$3<>0,$A110>=T0,Policy_Sched!$B110<LastAge),1+$D$3*$E$3,1)) | D110: =IF($A110>LastT,0,IF($C$3="up",MIN(Policy_Sched!$E110*(1+IF($A110>=T0,$E$3,0)),$F$3),IF($C$3="down",MAX(Policy_Sched!$E110*(1-IF($A110>=T0,$E$3,0)),Policy_Sched!$E110-$F$3),Policy_Sched!$E110))) | E110: =IF($A110>LastT,0,J109-K109-L109) | F110: =IF($A110>LastT,0,IF($A110=PolicyTerm,E110,0)) | G110: =IF($A110>LastT,0,E110-F110) | H110: =IF($A110=0,PolicyCount,0) | I110: =IF($A110>LastT,0,IF(AND($C$3="mass",$A110=T0),(G110+H110)*$E$3,0)) | J110: =IF($A110>LastT,0,G110+H110-I110) | K110: =IF($A110>LastT,0,J110*Policy_Sched!$C110*Policy_Sched!$D110*C110) | L110: =J110*D110 | M110: =IF($A110>LastT,0,(SizeAnnPrem*ExpsMaintAnnPrem+(SumAssured*ExpsMaintSA+ExpsMaintPol)*B110)*(1+IF($B$3="exps",$E$3,0))) | N110: =SizePremium*J110 | O110: =SumAssured*K110 | P110: =Policy_Sched!$I110*(L110+I110) | Q110: =O110+P110 | R110: =IF($A110=0,SizeExpsAcq0*H110,0) | S110: =IF($A110=0,SizeExpsCommInit0*J110,0) | T110: =Policy_Sched!$J110*J110 | U110: =M110*J110 | V110: =S110+T110+R110+U110 | W110: =IF($A110>LastT,0,N110+W111/(1+Policy_Sched!$K110)) | X110: =IF($A110>LastT,0,(-Q110+X111)/(1+Policy_Sched!$K110)) | Y110: =IF($A110>LastT,0,-V110+Y111/(1+Policy_Sched!$K110)) | Z110: =W110+Y110+X110 | AA110: =IF($A110>LastT,0,N110-V110-Q110/(1+Policy_Sched!$K110)+Z111/(1+Policy_Sched!$K110))

Sheet Proj_LapseMass
A1: Liability projection — mass lapse stress (one-off at t0). lifelib SCR_life.Projection['lapse', 'mass', None]
B2: Risk | C2: Shock | D2: Risk sign | E2: Shock factor | F2: Shock limit | G2: Inflation shock
B3: lapse | C3: mass | D3: 0 | E3: =IFERROR(INDEX(FactorVals,MATCH($B$3&"|"&$C$3&"||",FactorKeys,0)),0) | F3: =IFERROR(INDEX(FactorVals,MATCH($B$3&"|"&$C$3&"||limit",FactorKeys,0)),0) | G3: =IFERROR(INDEX(FactorVals,MATCH($B$3&"|||inflation",FactorKeys,0)),0)
B4: Risk | C4: Shock | E4: Factor
A5: t | B5: Inflation factor | C5: Mortality shock factor | D5: Surrender rate | E5: In force: end | F5: Maturities | G5: In force: after maturity | H5: New business | I5: Mass lapse | J5: In force: beginning | K5: Deaths | L5: Surrenders | M5: Maint expense pp | N5: Premium income | O5: Death benefits | P5: Surrender benefits | Q5: Total benefits | R5: Acquisition expenses | S5: Initial commission | T5: Renewal commission | U5: Maintenance expenses | V5: Total expenses | W5: PV premiums | X5: PV benefits | Y5: PV expenses | Z5: PV net cashflow | AA5: PV net cf (fwd check)
A6: t | B6: InflFactor | C6: MortRateFactor | D6: SurrRate | E6: PolsIF_End | F6: PolsMaturity | G6: PolsIF_Beg | H6: PolsNewBiz | I6: PolsSurrMass | J6: PolsIF_Beg1 | K6: PolsDeath | L6: PolsSurr | M6: SizeExpsMaint | N6: PremIncome | O6: BenefitDeath | P6: BenefitSurr | Q6: BenefitTotal | R6: ExpsAcq | S6: ExpsCommInit | T6: ExpsCommRen | U6: ExpsMaint | V6: ExpsTotal | W6: PV_PremIncome | X6: PV_BenefitTotal | Y6: PV_ExpsTotal | Z6: PV_NetCashflow | AA6: PV_NetCashflowForCheck
A7: 0 | B7: =1 | C7: =IF($A7>LastT,0,IF(AND($D$3<>0,$A7>=T0,Policy_Sched!$B7<LastAge),1+$D$3*$E$3,1)) | D7: =IF($A7>LastT,0,IF($C$3="up",MIN(Policy_Sched!$E7*(1+IF($A7>=T0,$E$3,0)),$F$3),IF($C$3="down",MAX(Policy_Sched!$E7*(1-IF($A7>=T0,$E$3,0)),Policy_Sched!$E7-$F$3),Policy_Sched!$E7))) | E7: =0 | F7: =IF($A7>LastT,0,IF($A7=PolicyTerm,E7,0)) | G7: =IF($A7>LastT,0,E7-F7) | H7: =IF($A7=0,PolicyCount,0) | I7: =IF($A7>LastT,0,IF(AND($C$3="mass",$A7=T0),(G7+H7)*$E$3,0)) | J7: =IF($A7>LastT,0,G7+H7-I7) | K7: =IF($A7>LastT,0,J7*Policy_Sched!$C7*Policy_Sched!$D7*C7) | L7: =J7*D7 | M7: =IF($A7>LastT,0,(SizeAnnPrem*ExpsMaintAnnPrem+(SumAssured*ExpsMaintSA+ExpsMaintPol)*B7)*(1+IF($B$3="exps",$E$3,0))) | N7: =SizePremium*J7 | O7: =SumAssured*K7 | P7: =Policy_Sched!$I7*(L7+I7) | Q7: =O7+P7 | R7: =IF($A7=0,SizeExpsAcq0*H7,0) | S7: =IF($A7=0,SizeExpsCommInit0*J7,0) | T7: =Policy_Sched!$J7*J7 | U7: =M7*J7 | V7: =S7+T7+R7+U7 | W7: =IF($A7>LastT,0,N7+W8/(1+Policy_Sched!$K7)) | X7: =IF($A7>LastT,0,(-Q7+X8)/(1+Policy_Sched!$K7)) | Y7: =IF($A7>LastT,0,-V7+Y8/(1+Policy_Sched!$K7)) | Z7: =W7+Y7+X7 | AA7: =IF($A7>LastT,0,N7-V7-Q7/(1+Policy_Sched!$K7)+Z8/(1+Policy_Sched!$K7))
A8: =A7+1 | B8: =IF($A8>LastT,0,IF($B$3="exps",B7*(1+InflRate+IF($A8>=T0,$G$3,0)),B7/(1+InflRate))) | C8: =IF($A8>LastT,0,IF(AND($D$3<>0,$A8>=T0,Policy_Sched!$B8<LastAge),1+$D$3*$E$3,1)) | D8: =IF($A8>LastT,0,IF($C$3="up",MIN(Policy_Sched!$E8*(1+IF($A8>=T0,$E$3,0)),$F$3),IF($C$3="down",MAX(Policy_Sched!$E8*(1-IF($A8>=T0,$E$3,0)),Policy_Sched!$E8-$F$3),Policy_Sched!$E8))) | E8: =IF($A8>LastT,0,J7-K7-L7) | F8: =IF($A8>LastT,0,IF($A8=PolicyTerm,E8,0)) | G8: =IF($A8>LastT,0,E8-F8) | H8: =IF($A8=0,PolicyCount,0) | I8: =IF($A8>LastT,0,IF(AND($C$3="mass",$A8=T0),(G8+H8)*$E$3,0)) | J8: =IF($A8>LastT,0,G8+H8-I8) | K8: =IF($A8>LastT,0,J8*Policy_Sched!$C8*Policy_Sched!$D8*C8) | L8: =J8*D8 | M8: =IF($A8>LastT,0,(SizeAnnPrem*ExpsMaintAnnPrem+(SumAssured*ExpsMaintSA+ExpsMaintPol)*B8)*(1+IF($B$3="exps",$E$3,0))) | N8: =SizePremium*J8 | O8: =SumAssured*K8 | P8: =Policy_Sched!$I8*(L8+I8) | Q8: =O8+P8 | R8: =IF($A8=0,SizeExpsAcq0*H8,0) | S8: =IF($A8=0,SizeExpsCommInit0*J8,0) | T8: =Policy_Sched!$J8*J8 | U8: =M8*J8 | V8: =S8+T8+R8+U8 | W8: =IF($A8>LastT,0,N8+W9/(1+Policy_Sched!$K8)) | X8: =IF($A8>LastT,0,(-Q8+X9)/(1+Policy_Sched!$K8)) | Y8: =IF($A8>LastT,0,-V8+Y9/(1+Policy_Sched!$K8)) | Z8: =W8+Y8+X8 | AA8: =IF($A8>LastT,0,N8-V8-Q8/(1+Policy_Sched!$K8)+Z9/(1+Policy_Sched!$K8))
A9: =A8+1 | B9: =IF($A9>LastT,0,IF($B$3="exps",B8*(1+InflRate+IF($A9>=T0,$G$3,0)),B8/(1+InflRate))) | C9: =IF($A9>LastT,0,IF(AND($D$3<>0,$A9>=T0,Policy_Sched!$B9<LastAge),1+$D$3*$E$3,1)) | D9: =IF($A9>LastT,0,IF($C$3="up",MIN(Policy_Sched!$E9*(1+IF($A9>=T0,$E$3,0)),$F$3),IF($C$3="down",MAX(Policy_Sched!$E9*(1-IF($A9>=T0,$E$3,0)),Policy_Sched!$E9-$F$3),Policy_Sched!$E9))) | E9: =IF($A9>LastT,0,J8-K8-L8) | F9: =IF($A9>LastT,0,IF($A9=PolicyTerm,E9,0)) | G9: =IF($A9>LastT,0,E9-F9) | H9: =IF($A9=0,PolicyCount,0) | I9: =IF($A9>LastT,0,IF(AND($C$3="mass",$A9=T0),(G9+H9)*$E$3,0)) | J9: =IF($A9>LastT,0,G9+H9-I9) | K9: =IF($A9>LastT,0,J9*Policy_Sched!$C9*Policy_Sched!$D9*C9) | L9: =J9*D9 | M9: =IF($A9>LastT,0,(SizeAnnPrem*ExpsMaintAnnPrem+(SumAssured*ExpsMaintSA+ExpsMaintPol)*B9)*(1+IF($B$3="exps",$E$3,0))) | N9: =SizePremium*J9 | O9: =SumAssured*K9 | P9: =Policy_Sched!$I9*(L9+I9) | Q9: =O9+P9 | R9: =IF($A9=0,SizeExpsAcq0*H9,0) | S9: =IF($A9=0,SizeExpsCommInit0*J9,0) | T9: =Policy_Sched!$J9*J9 | U9: =M9*J9 | V9: =S9+T9+R9+U9 | W9: =IF($A9>LastT,0,N9+W10/(1+Policy_Sched!$K9)) | X9: =IF($A9>LastT,0,(-Q9+X10)/(1+Policy_Sched!$K9)) | Y9: =IF($A9>LastT,0,-V9+Y10/(1+Policy_Sched!$K9)) | Z9: =W9+Y9+X9 | AA9: =IF($A9>LastT,0,N9-V9-Q9/(1+Policy_Sched!$K9)+Z10/(1+Policy_Sched!$K9))
A10: =A9+1 | B10: =IF($A10>LastT,0,IF($B$3="exps",B9*(1+InflRate+IF($A10>=T0,$G$3,0)),B9/(1+InflRate))) | C10: =IF($A10>LastT,0,IF(AND($D$3<>0,$A10>=T0,Policy_Sched!$B10<LastAge),1+$D$3*$E$3,1)) | D10: =IF($A10>LastT,0,IF($C$3="up",MIN(Policy_Sched!$E10*(1+IF($A10>=T0,$E$3,0)),$F$3),IF($C$3="down",MAX(Policy_Sched!$E10*(1-IF($A10>=T0,$E$3,0)),Policy_Sched!$E10-$F$3),Policy_Sched!$E10))) | E10: =IF($A10>LastT,0,J9-K9-L9) | F10: =IF($A10>LastT,0,IF($A10=PolicyTerm,E10,0)) | G10: =IF($A10>LastT,0,E10-F10) | H10: =IF($A10=0,PolicyCount,0) | I10: =IF($A10>LastT,0,IF(AND($C$3="mass",$A10=T0),(G10+H10)*$E$3,0)) | J10: =IF($A10>LastT,0,G10+H10-I10) | K10: =IF($A10>LastT,0,J10*Policy_Sched!$C10*Policy_Sched!$D10*C10) | L10: =J10*D10 | M10: =IF($A10>LastT,0,(SizeAnnPrem*ExpsMaintAnnPrem+(SumAssured*ExpsMaintSA+ExpsMaintPol)*B10)*(1+IF($B$3="exps",$E$3,0))) | N10: =SizePremium*J10 | O10: =SumAssured*K10 | P10: =Policy_Sched!$I10*(L10+I10) | Q10: =O10+P10 | R10: =IF($A10=0,SizeExpsAcq0*H10,0) | S10: =IF($A10=0,SizeExpsCommInit0*J10,0) | T10: =Policy_Sched!$J10*J10 | U10: =M10*J10 | V10: =S10+T10+R10+U10 | W10: =IF($A10>LastT,0,N10+W11/(1+Policy_Sched!$K10)) | X10: =IF($A10>LastT,0,(-Q10+X11)/(1+Policy_Sched!$K10)) | Y10: =IF($A10>LastT,0,-V10+Y11/(1+Policy_Sched!$K10)) | Z10: =W10+Y10+X10 | AA10: =IF($A10>LastT,0,N10-V10-Q10/(1+Policy_Sched!$K10)+Z11/(1+Policy_Sched!$K10))
A11: =A10+1 | B11: =IF($A11>LastT,0,IF($B$3="exps",B10*(1+InflRate+IF($A11>=T0,$G$3,0)),B10/(1+InflRate))) | C11: =IF($A11>LastT,0,IF(AND($D$3<>0,$A11>=T0,Policy_Sched!$B11<LastAge),1+$D$3*$E$3,1)) | D11: =IF($A11>LastT,0,IF($C$3="up",MIN(Policy_Sched!$E11*(1+IF($A11>=T0,$E$3,0)),$F$3),IF($C$3="down",MAX(Policy_Sched!$E11*(1-IF($A11>=T0,$E$3,0)),Policy_Sched!$E11-$F$3),Policy_Sched!$E11))) | E11: =IF($A11>LastT,0,J10-K10-L10) | F11: =IF($A11>LastT,0,IF($A11=PolicyTerm,E11,0)) | G11: =IF($A11>LastT,0,E11-F11) | H11: =IF($A11=0,PolicyCount,0) | I11: =IF($A11>LastT,0,IF(AND($C$3="mass",$A11=T0),(G11+H11)*$E$3,0)) | J11: =IF($A11>LastT,0,G11+H11-I11) | K11: =IF($A11>LastT,0,J11*Policy_Sched!$C11*Policy_Sched!$D11*C11) | L11: =J11*D11 | M11: =IF($A11>LastT,0,(SizeAnnPrem*ExpsMaintAnnPrem+(SumAssured*ExpsMaintSA+ExpsMaintPol)*B11)*(1+IF($B$3="exps",$E$3,0))) | N11: =SizePremium*J11 | O11: =SumAssured*K11 | P11: =Policy_Sched!$I11*(L11+I11) | Q11: =O11+P11 | R11: =IF($A11=0,SizeExpsAcq0*H11,0) | S11: =IF($A11=0,SizeExpsCommInit0*J11,0) | T11: =Policy_Sched!$J11*J11 | U11: =M11*J11 | V11: =S11+T11+R11+U11 | W11: =IF($A11>LastT,0,N11+W12/(1+Policy_Sched!$K11)) | X11: =IF($A11>LastT,0,(-Q11+X12)/(1+Policy_Sched!$K11)) | Y11: =IF($A11>LastT,0,-V11+Y12/(1+Policy_Sched!$K11)) | Z11: =W11+Y11+X11 | AA11: =IF($A11>LastT,0,N11-V11-Q11/(1+Policy_Sched!$K11)+Z12/(1+Policy_Sched!$K11))
A12: =A11+1 | B12: =IF($A12>LastT,0,IF($B$3="exps",B11*(1+InflRate+IF($A12>=T0,$G$3,0)),B11/(1+InflRate))) | C12: =IF($A12>LastT,0,IF(AND($D$3<>0,$A12>=T0,Policy_Sched!$B12<LastAge),1+$D$3*$E$3,1)) | D12: =IF($A12>LastT,0,IF($C$3="up",MIN(Policy_Sched!$E12*(1+IF($A12>=T0,$E$3,0)),$F$3),IF($C$3="down",MAX(Policy_Sched!$E12*(1-IF($A12>=T0,$E$3,0)),Policy_Sched!$E12-$F$3),Policy_Sched!$E12))) | E12: =IF($A12>LastT,0,J11-K11-L11) | F12: =IF($A12>LastT,0,IF($A12=PolicyTerm,E12,0)) | G12: =IF($A12>LastT,0,E12-F12) | H12: =IF($A12=0,PolicyCount,0) | I12: =IF($A12>LastT,0,IF(AND($C$3="mass",$A12=T0),(G12+H12)*$E$3,0)) | J12: =IF($A12>LastT,0,G12+H12-I12) | K12: =IF($A12>LastT,0,J12*Policy_Sched!$C12*Policy_Sched!$D12*C12) | L12: =J12*D12 | M12: =IF($A12>LastT,0,(SizeAnnPrem*ExpsMaintAnnPrem+(SumAssured*ExpsMaintSA+ExpsMaintPol)*B12)*(1+IF($B$3="exps",$E$3,0))) | N12: =SizePremium*J12 | O12: =SumAssured*K12 | P12: =Policy_Sched!$I12*(L12+I12) | Q12: =O12+P12 | R12: =IF($A12=0,SizeExpsAcq0*H12,0) | S12: =IF($A12=0,SizeExpsCommInit0*J12,0) | T12: =Policy_Sched!$J12*J12 | U12: =M12*J12 | V12: =S12+T12+R12+U12 | W12: =IF($A12>LastT,0,N12+W13/(1+Policy_Sched!$K12)) | X12: =IF($A12>LastT,0,(-Q12+X13)/(1+Policy_Sched!$K12)) | Y12: =IF($A12>LastT,0,-V12+Y13/(1+Policy_Sched!$K12)) | Z12: =W12+Y12+X12 | AA12: =IF($A12>LastT,0,N12-V12-Q12/(1+Policy_Sched!$K12)+Z13/(1+Policy_Sched!$K12))
A13: =A12+1 | B13: =IF($A13>LastT,0,IF($B$3="exps",B12*(1+InflRate+IF($A13>=T0,$G$3,0)),B12/(1+InflRate))) | C13: =IF($A13>LastT,0,IF(AND($D$3<>0,$A13>=T0,Policy_Sched!$B13<LastAge),1+$D$3*$E$3,1)) | D13: =IF($A13>LastT,0,IF($C$3="up",MIN(Policy_Sched!$E13*(1+IF($A13>=T0,$E$3,0)),$F$3),IF($C$3="down",MAX(Policy_Sched!$E13*(1-IF($A13>=T0,$E$3,0)),Policy_Sched!$E13-$F$3),Policy_Sched!$E13))) | E13: =IF($A13>LastT,0,J12-K12-L12) | F13: =IF($A13>LastT,0,IF($A13=PolicyTerm,E13,0)) | G13: =IF($A13>LastT,0,E13-F13) | H13: =IF($A13=0,PolicyCount,0) | I13: =IF($A13>LastT,0,IF(AND($C$3="mass",$A13=T0),(G13+H13)*$E$3,0)) | J13: =IF($A13>LastT,0,G13+H13-I13) | K13: =IF($A13>LastT,0,J13*Policy_Sched!$C13*Policy_Sched!$D13*C13) | L13: =J13*D13 | M13: =IF($A13>LastT,0,(SizeAnnPrem*ExpsMaintAnnPrem+(SumAssured*ExpsMaintSA+ExpsMaintPol)*B13)*(1+IF($B$3="exps",$E$3,0))) | N13: =SizePremium*J13 | O13: =SumAssured*K13 | P13: =Policy_Sched!$I13*(L13+I13) | Q13: =O13+P13 | R13: =IF($A13=0,SizeExpsAcq0*H13,0) | S13: =IF($A13=0,SizeExpsCommInit0*J13,0) | T13: =Policy_Sched!$J13*J13 | U13: =M13*J13 | V13: =S13+T13+R13+U13 | W13: =IF($A13>LastT,0,N13+W14/(1+Policy_Sched!$K13)) | X13: =IF($A13>LastT,0,(-Q13+X14)/(1+Policy_Sched!$K13)) | Y13: =IF($A13>LastT,0,-V13+Y14/(1+Policy_Sched!$K13)) | Z13: =W13+Y13+X13 | AA13: =IF($A13>LastT,0,N13-V13-Q13/(1+Policy_Sched!$K13)+Z14/(1+Policy_Sched!$K13))
A14: =A13+1 | B14: =IF($A14>LastT,0,IF($B$3="exps",B13*(1+InflRate+IF($A14>=T0,$G$3,0)),B13/(1+InflRate))) | C14: =IF($A14>LastT,0,IF(AND($D$3<>0,$A14>=T0,Policy_Sched!$B14<LastAge),1+$D$3*$E$3,1)) | D14: =IF($A14>LastT,0,IF($C$3="up",MIN(Policy_Sched!$E14*(1+IF($A14>=T0,$E$3,0)),$F$3),IF($C$3="down",MAX(Policy_Sched!$E14*(1-IF($A14>=T0,$E$3,0)),Policy_Sched!$E14-$F$3),Policy_Sched!$E14))) | E14: =IF($A14>LastT,0,J13-K13-L13) | F14: =IF($A14>LastT,0,IF($A14=PolicyTerm,E14,0)) | G14: =IF($A14>LastT,0,E14-F14) | H14: =IF($A14=0,PolicyCount,0) | I14: =IF($A14>LastT,0,IF(AND($C$3="mass",$A14=T0),(G14+H14)*$E$3,0)) | J14: =IF($A14>LastT,0,G14+H14-I14) | K14: =IF($A14>LastT,0,J14*Policy_Sched!$C14*Policy_Sched!$D14*C14) | L14: =J14*D14 | M14: =IF($A14>LastT,0,(SizeAnnPrem*ExpsMaintAnnPrem+(SumAssured*ExpsMaintSA+ExpsMaintPol)*B14)*(1+IF($B$3="exps",$E$3,0))) | N14: =SizePremium*J14 | O14: =SumAssured*K14 | P14: =Policy_Sched!$I14*(L14+I14) | Q14: =O14+P14 | R14: =IF($A14=0,SizeExpsAcq0*H14,0) | S14: =IF($A14=0,SizeExpsCommInit0*J14,0) | T14: =Policy_Sched!$J14*J14 | U14: =M14*J14 | V14: =S14+T14+R14+U14 | W14: =IF($A14>LastT,0,N14+W15/(1+Policy_Sched!$K14)) | X14: =IF($A14>LastT,0,(-Q14+X15)/(1+Policy_Sched!$K14)) | Y14: =IF($A14>LastT,0,-V14+Y15/(1+Policy_Sched!$K14)) | Z14: =W14+Y14+X14 | AA14: =IF($A14>LastT,0,N14-V14-Q14/(1+Policy_Sched!$K14)+Z15/(1+Policy_Sched!$K14))
A15: =A14+1 | B15: =IF($A15>LastT,0,IF($B$3="exps",B14*(1+InflRate+IF($A15>=T0,$G$3,0)),B14/(1+InflRate))) | C15: =IF($A15>LastT,0,IF(AND($D$3<>0,$A15>=T0,Policy_Sched!$B15<LastAge),1+$D$3*$E$3,1)) | D15: =IF($A15>LastT,0,IF($C$3="up",MIN(Policy_Sched!$E15*(1+IF($A15>=T0,$E$3,0)),$F$3),IF($C$3="down",MAX(Policy_Sched!$E15*(1-IF($A15>=T0,$E$3,0)),Policy_Sched!$E15-$F$3),Policy_Sched!$E15))) | E15: =IF($A15>LastT,0,J14-K14-L14) | F15: =IF($A15>LastT,0,IF($A15=PolicyTerm,E15,0)) | G15: =IF($A15>LastT,0,E15-F15) | H15: =IF($A15=0,PolicyCount,0) | I15: =IF($A15>LastT,0,IF(AND($C$3="mass",$A15=T0),(G15+H15)*$E$3,0)) | J15: =IF($A15>LastT,0,G15+H15-I15) | K15: =IF($A15>LastT,0,J15*Policy_Sched!$C15*Policy_Sched!$D15*C15) | L15: =J15*D15 | M15: =IF($A15>LastT,0,(SizeAnnPrem*ExpsMaintAnnPrem+(SumAssured*ExpsMaintSA+ExpsMaintPol)*B15)*(1+IF($B$3="exps",$E$3,0))) | N15: =SizePremium*J15 | O15: =SumAssured*K15 | P15: =Policy_Sched!$I15*(L15+I15) | Q15: =O15+P15 | R15: =IF($A15=0,SizeExpsAcq0*H15,0) | S15: =IF($A15=0,SizeExpsCommInit0*J15,0) | T15: =Policy_Sched!$J15*J15 | U15: =M15*J15 | V15: =S15+T15+R15+U15 | W15: =IF($A15>LastT,0,N15+W16/(1+Policy_Sched!$K15)) | X15: =IF($A15>LastT,0,(-Q15+X16)/(1+Policy_Sched!$K15)) | Y15: =IF($A15>LastT,0,-V15+Y16/(1+Policy_Sched!$K15)) | Z15: =W15+Y15+X15 | AA15: =IF($A15>LastT,0,N15-V15-Q15/(1+Policy_Sched!$K15)+Z16/(1+Policy_Sched!$K15))
A16: =A15+1 | B16: =IF($A16>LastT,0,IF($B$3="exps",B15*(1+InflRate+IF($A16>=T0,$G$3,0)),B15/(1+InflRate))) | C16: =IF($A16>LastT,0,IF(AND($D$3<>0,$A16>=T0,Policy_Sched!$B16<LastAge),1+$D$3*$E$3,1)) | D16: =IF($A16>LastT,0,IF($C$3="up",MIN(Policy_Sched!$E16*(1+IF($A16>=T0,$E$3,0)),$F$3),IF($C$3="down",MAX(Policy_Sched!$E16*(1-IF($A16>=T0,$E$3,0)),Policy_Sched!$E16-$F$3),Policy_Sched!$E16))) | E16: =IF($A16>LastT,0,J15-K15-L15) | F16: =IF($A16>LastT,0,IF($A16=PolicyTerm,E16,0)) | G16: =IF($A16>LastT,0,E16-F16) | H16: =IF($A16=0,PolicyCount,0) | I16: =IF($A16>LastT,0,IF(AND($C$3="mass",$A16=T0),(G16+H16)*$E$3,0)) | J16: =IF($A16>LastT,0,G16+H16-I16) | K16: =IF($A16>LastT,0,J16*Policy_Sched!$C16*Policy_Sched!$D16*C16) | L16: =J16*D16 | M16: =IF($A16>LastT,0,(SizeAnnPrem*ExpsMaintAnnPrem+(SumAssured*ExpsMaintSA+ExpsMaintPol)*B16)*(1+IF($B$3="exps",$E$3,0))) | N16: =SizePremium*J16 | O16: =SumAssured*K16 | P16: =Policy_Sched!$I16*(L16+I16) | Q16: =O16+P16 | R16: =IF($A16=0,SizeExpsAcq0*H16,0) | S16: =IF($A16=0,SizeExpsCommInit0*J16,0) | T16: =Policy_Sched!$J16*J16 | U16: =M16*J16 | V16: =S16+T16+R16+U16 | W16: =IF($A16>LastT,0,N16+W17/(1+Policy_Sched!$K16)) | X16: =IF($A16>LastT,0,(-Q16+X17)/(1+Policy_Sched!$K16)) | Y16: =IF($A16>LastT,0,-V16+Y17/(1+Policy_Sched!$K16)) | Z16: =W16+Y16+X16 | AA16: =IF($A16>LastT,0,N16-V16-Q16/(1+Policy_Sched!$K16)+Z17/(1+Policy_Sched!$K16))
A17: =A16+1 | B17: =IF($A17>LastT,0,IF($B$3="exps",B16*(1+InflRate+IF($A17>=T0,$G$3,0)),B16/(1+InflRate))) | C17: =IF($A17>LastT,0,IF(AND($D$3<>0,$A17>=T0,Policy_Sched!$B17<LastAge),1+$D$3*$E$3,1)) | D17: =IF($A17>LastT,0,IF($C$3="up",MIN(Policy_Sched!$E17*(1+IF($A17>=T0,$E$3,0)),$F$3),IF($C$3="down",MAX(Policy_Sched!$E17*(1-IF($A17>=T0,$E$3,0)),Policy_Sched!$E17-$F$3),Policy_Sched!$E17))) | E17: =IF($A17>LastT,0,J16-K16-L16) | F17: =IF($A17>LastT,0,IF($A17=PolicyTerm,E17,0)) | G17: =IF($A17>LastT,0,E17-F17) | H17: =IF($A17=0,PolicyCount,0) | I17: =IF($A17>LastT,0,IF(AND($C$3="mass",$A17=T0),(G17+H17)*$E$3,0)) | J17: =IF($A17>LastT,0,G17+H17-I17) | K17: =IF($A17>LastT,0,J17*Policy_Sched!$C17*Policy_Sched!$D17*C17) | L17: =J17*D17 | M17: =IF($A17>LastT,0,(SizeAnnPrem*ExpsMaintAnnPrem+(SumAssured*ExpsMaintSA+ExpsMaintPol)*B17)*(1+IF($B$3="exps",$E$3,0))) | N17: =SizePremium*J17 | O17: =SumAssured*K17 | P17: =Policy_Sched!$I17*(L17+I17) | Q17: =O17+P17 | R17: =IF($A17=0,SizeExpsAcq0*H17,0) | S17: =IF($A17=0,SizeExpsCommInit0*J17,0) | T17: =Policy_Sched!$J17*J17 | U17: =M17*J17 | V17: =S17+T17+R17+U17 | W17: =IF($A17>LastT,0,N17+W18/(1+Policy_Sched!$K17)) | X17: =IF($A17>LastT,0,(-Q17+X18)/(1+Policy_Sched!$K17)) | Y17: =IF($A17>LastT,0,-V17+Y18/(1+Policy_Sched!$K17)) | Z17: =W17+Y17+X17 | AA17: =IF($A17>LastT,0,N17-V17-Q17/(1+Policy_Sched!$K17)+Z18/(1+Policy_Sched!$K17))
A18: =A17+1 | B18: =IF($A18>LastT,0,IF($B$3="exps",B17*(1+InflRate+IF($A18>=T0,$G$3,0)),B17/(1+InflRate))) | C18: =IF($A18>LastT,0,IF(AND($D$3<>0,$A18>=T0,Policy_Sched!$B18<LastAge),1+$D$3*$E$3,1)) | D18: =IF($A18>LastT,0,IF($C$3="up",MIN(Policy_Sched!$E18*(1+IF($A18>=T0,$E$3,0)),$F$3),IF($C$3="down",MAX(Policy_Sched!$E18*(1-IF($A18>=T0,$E$3,0)),Policy_Sched!$E18-$F$3),Policy_Sched!$E18))) | E18: =IF($A18>LastT,0,J17-K17-L17) | F18: =IF($A18>LastT,0,IF($A18=PolicyTerm,E18,0)) | G18: =IF($A18>LastT,0,E18-F18) | H18: =IF($A18=0,PolicyCount,0) | I18: =IF($A18>LastT,0,IF(AND($C$3="mass",$A18=T0),(G18+H18)*$E$3,0)) | J18: =IF($A18>LastT,0,G18+H18-I18) | K18: =IF($A18>LastT,0,J18*Policy_Sched!$C18*Policy_Sched!$D18*C18) | L18: =J18*D18 | M18: =IF($A18>LastT,0,(SizeAnnPrem*ExpsMaintAnnPrem+(SumAssured*ExpsMaintSA+ExpsMaintPol)*B18)*(1+IF($B$3="exps",$E$3,0))) | N18: =SizePremium*J18 | O18: =SumAssured*K18 | P18: =Policy_Sched!$I18*(L18+I18) | Q18: =O18+P18 | R18: =IF($A18=0,SizeExpsAcq0*H18,0) | S18: =IF($A18=0,SizeExpsCommInit0*J18,0) | T18: =Policy_Sched!$J18*J18 | U18: =M18*J18 | V18: =S18+T18+R18+U18 | W18: =IF($A18>LastT,0,N18+W19/(1+Policy_Sched!$K18)) | X18: =IF($A18>LastT,0,(-Q18+X19)/(1+Policy_Sched!$K18)) | Y18: =IF($A18>LastT,0,-V18+Y19/(1+Policy_Sched!$K18)) | Z18: =W18+Y18+X18 | AA18: =IF($A18>LastT,0,N18-V18-Q18/(1+Policy_Sched!$K18)+Z19/(1+Policy_Sched!$K18))
A19: =A18+1 | B19: =IF($A19>LastT,0,IF($B$3="exps",B18*(1+InflRate+IF($A19>=T0,$G$3,0)),B18/(1+InflRate))) | C19: =IF($A19>LastT,0,IF(AND($D$3<>0,$A19>=T0,Policy_Sched!$B19<LastAge),1+$D$3*$E$3,1)) | D19: =IF($A19>LastT,0,IF($C$3="up",MIN(Policy_Sched!$E19*(1+IF($A19>=T0,$E$3,0)),$F$3),IF($C$3="down",MAX(Policy_Sched!$E19*(1-IF($A19>=T0,$E$3,0)),Policy_Sched!$E19-$F$3),Policy_Sched!$E19))) | E19: =IF($A19>LastT,0,J18-K18-L18) | F19: =IF($A19>LastT,0,IF($A19=PolicyTerm,E19,0)) | G19: =IF($A19>LastT,0,E19-F19) | H19: =IF($A19=0,PolicyCount,0) | I19: =IF($A19>LastT,0,IF(AND($C$3="mass",$A19=T0),(G19+H19)*$E$3,0)) | J19: =IF($A19>LastT,0,G19+H19-I19) | K19: =IF($A19>LastT,0,J19*Policy_Sched!$C19*Policy_Sched!$D19*C19) | L19: =J19*D19 | M19: =IF($A19>LastT,0,(SizeAnnPrem*ExpsMaintAnnPrem+(SumAssured*ExpsMaintSA+ExpsMaintPol)*B19)*(1+IF($B$3="exps",$E$3,0))) | N19: =SizePremium*J19 | O19: =SumAssured*K19 | P19: =Policy_Sched!$I19*(L19+I19) | Q19: =O19+P19 | R19: =IF($A19=0,SizeExpsAcq0*H19,0) | S19: =IF($A19=0,SizeExpsCommInit0*J19,0) | T19: =Policy_Sched!$J19*J19 | U19: =M19*J19 | V19: =S19+T19+R19+U19 | W19: =IF($A19>LastT,0,N19+W20/(1+Policy_Sched!$K19)) | X19: =IF($A19>LastT,0,(-Q19+X20)/(1+Policy_Sched!$K19)) | Y19: =IF($A19>LastT,0,-V19+Y20/(1+Policy_Sched!$K19)) | Z19: =W19+Y19+X19 | AA19: =IF($A19>LastT,0,N19-V19-Q19/(1+Policy_Sched!$K19)+Z20/(1+Policy_Sched!$K19))
... A110: =A109+1 | B110: =IF($A110>LastT,0,IF($B$3="exps",B109*(1+InflRate+IF($A110>=T0,$G$3,0)),B109/(1+InflRate))) | C110: =IF($A110>LastT,0,IF(AND($D$3<>0,$A110>=T0,Policy_Sched!$B110<LastAge),1+$D$3*$E$3,1)) | D110: =IF($A110>LastT,0,IF($C$3="up",MIN(Policy_Sched!$E110*(1+IF($A110>=T0,$E$3,0)),$F$3),IF($C$3="down",MAX(Policy_Sched!$E110*(1-IF($A110>=T0,$E$3,0)),Policy_Sched!$E110-$F$3),Policy_Sched!$E110))) | E110: =IF($A110>LastT,0,J109-K109-L109) | F110: =IF($A110>LastT,0,IF($A110=PolicyTerm,E110,0)) | G110: =IF($A110>LastT,0,E110-F110) | H110: =IF($A110=0,PolicyCount,0) | I110: =IF($A110>LastT,0,IF(AND($C$3="mass",$A110=T0),(G110+H110)*$E$3,0)) | J110: =IF($A110>LastT,0,G110+H110-I110) | K110: =IF($A110>LastT,0,J110*Policy_Sched!$C110*Policy_Sched!$D110*C110) | L110: =J110*D110 | M110: =IF($A110>LastT,0,(SizeAnnPrem*ExpsMaintAnnPrem+(SumAssured*ExpsMaintSA+ExpsMaintPol)*B110)*(1+IF($B$3="exps",$E$3,0))) | N110: =SizePremium*J110 | O110: =SumAssured*K110 | P110: =Policy_Sched!$I110*(L110+I110) | Q110: =O110+P110 | R110: =IF($A110=0,SizeExpsAcq0*H110,0) | S110: =IF($A110=0,SizeExpsCommInit0*J110,0) | T110: =Policy_Sched!$J110*J110 | U110: =M110*J110 | V110: =S110+T110+R110+U110 | W110: =IF($A110>LastT,0,N110+W111/(1+Policy_Sched!$K110)) | X110: =IF($A110>LastT,0,(-Q110+X111)/(1+Policy_Sched!$K110)) | Y110: =IF($A110>LastT,0,-V110+Y111/(1+Policy_Sched!$K110)) | Z110: =W110+Y110+X110 | AA110: =IF($A110>LastT,0,N110-V110-Q110/(1+Policy_Sched!$K110)+Z111/(1+Policy_Sched!$K110))

Sheet SCR
B2: Net asset value by scenario — PV of net liability cashflows at t0
B3: Scenario | C3: NAV | D3: Notes / lifelib cell
B4: NetAstValue
B5: Base | C5: =INDEX(PVNCF_Base,T0+1) | D5: NetAstValue() — Projection['base'].PV_NetCashflow(t0)
B6: Mortality stress | C6: =INDEX(PVNCF_Mort,T0+1) | D6: NetAstValue('mort')
B7: Longevity stress | C7: =INDEX(PVNCF_Longev,T0+1) | D7: NetAstValue('longev')
B8: Expense stress | C8: =INDEX(PVNCF_Exps,T0+1) | D8: NetAstValue('exps')
B9: Lapse up | C9: =INDEX(PVNCF_LapseUp,T0+1) | D9: NetAstValue('lapse','up')
B10: Lapse down | C10: =INDEX(PVNCF_LapseDown,T0+1) | D10: NetAstValue('lapse','down')
B11: Mass lapse | C11: =INDEX(PVNCF_LapseMass,T0+1) | D11: NetAstValue('lapse','mass')
B13: Lapse risk by shock
B14: Shock | C14: Charge | D14: Notes / lifelib cell
B15: Up | C15: =MAX(NAV_Base-NAV_LapseUp,0) | D15: LapseRisk(shock)
B16: Down | C16: =MAX(NAV_Base-NAV_LapseDown,0) | D16: LapseRisk(shock)
B17: Mass | C17: =MAX(NAV_Base-NAV_LapseMass,0) | D17: LapseRisk(shock); mass: retail_share = 1 in lifelib, so the non-retail leg vanishes
B19: Life underwriting risk charges
B20: Risk | C20: Life(risk) | D20: Notes / lifelib cell
B21: mort | C21: =MAX(NAV_Base-NAV_Mort,0) | D21: Life('mort')
B22: longev | C22: =MAX(NAV_Base-NAV_Longev,0) | D22: Life('longev')
B23: disab | C23: 0 | D23: Life('disab') = 0 — no lifelib override: the stressed projection is identical to base by construction
B24: lapse | C24: =MAX(LapseUp_Risk,LapseDown_Risk,LapseMass_Risk) | D24: Life('lapse')
B25: exps | C25: =MAX(NAV_Base-NAV_Exps,0) | D25: Life('exps')
B26: rev | C26: 0 | D26: Life('rev') = 0 — no lifelib override
B27: cat | C27: 0 | D27: Life('cat') = 0 — no lifelib override
B29: Correlation matrix (standard formula, lifelib CorrData)
B30: Corr
B31: mort | C31: longev | D31: disab | E31: lapse | F31: exps | G31: rev | H31: cat
A32: mort | B32: 1 | C32: -0.25 | D32: 0.25 | E32: 0 | F32: 0.25 | G32: 0 | H32: 0.25
A33: longev | B33: -0.25 | C33: 1 | D33: 0 | E33: 0.25 | F33: 0.25 | G33: 0.25 | H33: 0
A34: disab | B34: 0.25 | C34: 0 | D34: 1 | E34: 0 | F34: 0.5 | G34: 0 | H34: 0.25
